rtl/pe_serdes.v
// pe_serdes.v — protocol-emulator shared serializer / deserializer.
//
// One shift engine serves every target protocol (UART, SPI, I2C, JTAG, SWD,
// PS/2, CAN, USB-LS, 10BASE-T): firmware works at the word level, this block
// handles bit order and bit counting.
//
// * Bit order is SNAPSHOT at tx_load / rx_start into per-side registers, so
//   cfg_lsb_first may be rewritten by the core at any time without
//   corrupting an in-flight transfer (cfg = 1 UART LSB-first, 0 SPI-style).
// * Transfer length 1..MAXLEN bits, captured on load/start. Lengths above
//   MAXLEN or 0 are out of contract (0 is ignored; >MAXLEN is not clamped).
// * bit_en is the per-bit-cell strobe from the core/DRU timing logic.
//   The RX serial input is expected to be already synchronized (latch-pair
//   dual-edge capture flop, ADR-002); this block is single-edge.
// * tx_ser idles HIGH (suits UART; SPI is CS-gated; I2C/SWD direction is
//   handled by the pin-matrix OE logic, not here).
// * A load/start while busy restarts the transfer (start on the final bit
//   cell drops that bit; start one cycle later still completes the word).
// * Valid RX payload lands in rx_data[rx_len-1:0]: first-received bit sits
//   at [0] when LSB-first, at [rx_len-1] when MSB-first.
// * RX completion is delayed one cycle from the final strobe (rx_busy drops
//   first, rx_valid/rx_data follow) so rx_data can copy rx_shreg directly
//   instead of paying for a variable-shift forward path.
// * Parameter constraint: MAXLEN >= 2 (IDXW would otherwise be 0).

module pe_serdes #(
  parameter int MAXLEN = 32,
  parameter int LENW   = $clog2(MAXLEN + 1),
  parameter int IDXW   = $clog2(MAXLEN)
) (
  input  logic                 clk,
  input  logic                 rst_n,

  input  logic                 cfg_lsb_first,
  input  logic                 bit_en,

  // Transmit side
  input  logic                 tx_load,
  input  logic [MAXLEN-1:0]    tx_data,
  input  logic [LENW-1:0]      tx_len,
  output logic                 tx_ser,
  output logic                 tx_busy,
  output logic                 tx_done,

  // Receive side
  input  logic                 rx_ser,
  input  logic                 rx_start,
  input  logic [LENW-1:0]      rx_len,
  output logic [MAXLEN-1:0]    rx_data,
  output logic                 rx_busy,
  output logic                 rx_valid
);

  // Elaboration guard: MAXLEN=1 would make IDXW=0 (illegal range).
  if (IDXW < 1) $error("pe_serdes: MAXLEN must be >= 2");

  // ---------------- Transmit ----------------
  logic [MAXLEN-1:0] tx_shreg;
  logic [LENW-1:0]   tx_nbits;   // snapshot of tx_len at load
  logic [LENW-1:0]   tx_cnt;     // index of the bit currently on tx_ser
  logic              cfg_lsb_tx; // snapshot of cfg_lsb_first at load

  // Index width only needs $clog2(MAXLEN); LENW expressions truncate cleanly.
  logic [IDXW-1:0] tx_rd_idx;
  assign tx_rd_idx = cfg_lsb_tx
    ? IDXW'(tx_cnt)
    : IDXW'(tx_nbits - 1'b1 - tx_cnt);
  assign tx_ser = tx_busy ? tx_shreg[tx_rd_idx] : 1'b1;

  always_ff @(posedge clk or negedge rst_n) begin
    if (!rst_n) begin
      tx_shreg   <= '0;
      tx_nbits   <= '0;
      tx_cnt     <= '0;
      cfg_lsb_tx <= 1'b0;
      tx_busy    <= 1'b0;
      tx_done    <= 1'b0;
    end else begin
      tx_done <= 1'b0;
      if (tx_load && (|tx_len)) begin
        tx_shreg   <= tx_data;
        tx_nbits   <= tx_len;
        tx_cnt     <= '0;
        cfg_lsb_tx <= cfg_lsb_first;
        tx_busy    <= 1'b1;
      end else if (bit_en && tx_busy) begin
        if (tx_cnt == tx_nbits - 1'b1) begin
          tx_busy <= 1'b0;
          tx_done <= 1'b1;
        end else begin
          tx_cnt <= tx_cnt + 1'b1;
        end
      end
    end
  end

  // ---------------- Receive ----------------
  // Bit-placer (not a shifter): bit k of the transfer is written straight
  // to rx_shreg[pos], with pos counting 0..len-1 when LSB-first and
  // len-1..0 when MSB-first. Payload always ends up in [len-1:0].
  logic [MAXLEN-1:0] rx_shreg;
  logic [LENW-1:0]   rx_nbits;   // snapshot of rx_len at start
  logic [LENW-1:0]   rx_cnt;     // number of bits captured so far
  logic [IDXW-1:0]   rx_pos;     // write position for the incoming bit
  logic              cfg_lsb_rx; // snapshot of cfg_lsb_first at start
  logic              rx_fin;     // final bit seen; complete next cycle

  always_ff @(posedge clk or negedge rst_n) begin
    if (!rst_n) begin
      rx_shreg   <= '0;
      rx_nbits   <= '0;
      rx_cnt     <= '0;
      rx_pos     <= '0;
      cfg_lsb_rx <= 1'b0;
      rx_fin     <= 1'b0;
      rx_data    <= '0;
      rx_busy    <= 1'b0;
      rx_valid   <= 1'b0;
    end else begin
      rx_valid <= 1'b0;
      // Delayed completion: rx_shreg holds the full word by now, so the
      // copy needs no variable-shift forward path. Deliberately ordered
      // before rx_start handling so a start on this exact cycle still
      // delivers the old word (no register conflict: disjoint targets).
      if (rx_fin) begin
        rx_fin   <= 1'b0;
        rx_valid <= 1'b1;
        rx_data  <= rx_shreg;
      end
      if (rx_start && (|rx_len)) begin
        rx_shreg   <= '0;
        rx_nbits   <= rx_len;
        rx_cnt     <= '0;
        rx_pos     <= cfg_lsb_first ? '0 : IDXW'(rx_len - 1'b1);
        cfg_lsb_rx <= cfg_lsb_first;
        rx_busy    <= 1'b1;
      end else if (bit_en && rx_busy) begin
        rx_shreg[rx_pos] <= rx_ser;
        if (rx_cnt == rx_nbits - 1'b1) begin
          rx_busy <= 1'b0;
          rx_fin  <= 1'b1;
        end else begin
          rx_cnt <= rx_cnt + 1'b1;
          rx_pos <= cfg_lsb_rx ? rx_pos + 1'b1 : rx_pos - 1'b1;
        end
      end
    end
  end

endmodule

tb/tb_pe_serdes.v
// tb_pe_serdes.v — self-checking testbench for pe_serdes.
// Covers: UART-style LSB-first TX, SPI-style MSB-first TX (8/16/32b),
// TX+RX loopback both orders, 1-bit and 32-bit boundaries, zero-length
// ignore, busy flags, idle-high tx_ser.
//
// Discipline: inputs driven with BLOCKING assignments after a #1 settle
// past the posedge, so checks always observe settled (post-NBA) values.

`timescale 1ns / 1ps

module tb_pe_serdes;

  localparam int MAXLEN = 32;
  localparam int LENW = $clog2(MAXLEN + 1);

  logic              clk;
  logic              rst_n;
  logic              cfg_lsb_first;
  logic              bit_en;
  logic              tx_load;
  logic [MAXLEN-1:0] tx_data;
  logic [LENW-1:0]   tx_len;
  logic              tx_ser;
  logic              tx_busy;
  logic              tx_done;
  logic              rx_ser;
  logic              rx_start;
  logic [LENW-1:0]   rx_len;
  logic [MAXLEN-1:0] rx_data;
  logic              rx_busy;
  logic              rx_valid;

  pe_serdes #(.MAXLEN(MAXLEN)) dut (.*);

  initial clk = 0;
  always #5 clk = ~clk;  // 100 MHz sim clock; bit_en is the bit strobe

  integer errors = 0;

  task automatic check(input bit cond, input string msg);
    if (!cond) begin
      $display("FAIL: %s @%0t", msg, $time);
      errors++;
    end
  endtask

  // Advance one full bit cell: bit_en high across exactly one posedge,
  // then settle so the DUT outputs can be checked.
  task automatic strobe();
    #1;
    bit_en = 1'b1;
    @(posedge clk);
    #1;
    bit_en = 1'b0;
  endtask

  // Expected TX bit k for given order (only low len bits of data are sent).
  function automatic bit tx_bit(input bit lsb, input [MAXLEN-1:0] d,
                               input int len, input int k);
    return lsb ? d[k] : d[len - 1 - k];
  endfunction

  // Full TX-only transfer check.
  task automatic check_tx(input bit lsb, input [MAXLEN-1:0] d,
                          input int len, input string tag);
    @(posedge clk);
    #1;
    cfg_lsb_first = lsb;
    tx_data = d;
    tx_len = LENW'(len);
    tx_load = 1'b1;
    @(posedge clk);  // DUT captures load here
    #1;
    tx_load = 1'b0;
    check(tx_busy === 1'b1, {tag, ": busy after load"});
    for (int k = 0; k < len; k++) begin
      check(tx_ser === tx_bit(lsb, d, len, k),
            $sformatf("%s: tx bit %0d", tag, k));
      strobe();
    end
    check(tx_done === 1'b1, {tag, ": done pulses"});
    check(tx_busy === 1'b0, {tag, ": busy drops"});
    @(posedge clk);
    #1;
    check(tx_done === 1'b0, {tag, ": done is single-cycle"});
  endtask

  // TX+RX loopback: rx_ser follows tx_ser each cell.
  task automatic check_loopback(input bit lsb, input [MAXLEN-1:0] d,
                                input int len, input string tag);
    logic [MAXLEN-1:0] mask;
    mask = (len == MAXLEN) ? '1 : ((36'b1 << len) - 1'b1);
    @(posedge clk);
    #1;
    cfg_lsb_first = lsb;
    tx_data = d;
    tx_len = LENW'(len);
    rx_len = LENW'(len);
    tx_load = 1'b1;
    rx_start = 1'b1;
    @(posedge clk);  // DUT captures load/start here
    #1;
    tx_load = 1'b0;
    rx_start = 1'b0;
    check(tx_busy && rx_busy, {tag, ": both busy"});
    for (int k = 0; k < len; k++) begin
      rx_ser = tx_ser;  // loopback wire
      strobe();
    end
    check(tx_done === 1'b1, {tag, ": tx done"});
    // RX completion is delayed one cycle past the final strobe (by design).
    @(posedge clk);
    #1;
    check(rx_valid === 1'b1, {tag, ": rx valid"});
    check((rx_data & mask) === (d & mask), {tag, ": payload matches"});
    check(rx_busy === 1'b0, {tag, ": rx busy drops"});
  endtask

  initial begin
    $dumpfile("pe_serdes.vcd");
    $dumpvars(0, tb_pe_serdes);
    // init
    rst_n = 0; cfg_lsb_first = 0; bit_en = 0;
    tx_load = 0; tx_data = 0; tx_len = 0;
    rx_ser = 0; rx_start = 0; rx_len = 0;
    repeat (3) @(posedge clk);
    #1;
    rst_n = 1;
    @(posedge clk);
    #1;

    check(tx_ser === 1'b1, "idle: tx_ser high");
    check(!tx_busy && !rx_busy, "idle: not busy");

    // UART-style: LSB-first 8b
    check_tx(1'b1, 32'hA5, 8, "uart8");
    // SPI-style: MSB-first 8b / 16b / 32b
    check_tx(1'b0, 32'h3C, 8, "spi8");
    check_tx(1'b0, 32'hCAFE, 16, "spi16");
    check_tx(1'b0, 32'hDEADBEEF, 32, "spi32");
    // 1-bit boundary, both orders
    check_tx(1'b1, 32'h1, 1, "lsb1");
    check_tx(1'b0, 32'h80000000, 1, "msb1");
    // odd I2C-ish length, MSB-first 9b (8b + ACK slot shape)
    check_tx(1'b0, 32'h1A5, 9, "i2c9");

    // loopbacks
    check_loopback(1'b1, 32'hA5, 8, "lb-uart8");
    check_loopback(1'b0, 32'hCAFE, 16, "lb-spi16");
    check_loopback(1'b0, 32'hDEADBEEF, 32, "lb-spi32");
    check_loopback(1'b1, 32'h1, 1, "lb-lsb1");

    // zero length ignored
    @(posedge clk);
    #1;
    tx_len = 0; tx_load = 1'b1;
    @(posedge clk);
    #1;
    tx_load = 1'b0;
    check(!tx_busy && !tx_done, "len0: tx ignored");
    @(posedge clk);
    #1;
    rx_len = 0; rx_start = 1'b1;
    @(posedge clk);
    #1;
    rx_start = 1'b0;
    check(!rx_busy && !rx_valid, "len0: rx ignored");

    // restart-while-busy
    @(posedge clk);
    #1;
    cfg_lsb_first = 1'b0; tx_data = 32'hFF; tx_len = 8; tx_load = 1'b1;
    @(posedge clk);
    #1;
    tx_load = 1'b0;
    strobe(); strobe();
    tx_data = 32'h00; tx_load = 1'b1;  // restart mid-transfer
    @(posedge clk);
    #1;
    tx_load = 1'b0;
    check(tx_ser === 1'b0, "restart: new data bit0 out");

    if (errors == 0) $display("PASS: all pe_serdes checks");
    else $display("FAILURES: %0d", errors);
    $finish;
  end

endmodule

pe_serdes.vcd
$date
	Fri Sep 18 10:17:38 2026
$end
$version
	Icarus Verilog
$end
$timescale
	1ps
$end
$scope module tb_pe_serdes $end
$var wire 1 ! tx_ser $end
$var wire 1 " tx_done $end
$var wire 1 # tx_busy $end
$var wire 1 $ rx_valid $end
$var wire 32 % rx_data [31:0] $end
$var wire 1 & rx_busy $end
$var parameter 32 ' LENW $end
$var parameter 32 ( MAXLEN $end
$var reg 1 ) bit_en $end
$var reg 1 * cfg_lsb_first $end
$var reg 1 + clk $end
$var reg 1 , rst_n $end
$var reg 6 - rx_len [5:0] $end
$var reg 1 . rx_ser $end
$var reg 1 / rx_start $end
$var reg 32 0 tx_data [31:0] $end
$var reg 6 1 tx_len [5:0] $end
$var reg 1 2 tx_load $end
$var integer 32 3 errors [31:0] $end
$scope function tx_bit $end
$upscope $end
$scope module dut $end
$var wire 1 ) bit_en $end
$var wire 1 * cfg_lsb_first $end
$var wire 1 + clk $end
$var wire 1 , rst_n $end
$var wire 6 4 rx_len [5:0] $end
$var wire 1 . rx_ser $end
$var wire 1 / rx_start $end
$var wire 32 5 tx_data [31:0] $end
$var wire 6 6 tx_len [5:0] $end
$var wire 1 2 tx_load $end
$var wire 1 ! tx_ser $end
$var wire 5 7 tx_rd_idx [4:0] $end
$var parameter 32 8 IDXW $end
$var parameter 32 9 LENW $end
$var parameter 32 : MAXLEN $end
$var reg 1 ; cfg_lsb_rx $end
$var reg 1 < cfg_lsb_tx $end
$var reg 1 & rx_busy $end
$var reg 6 = rx_cnt [5:0] $end
$var reg 32 > rx_data [31:0] $end
$var reg 1 ? rx_fin $end
$var reg 6 @ rx_nbits [5:0] $end
$var reg 5 A rx_pos [4:0] $end
$var reg 32 B rx_shreg [31:0] $end
$var reg 1 $ rx_valid $end
$var reg 1 # tx_busy $end
$var reg 6 C tx_cnt [5:0] $end
$var reg 1 " tx_done $end
$var reg 6 D tx_nbits [5:0] $end
$var reg 32 E tx_shreg [31:0] $end
$upscope $end
$scope task check $end
$upscope $end
$scope task check_loopback $end
$scope begin $ivl_for_loop1 $end
$upscope $end
$upscope $end
$scope task check_tx $end
$scope begin $ivl_for_loop0 $end
$upscope $end
$upscope $end
$scope task strobe $end
$upscope $end
$upscope $end
$enddefinitions $end
$comment Show the parameter values. $end
$dumpall
b100000 :
b110 9
b101 8
b100000 (
b110 '
$end
#0
$dumpvars
b0 E
b0 D
b0 C
b0 B
b0 A
b0 @
0?
b0 >
b0 =
0<
0;
b11111 7
b0 6
b0 5
b0 4
b0 3
02
b0 1
b0 0
0/
0.
b0 -
0,
0+
0*
0)
0&
b0 %
0$
0#
0"
1!
$end
#5000
1+
#10000
0+
#15000
1+
#20000
0+
#25000
1+
#26000
1,
#30000
0+
#35000
1+
#40000
0+
#45000
1+
#46000
12
b1000 1
b1000 6
b10100101 0
b10100101 5
1*
#50000
0+
#55000
b0 7
1#
1<
b1000 D
b10100101 E
1+
#56000
02
#57000
1)
#60000
0+
#65000
0!
b1 7
b1 C
1+
#66000
0)
#67000
1)
#70000
0+
#75000
1!
b10 7
b10 C
1+
#76000
0)
#77000
1)
#80000
0+
#85000
0!
b11 7
b11 C
1+
#86000
0)
#87000
1)
#90000
0+
#95000
b100 7
b100 C
1+
#96000
0)
#97000
1)
#100000
0+
#105000
1!
b101 7
b101 C
1+
#106000
0)
#107000
1)
#110000
0+
#115000
0!
b110 7
b110 C
1+
#116000
0)
#117000
1)
#120000
0+
#125000
1!
b111 7
b111 C
1+
#126000
0)
#127000
1)
#130000
0+
#135000
1"
0#
1+
#136000
0)
#140000
0+
#145000
0"
1+
#150000
0+
#155000
1+
#156000
12
b111100 0
b111100 5
0*
#160000
0+
#165000
0!
1#
0<
b0 C
b111100 E
1+
#166000
02
#167000
1)
#170000
0+
#175000
b110 7
b1 C
1+
#176000
0)
#177000
1)
#180000
0+
#185000
1!
b101 7
b10 C
1+
#186000
0)
#187000
1)
#190000
0+
#195000
b100 7
b11 C
1+
#196000
0)
#197000
1)
#200000
0+
#205000
b11 7
b100 C
1+
#206000
0)
#207000
1)
#210000
0+
#215000
b10 7
b101 C
1+
#216000
0)
#217000
1)
#220000
0+
#225000
0!
b1 7
b110 C
1+
#226000
0)
#227000
1)
#230000
0+
#235000
b0 7
b111 C
1+
#236000
0)
#237000
1)
#240000
0+
#245000
1!
1"
0#
1+
#246000
0)
#250000
0+
#255000
0"
1+
#260000
0+
#265000
1+
#266000
12
b10000 1
b10000 6
b1100101011111110 0
b1100101011111110 5
#270000
0+
#275000
b1111 7
1!
1#
b0 C
b10000 D
b1100101011111110 E
1+
#276000
02
#277000
1)
#280000
0+
#285000
b1110 7
b1 C
1+
#286000
0)
#287000
1)
#290000
0+
#295000
0!
b1101 7
b10 C
1+
#296000
0)
#297000
1)
#300000
0+
#305000
b1100 7
b11 C
1+
#306000
0)
#307000
1)
#310000
0+
#315000
1!
b1011 7
b100 C
1+
#316000
0)
#317000
1)
#320000
0+
#325000
0!
b1010 7
b101 C
1+
#326000
0)
#327000
1)
#330000
0+
#335000
1!
b1001 7
b110 C
1+
#336000
0)
#337000
1)
#340000
0+
#345000
0!
b1000 7
b111 C
1+
#346000
0)
#347000
1)
#350000
0+
#355000
1!
b111 7
b1000 C
1+
#356000
0)
#357000
1)
#360000
0+
#365000
b110 7
b1001 C
1+
#366000
0)
#367000
1)
#370000
0+
#375000
b101 7
b1010 C
1+
#376000
0)
#377000
1)
#380000
0+
#385000
b100 7
b1011 C
1+
#386000
0)
#387000
1)
#390000
0+
#395000
b11 7
b1100 C
1+
#396000
0)
#397000
1)
#400000
0+
#405000
b10 7
b1101 C
1+
#406000
0)
#407000
1)
#410000
0+
#415000
b1 7
b1110 C
1+
#416000
0)
#417000
1)
#420000
0+
#425000
0!
b0 7
b1111 C
1+
#426000
0)
#427000
1)
#430000
0+
#435000
1!
1"
0#
1+
#436000
0)
#440000
0+
#445000
0"
1+
#450000
0+
#455000
1+
#456000
12
b100000 1
b100000 6
b11011110101011011011111011101111 0
b11011110101011011011111011101111 5
#460000
0+
#465000
b11111 7
1#
b0 C
b100000 D
b11011110101011011011111011101111 E
1+
#466000
02
#467000
1)
#470000
0+
#475000
b11110 7
b1 C
1+
#476000
0)
#477000
1)
#480000
0+
#485000
0!
b11101 7
b10 C
1+
#486000
0)
#487000
1)
#490000
0+
#495000
1!
b11100 7
b11 C
1+
#496000
0)
#497000
1)
#500000
0+
#505000
b11011 7
b100 C
1+
#506000
0)
#507000
1)
#510000
0+
#515000
b11010 7
b101 C
1+
#516000
0)
#517000
1)
#520000
0+
#525000
b11001 7
b110 C
1+
#526000
0)
#527000
1)
#530000
0+
#535000
0!
b11000 7
b111 C
1+
#536000
0)
#537000
1)
#540000
0+
#545000
1!
b10111 7
b1000 C
1+
#546000
0)
#547000
1)
#550000
0+
#555000
0!
b10110 7
b1001 C
1+
#556000
0)
#557000
1)
#560000
0+
#565000
1!
b10101 7
b1010 C
1+
#566000
0)
#567000
1)
#570000
0+
#575000
0!
b10100 7
b1011 C
1+
#576000
0)
#577000
1)
#580000
0+
#585000
1!
b10011 7
b1100 C
1+
#586000
0)
#587000
1)
#590000
0+
#595000
b10010 7
b1101 C
1+
#596000
0)
#597000
1)
#600000
0+
#605000
0!
b10001 7
b1110 C
1+
#606000
0)
#607000
1)
#610000
0+
#615000
1!
b10000 7
b1111 C
1+
#616000
0)
#617000
1)
#620000
0+
#625000
b1111 7
b10000 C
1+
#626000
0)
#627000
1)
#630000
0+
#635000
0!
b1110 7
b10001 C
1+
#636000
0)
#637000
1)
#640000
0+
#645000
1!
b1101 7
b10010 C
1+
#646000
0)
#647000
1)
#650000
0+
#655000
b1100 7
b10011 C
1+
#656000
0)
#657000
1)
#660000
0+
#665000
b1011 7
b10100 C
1+
#666000
0)
#667000
1)
#670000
0+
#675000
b1010 7
b10101 C
1+
#676000
0)
#677000
1)
#680000
0+
#685000
b1001 7
b10110 C
1+
#686000
0)
#687000
1)
#690000
0+
#695000
0!
b1000 7
b10111 C
1+
#696000
0)
#697000
1)
#700000
0+
#705000
1!
b111 7
b11000 C
1+
#706000
0)
#707000
1)
#710000
0+
#715000
b110 7
b11001 C
1+
#716000
0)
#717000
1)
#720000
0+
#725000
b101 7
b11010 C
1+
#726000
0)
#727000
1)
#730000
0+
#735000
0!
b100 7
b11011 C
1+
#736000
0)
#737000
1)
#740000
0+
#745000
1!
b11 7
b11100 C
1+
#746000
0)
#747000
1)
#750000
0+
#755000
b10 7
b11101 C
1+
#756000
0)
#757000
1)
#760000
0+
#765000
b1 7
b11110 C
1+
#766000
0)
#767000
1)
#770000
0+
#775000
b0 7
b11111 C
1+
#776000
0)
#777000
1)
#780000
0+
#785000
1"
0#
1+
#786000
0)
#790000
0+
#795000
0"
1+
#800000
0+
#805000
1+
#806000
12
b1 1
b1 6
b1 0
b1 5
1*
#810000
0+
#815000
1#
1<
b0 C
b1 D
b1 E
1+
#816000
02
#817000
1)
#820000
0+
#825000
1"
0#
1+
#826000
0)
#830000
0+
#835000
0"
1+
#840000
0+
#845000
1+
#846000
12
b10000000000000000000000000000000 0
b10000000000000000000000000000000 5
0*
#850000
0+
#855000
0!
1#
0<
b10000000000000000000000000000000 E
1+
#856000
02
#857000
1)
#860000
0+
#865000
1!
1"
0#
1+
#866000
0)
#870000
0+
#875000
0"
1+
#880000
0+
#885000
1+
#886000
12
b1001 1
b1001 6
b110100101 0
b110100101 5
#890000
0+
#895000
b1000 7
1#
b1001 D
b110100101 E
1+
#896000
02
#897000
1)
#900000
0+
#905000
b111 7
b1 C
1+
#906000
0)
#907000
1)
#910000
0+
#915000
0!
b110 7
b10 C
1+
#916000
0)
#917000
1)
#920000
0+
#925000
1!
b101 7
b11 C
1+
#926000
0)
#927000
1)
#930000
0+
#935000
0!
b100 7
b100 C
1+
#936000
0)
#937000
1)
#940000
0+
#945000
b11 7
b101 C
1+
#946000
0)
#947000
1)
#950000
0+
#955000
1!
b10 7
b110 C
1+
#956000
0)
#957000
1)
#960000
0+
#965000
0!
b1 7
b111 C
1+
#966000
0)
#967000
1)
#970000
0+
#975000
1!
b0 7
b1000 C
1+
#976000
0)
#977000
1)
#980000
0+
#985000
1"
0#
1+
#986000
0)
#990000
0+
#995000
0"
1+
#1000000
0+
#1005000
1+
#1006000
1/
12
b1000 -
b1000 4
b1000 1
b1000 6
b10100101 0
b10100101 5
1*
#1010000
0+
#1015000
1#
1<
b0 C
b1000 D
b10100101 E
1&
1;
b1000 @
1+
#1016000
1.
0/
02
#1017000
1)
#1020000
0+
#1025000
0!
b1 7
b1 A
b1 =
b1 B
b1 C
1+
#1026000
0.
0)
#1027000
1)
#1030000
0+
#1035000
1!
b10 7
b10 C
b10 A
b10 =
1+
#1036000
1.
0)
#1037000
1)
#1040000
0+
#1045000
0!
b11 7
b11 A
b11 =
b101 B
b11 C
1+
#1046000
0.
0)
#1047000
1)
#1050000
0+
#1055000
b100 7
b100 C
b100 A
b100 =
1+
#1056000
0)
#1057000
1)
#1060000
0+
#1065000
1!
b101 7
b101 A
b101 =
b101 C
1+
#1066000
1.
0)
#1067000
1)
#1070000
0+
#1075000
0!
b110 7
b110 C
b110 A
b110 =
b100101 B
1+
#1076000
0.
0)
#1077000
1)
#1080000
0+
#1085000
1!
b111 7
b111 A
b111 =
b111 C
1+
#1086000
1.
0)
#1087000
1)
#1090000
0+
#1095000
1"
0#
1?
0&
b10100101 B
1+
#1096000
b10 3
0)
#1100000
0+
#1105000
b10100101 %
b10100101 >
1$
0?
0"
1+
#1106000
1/
12
b10000 -
b10000 4
b10000 1
b10000 6
b1100101011111110 0
b1100101011111110 5
0*
#1110000
0+
#1115000
b1111 7
1#
0<
b0 C
b10000 D
b1100101011111110 E
1&
0;
b1111 A
b0 =
b10000 @
b0 B
0$
1+
#1116000
0/
02
#1117000
1)
#1120000
0+
#1125000
b1110 7
b1110 A
b1 =
b1000000000000000 B
b1 C
1+
#1126000
0)
#1127000
1)
#1130000
0+
#1135000
0!
b1101 7
b10 C
b1101 A
b10 =
b1100000000000000 B
1+
#1136000
0.
0)
#1137000
1)
#1140000
0+
#1145000
b1100 7
b1100 A
b11 =
b11 C
1+
#1146000
0)
#1147000
1)
#1150000
0+
#1155000
1!
b1011 7
b100 C
b1011 A
b100 =
1+
#1156000
1.
0)
#1157000
1)
#1160000
0+
#1165000
0!
b1010 7
b1010 A
b101 =
b1100100000000000 B
b101 C
1+
#1166000
0.
0)
#1167000
1)
#1170000
0+
#1175000
1!
b1001 7
b110 C
b1001 A
b110 =
1+
#1176000
1.
0)
#1177000
1)
#1180000
0+
#1185000
0!
b1000 7
b1000 A
b111 =
b1100101000000000 B
b111 C
1+
#1186000
0.
0)
#1187000
1)
#1190000
0+
#1195000
1!
b111 7
b1000 C
b111 A
b1000 =
1+
#1196000
1.
0)
#1197000
1)
#1200000
0+
#1205000
b110 7
b110 A
b1001 =
b1100101010000000 B
b1001 C
1+
#1206000
0)
#1207000
1)
#1210000
0+
#1215000
b101 7
b1010 C
b101 A
b1010 =
b1100101011000000 B
1+
#1216000
0)
#1217000
1)
#1220000
0+
#1225000
b100 7
b100 A
b1011 =
b1100101011100000 B
b1011 C
1+
#1226000
0)
#1227000
1)
#1230000
0+
#1235000
b11 7
b1100 C
b11 A
b1100 =
b1100101011110000 B
1+
#1236000
0)
#1237000
1)
#1240000
0+
#1245000
b10 7
b10 A
b1101 =
b1100101011111000 B
b1101 C
1+
#1246000
0)
#1247000
1)
#1250000
0+
#1255000
b1 7
b1110 C
b1 A
b1110 =
b1100101011111100 B
1+
#1256000
0)
#1257000
1)
#1260000
0+
#1265000
0!
b0 7
b0 A
b1111 =
b1100101011111110 B
b1111 C
1+
#1266000
0.
0)
#1267000
1)
#1270000
0+
#1275000
1!
1"
0#
1?
0&
1+
#1276000
b100 3
0)
#1280000
0+
#1285000
b1100101011111110 %
b1100101011111110 >
1$
0?
0"
1+
#1286000
1/
12
b100000 -
b100000 4
b100000 1
b100000 6
b11011110101011011011111011101111 0
b11011110101011011011111011101111 5
#1290000
0+
#1295000
b11111 7
1#
b0 C
b100000 D
b11011110101011011011111011101111 E
1&
b11111 A
b0 =
b100000 @
b0 B
0$
1+
#1296000
1.
0/
02
#1297000
1)
#1300000
0+
#1305000
b11110 7
b11110 A
b1 =
b10000000000000000000000000000000 B
b1 C
1+
#1306000
0)
#1307000
1)
#1310000
0+
#1315000
0!
b11101 7
b10 C
b11101 A
b10 =
b11000000000000000000000000000000 B
1+
#1316000
0.
0)
#1317000
1)
#1320000
0+
#1325000
1!
b11100 7
b11100 A
b11 =
b11 C
1+
#1326000
1.
0)
#1327000
1)
#1330000
0+
#1335000
b11011 7
b100 C
b11011 A
b100 =
b11010000000000000000000000000000 B
1+
#1336000
0)
#1337000
1)
#1340000
0+
#1345000
b11010 7
b11010 A
b101 =
b11011000000000000000000000000000 B
b101 C
1+
#1346000
0)
#1347000
1)
#1350000
0+
#1355000
b11001 7
b110 C
b11001 A
b110 =
b11011100000000000000000000000000 B
1+
#1356000
0)
#1357000
1)
#1360000
0+
#1365000
0!
b11000 7
b11000 A
b111 =
b11011110000000000000000000000000 B
b111 C
1+
#1366000
0.
0)
#1367000
1)
#1370000
0+
#1375000
1!
b10111 7
b1000 C
b10111 A
b1000 =
1+
#1376000
1.
0)
#1377000
1)
#1380000
0+
#1385000
0!
b10110 7
b10110 A
b1001 =
b11011110100000000000000000000000 B
b1001 C
1+
#1386000
0.
0)
#1387000
1)
#1390000
0+
#1395000
1!
b10101 7
b1010 C
b10101 A
b1010 =
1+
#1396000
1.
0)
#1397000
1)
#1400000
0+
#1405000
0!
b10100 7
b10100 A
b1011 =
b11011110101000000000000000000000 B
b1011 C
1+
#1406000
0.
0)
#1407000
1)
#1410000
0+
#1415000
1!
b10011 7
b1100 C
b10011 A
b1100 =
1+
#1416000
1.
0)
#1417000
1)
#1420000
0+
#1425000
b10010 7
b10010 A
b1101 =
b11011110101010000000000000000000 B
b1101 C
1+
#1426000
0)
#1427000
1)
#1430000
0+
#1435000
0!
b10001 7
b1110 C
b10001 A
b1110 =
b11011110101011000000000000000000 B
1+
#1436000
0.
0)
#1437000
1)
#1440000
0+
#1445000
1!
b10000 7
b10000 A
b1111 =
b1111 C
1+
#1446000
1.
0)
#1447000
1)
#1450000
0+
#1455000
b1111 7
b10000 C
b1111 A
b10000 =
b11011110101011010000000000000000 B
1+
#1456000
0)
#1457000
1)
#1460000
0+
#1465000
0!
b1110 7
b1110 A
b10001 =
b11011110101011011000000000000000 B
b10001 C
1+
#1466000
0.
0)
#1467000
1)
#1470000
0+
#1475000
1!
b1101 7
b10010 C
b1101 A
b10010 =
1+
#1476000
1.
0)
#1477000
1)
#1480000
0+
#1485000
b1100 7
b1100 A
b10011 =
b11011110101011011010000000000000 B
b10011 C
1+
#1486000
0)
#1487000
1)
#1490000
0+
#1495000
b1011 7
b10100 C
b1011 A
b10100 =
b11011110101011011011000000000000 B
1+
#1496000
0)
#1497000
1)
#1500000
0+
#1505000
b1010 7
b1010 A
b10101 =
b11011110101011011011100000000000 B
b10101 C
1+
#1506000
0)
#1507000
1)
#1510000
0+
#1515000
b1001 7
b10110 C
b1001 A
b10110 =
b11011110101011011011110000000000 B
1+
#1516000
0)
#1517000
1)
#1520000
0+
#1525000
0!
b1000 7
b1000 A
b10111 =
b11011110101011011011111000000000 B
b10111 C
1+
#1526000
0.
0)
#1527000
1)
#1530000
0+
#1535000
1!
b111 7
b11000 C
b111 A
b11000 =
1+
#1536000
1.
0)
#1537000
1)
#1540000
0+
#1545000
b110 7
b110 A
b11001 =
b11011110101011011011111010000000 B
b11001 C
1+
#1546000
0)
#1547000
1)
#1550000
0+
#1555000
b101 7
b11010 C
b101 A
b11010 =
b11011110101011011011111011000000 B
1+
#1556000
0)
#1557000
1)
#1560000
0+
#1565000
0!
b100 7
b100 A
b11011 =
b11011110101011011011111011100000 B
b11011 C
1+
#1566000
0.
0)
#1567000
1)
#1570000
0+
#1575000
1!
b11 7
b11100 C
b11 A
b11100 =
1+
#1576000
1.
0)
#1577000
1)
#1580000
0+
#1585000
b10 7
b10 A
b11101 =
b11011110101011011011111011101000 B
b11101 C
1+
#1586000
0)
#1587000
1)
#1590000
0+
#1595000
b1 7
b11110 C
b1 A
b11110 =
b11011110101011011011111011101100 B
1+
#1596000
0)
#1597000
1)
#1600000
0+
#1605000
b0 7
b0 A
b11111 =
b11011110101011011011111011101110 B
b11111 C
1+
#1606000
0)
#1607000
1)
#1610000
0+
#1615000
1"
0#
1?
0&
b11011110101011011011111011101111 B
1+
#1616000
b110 3
0)
#1620000
0+
