rtl/pe_serdes.v
// pe_serdes.v — protocol-emulator shared serializer / deserializer.
// Signal meanings: wiki/reference/signal-names.md#pe_serdes
//
// One shift engine serves every target protocol (UART, SPI, I2C, JTAG, SWD,
// PS/2, CAN, USB-LS, 10BASE-T): firmware works at the word level, this block
// handles bit order and bit counting.
//
// * Bit order is SNAPSHOT at tx_load / rx_start into per-side registers, so
//   cfg_lsb_first may be rewritten by the core at any time without
//   corrupting an in-flight transfer (cfg = 1 UART LSB-first, 0 SPI-style).
// * Transfer length 1..MAXLEN bits, captured on load/start. Lengths above
//   MAXLEN or 0 are out of contract (0 is ignored; >MAXLEN is not clamped).
// * bit_en is the per-bit-cell strobe from the core/DRU timing logic.
//   The RX serial input is expected to be already synchronized (latch-pair
//   dual-edge capture flop, ADR-002); this block is single-edge.
// * tx_ser idles HIGH (suits UART; SPI is CS-gated; I2C/SWD direction is
//   handled by the pin-matrix OE logic, not here).
// * A load/start while busy restarts the transfer (start on the final bit
//   cell drops that bit; start one cycle later still completes the word).
// * Valid RX payload lands in rx_data[rx_len-1:0]: first-received bit sits
//   at [0] when LSB-first, at [rx_len-1] when MSB-first.
// * RX completion is delayed one cycle from the final strobe (rx_busy drops
//   first, rx_valid/rx_data follow) so rx_data can copy rx_shreg directly
//   instead of paying for a variable-shift forward path.
// * Parameter constraint: MAXLEN >= 2 (IDXW would otherwise be 0).

module pe_serdes #(
  parameter int MAXLEN = 32,
  parameter int LENW   = $clog2(MAXLEN + 1),
  parameter int IDXW   = $clog2(MAXLEN)
) (
  input  logic                 clk,
  input  logic                 rst_n,

  input  logic                 cfg_lsb_first,
  input  logic                 bit_en,

  // Transmit side
  input  logic                 tx_load,
  input  logic [MAXLEN-1:0]    tx_data,
  input  logic [LENW-1:0]      tx_len,
  output logic                 tx_ser,
  output logic                 tx_busy,
  output logic                 tx_done,

  // Receive side
  input  logic                 rx_ser,
  input  logic                 rx_start,
  input  logic [LENW-1:0]      rx_len,
  output logic [MAXLEN-1:0]    rx_data,
  output logic                 rx_busy,
  output logic                 rx_valid
);

  // Elaboration guard: MAXLEN=1 would make IDXW=0 (illegal range).
  if (IDXW < 1) $error("pe_serdes: MAXLEN must be >= 2");

  // ---------------- Transmit ----------------
  logic [MAXLEN-1:0] tx_shreg;
  logic [LENW-1:0]   tx_nbits;   // snapshot of tx_len at load
  logic [LENW-1:0]   tx_cnt;     // index of the bit currently on tx_ser
  logic              cfg_lsb_tx; // snapshot of cfg_lsb_first at load

  // Index width only needs $clog2(MAXLEN); LENW expressions truncate cleanly.
  logic [IDXW-1:0] tx_rd_idx;
  assign tx_rd_idx = cfg_lsb_tx
    ? IDXW'(tx_cnt)
    : IDXW'(tx_nbits - 1'b1 - tx_cnt);
  assign tx_ser = tx_busy ? tx_shreg[tx_rd_idx] : 1'b1;

  always_ff @(posedge clk or negedge rst_n) begin
    if (!rst_n) begin
      tx_shreg   <= '0;
      tx_nbits   <= '0;
      tx_cnt     <= '0;
      cfg_lsb_tx <= 1'b0;
      tx_busy    <= 1'b0;
      tx_done    <= 1'b0;
    end else begin
      tx_done <= 1'b0;
      if (tx_load && (|tx_len)) begin
        tx_shreg   <= tx_data;
        tx_nbits   <= tx_len;
        tx_cnt     <= '0;
        cfg_lsb_tx <= cfg_lsb_first;
        tx_busy    <= 1'b1;
      end else if (bit_en && tx_busy) begin
        if (tx_cnt == tx_nbits - 1'b1) begin
          tx_busy <= 1'b0;
          tx_done <= 1'b1;
        end else begin
          tx_cnt <= tx_cnt + 1'b1;
        end
      end
    end
  end

  // ---------------- Receive ----------------
  // Bit-placer (not a shifter): bit k of the transfer is written straight
  // to rx_shreg[pos], with pos counting 0..len-1 when LSB-first and
  // len-1..0 when MSB-first. Payload always ends up in [len-1:0].
  logic [MAXLEN-1:0] rx_shreg;
  logic [LENW-1:0]   rx_nbits;   // snapshot of rx_len at start
  logic [LENW-1:0]   rx_cnt;     // number of bits captured so far
  logic [IDXW-1:0]   rx_pos;     // write position for the incoming bit
  logic              cfg_lsb_rx; // snapshot of cfg_lsb_first at start
  logic              rx_fin;     // final bit seen; complete next cycle

  always_ff @(posedge clk or negedge rst_n) begin
    if (!rst_n) begin
      rx_shreg   <= '0;
      rx_nbits   <= '0;
      rx_cnt     <= '0;
      rx_pos     <= '0;
      cfg_lsb_rx <= 1'b0;
      rx_fin     <= 1'b0;
      rx_data    <= '0;
      rx_busy    <= 1'b0;
      rx_valid   <= 1'b0;
    end else begin
      rx_valid <= 1'b0;
      // Delayed completion: rx_shreg holds the full word by now, so the
      // copy needs no variable-shift forward path. Deliberately ordered
      // before rx_start handling so a start on this exact cycle still
      // delivers the old word (no register conflict: disjoint targets).
      if (rx_fin) begin
        rx_fin   <= 1'b0;
        rx_valid <= 1'b1;
        rx_data  <= rx_shreg;
      end
      if (rx_start && (|rx_len)) begin
        rx_shreg   <= '0;
        rx_nbits   <= rx_len;
        rx_cnt     <= '0;
        rx_pos     <= cfg_lsb_first ? '0 : IDXW'(rx_len - 1'b1);
        cfg_lsb_rx <= cfg_lsb_first;
        rx_busy    <= 1'b1;
      end else if (bit_en && rx_busy) begin
        rx_shreg[rx_pos] <= rx_ser;
        if (rx_cnt == rx_nbits - 1'b1) begin
          rx_busy <= 1'b0;
          rx_fin  <= 1'b1;
        end else begin
          rx_cnt <= rx_cnt + 1'b1;
          rx_pos <= cfg_lsb_rx ? rx_pos + 1'b1 : rx_pos - 1'b1;
        end
      end
    end
  end

endmodule

tb/tb_pe_jtag.v
// tb_pe_jtag.v — JTAG Shift-DR scan around pe_serdes.
//
// Minimal TAP controller model (Test-Logic-Reset -> Run-Test/Idle ->
// Select-DR -> Capture-DR -> Shift-DR -> Exit1 -> Update-DR). TDI from
// SERDES tx (MSB-first), TDO into SERDES rx. BSR model: parallel-loads
// a capture pattern, shifts TDI in / MSB out; TDO changes on TCK
// falling edge. Self-checking both directions.

`timescale 1ns / 1ps

module tb_pe_jtag;

  localparam int MAXLEN = 32;
  localparam int LENW = $clog2(MAXLEN + 1);
  localparam int H = 8;   // clk cycles per TCK half period
  localparam int NDR = 16;

  // TAP states (DR column only)
  localparam int TLR = 0, RTI = 1, SELDR = 2, CAPDR = 3,
                 SHDR = 4, EXIT1 = 5, UPD = 6, SELIR = 7;

  logic              clk, rst_n;
  logic              cfg_lsb_first, bit_en;
  logic              tx_load, tx_ser, tx_busy, tx_done;
  logic [MAXLEN-1:0] tx_data;
  logic [LENW-1:0]   tx_len;
  logic              rx_ser, rx_start, rx_busy, rx_valid;
  logic [MAXLEN-1:0] rx_data;
  logic [LENW-1:0]   rx_len;
  logic              tck, tms, tdi, tdo;

  // Sticky event flags for the single-cycle pulses.
  logic tx_done_seen, rx_valid_seen;
  always @(posedge clk or negedge rst_n)
    if (!rst_n) begin tx_done_seen <= 0; rx_valid_seen <= 0; end
    else begin
      if (tx_done)  tx_done_seen  <= 1'b1;
      if (rx_valid) rx_valid_seen <= 1'b1;
    end

  int                state;
  logic [NDR-1:0]    bsr;        // boundary scan register
  logic [NDR-1:0]    cap_pattern;

  pe_serdes #(.MAXLEN(MAXLEN)) dut (.*);

  initial clk = 0;
  always #5 clk = ~clk;

  integer errors = 0;

  task automatic check(input bit c, input string m);
    if (!c) begin $display("FAIL: %s @%0t", m, $time); errors++; end
  endtask

  // One TCK cycle: drive TMS/TDI during the low phase; rising edge
  // advances the TAP (capture/shift actions); falling edge updates TDO.
  task automatic tck_cycle(input bit tms_v, input bit tdi_v);
    #1; tck = 1'b0; tms = tms_v; tdi = tdi_v;
    repeat (H) @(posedge clk); #1;
    tck = 1'b1;  // rising edge: TAP samples
    case (state)
      TLR:   state = tms_v ? TLR  : RTI;
      RTI:   state = tms_v ? SELDR: RTI;
      SELDR: state = tms_v ? SELIR: CAPDR;
      CAPDR: begin
        bsr   = cap_pattern;              // parallel load
        state = tms_v ? EXIT1 : SHDR;
      end
      SHDR: begin
        bsr   = {bsr[NDR-2:0], tdi_v};    // shift TDI in, MSB out
        state = tms_v ? EXIT1 : SHDR;
      end
      EXIT1: state = tms_v ? UPD  : SHDR;
      UPD:   state = tms_v ? SELDR: RTI;
      default: state = TLR;
    endcase
    repeat (H) @(posedge clk); #1;
    tck = 1'b0;  // falling edge: TDO updates
    tdo = (state == SHDR || state == EXIT1) ? bsr[NDR-1] : 1'b0;
  endtask

  // Full scan: walk TAP to Shift-DR, shift a word through, exit to RTI.
  task automatic scan(input [NDR-1:0] w, input [NDR-1:0] pat,
                      output [NDR-1:0] captured);
    cap_pattern = pat;
    // Canonical TAP reset (5x TMS=1 lands in TLR from ANY state), then
    // TLR -> RTI -> Select-DR -> Capture-DR — deterministic per scan.
    repeat (5) tck_cycle(1, 0);
    tck_cycle(0, 0);  // -> RTI
    tck_cycle(1, 0);  // -> Select-DR
    tck_cycle(0, 0);  // -> Capture-DR (loads on its exit edge next)
    // Load SERDES: MSB-first out on TDI, capture TDO
    @(posedge clk); #1;
    cfg_lsb_first = 1'b0;
    tx_data = w; tx_len = NDR; tx_load = 1'b1;
    rx_len = NDR; rx_start = 1'b1;
    tx_done_seen = 1'b0; rx_valid_seen = 1'b0;
    @(posedge clk); #1; tx_load = 1'b0; rx_start = 1'b0;
    // Capture->Shift transition: its falling edge presents TDO = BSR
    // MSB (the capture pattern's first bit). Without this cycle the
    // first latched TDO is stale and only NDR-1 shifts occur.
    tck_cycle(0, 0);
    for (int k = 0; k < NDR; k++) begin
      // Latch TDO BEFORE this cycle's rising edge shifts the BSR.
      rx_ser = tdo;
      tck_cycle(k == NDR-1, tx_ser);  // TMS=1 on the last bit -> Exit1
      bit_en = 1'b1; @(posedge clk); #1; bit_en = 1'b0;
    end
    repeat (2) @(posedge clk); #1;  // delayed RX completion
    check(rx_valid_seen === 1'b1, "jtag: rx_valid");
    check(tx_done_seen === 1'b1, "jtag: tx_done");
    captured = rx_data[NDR-1:0];
    // Exit1-DR -> Update-DR -> Run-Test/Idle
    tck_cycle(1, 0);
    tck_cycle(0, 0);
  endtask

  logic [NDR-1:0] cap;

  initial begin
    $dumpfile("tb_pe_jtag.vcd");
    $dumpvars(0, tb_pe_jtag);
    rst_n = 0; tck = 0; tms = 1; tdi = 0; tdo = 0; bit_en = 0;
    state = TLR; bsr = '0; cap_pattern = '0;
    cfg_lsb_first = 0; tx_load = 0; tx_data = 0; tx_len = 0;
    rx_ser = 0; rx_start = 0; rx_len = 0;
    repeat (3) @(posedge clk); #1; rst_n = 1;
    @(posedge clk); #1;

    scan(16'hBEEF, 16'hA53C, cap);
    check(cap === 16'hA53C, "jtag: captured pattern matches");
    check(bsr === 16'hBEEF, "jtag: bsr fully loaded with scan word");

    scan(16'h0001, 16'h8000, cap);
    check(cap === 16'h8000, "jtag: captured MSB edge pattern");
    check(bsr === 16'h0001, "jtag: bsr LSB edge word");

    scan(16'hFFFF, 16'h0000, cap);
    check(cap === 16'h0000, "jtag: all-zero capture");
    check(bsr === 16'hFFFF, "jtag: all-ones scan");

    if (errors == 0) $display("PASS: tb_pe_jtag");
    else $display("FAILURES: %0d", errors);
    $finish;
  end

endmodule

sim/tb_pe_jtag.vcd
$date
	Fri Sep 18 10:36:06 2026
$end
$version
	Icarus Verilog
$end
$timescale
	1ps
$end
$scope module tb_pe_jtag $end
$var wire 1 ! tx_ser $end
$var wire 1 " tx_done $end
$var wire 1 # tx_busy $end
$var wire 1 $ rx_valid $end
$var wire 32 % rx_data [31:0] $end
$var wire 1 & rx_busy $end
$var parameter 32 ' CAPDR $end
$var parameter 32 ( EXIT1 $end
$var parameter 32 ) H $end
$var parameter 32 * LENW $end
$var parameter 32 + MAXLEN $end
$var parameter 32 , NDR $end
$var parameter 32 - RTI $end
$var parameter 32 . SELDR $end
$var parameter 32 / SELIR $end
$var parameter 32 0 SHDR $end
$var parameter 32 1 TLR $end
$var parameter 32 2 UPD $end
$var reg 1 3 bit_en $end
$var reg 16 4 bsr [15:0] $end
$var reg 16 5 cap [15:0] $end
$var reg 16 6 cap_pattern [15:0] $end
$var reg 1 7 cfg_lsb_first $end
$var reg 1 8 clk $end
$var reg 1 9 rst_n $end
$var reg 6 : rx_len [5:0] $end
$var reg 1 ; rx_ser $end
$var reg 1 < rx_start $end
$var reg 1 = rx_valid_seen $end
$var reg 1 > tck $end
$var reg 1 ? tdi $end
$var reg 1 @ tdo $end
$var reg 1 A tms $end
$var reg 32 B tx_data [31:0] $end
$var reg 1 C tx_done_seen $end
$var reg 6 D tx_len [5:0] $end
$var reg 1 E tx_load $end
$var integer 32 F errors [31:0] $end
$var integer 32 G state [31:0] $end
$scope module dut $end
$var wire 1 3 bit_en $end
$var wire 1 7 cfg_lsb_first $end
$var wire 1 8 clk $end
$var wire 1 9 rst_n $end
$var wire 6 H rx_len [5:0] $end
$var wire 1 ; rx_ser $end
$var wire 1 < rx_start $end
$var wire 32 I tx_data [31:0] $end
$var wire 6 J tx_len [5:0] $end
$var wire 1 E tx_load $end
$var wire 1 ! tx_ser $end
$var wire 5 K tx_rd_idx [4:0] $end
$var parameter 32 L IDXW $end
$var parameter 32 M LENW $end
$var parameter 32 N MAXLEN $end
$var reg 1 O cfg_lsb_rx $end
$var reg 1 P cfg_lsb_tx $end
$var reg 1 & rx_busy $end
$var reg 6 Q rx_cnt [5:0] $end
$var reg 32 R rx_data [31:0] $end
$var reg 1 S rx_fin $end
$var reg 6 T rx_nbits [5:0] $end
$var reg 5 U rx_pos [4:0] $end
$var reg 32 V rx_shreg [31:0] $end
$var reg 1 $ rx_valid $end
$var reg 1 # tx_busy $end
$var reg 6 W tx_cnt [5:0] $end
$var reg 1 " tx_done $end
$var reg 6 X tx_nbits [5:0] $end
$var reg 32 Y tx_shreg [31:0] $end
$upscope $end
$scope task check $end
$upscope $end
$scope task scan $end
$scope begin $ivl_for_loop0 $end
$upscope $end
$upscope $end
$scope task tck_cycle $end
$upscope $end
$upscope $end
$enddefinitions $end
$comment Show the parameter values. $end
$dumpall
b100000 N
b110 M
b101 L
b110 2
b0 1
b100 0
b111 /
b10 .
b1 -
b10000 ,
b100000 +
b110 *
b1000 )
b101 (
b11 '
$end
#0
$dumpvars
b0 Y
b0 X
b0 W
b0 V
b0 U
b0 T
0S
b0 R
b0 Q
0P
0O
b11111 K
b0 J
b0 I
b0 H
b0 G
b0 F
0E
b0 D
0C
b0 B
1A
0@
0?
0>
0=
0<
0;
b0 :
09
08
07
b0 6
bx 5
b0 4
03
0&
b0 %
0$
0#
0"
1!
$end
#5000
18
#10000
08
#15000
18
#20000
08
#25000
18
#26000
19
#30000
08
#35000
18
#36000
b1010010100111100 6
#40000
08
#45000
18
#50000
08
#55000
18
#60000
08
#65000
18
#70000
08
#75000
18
#80000
08
#85000
18
#90000
08
#95000
18
#100000
08
#105000
18
#110000
08
#115000
18
#116000
1>
#120000
08
#125000
18
#130000
08
#135000
18
#140000
08
#145000
18
#150000
08
#155000
18
#160000
08
#165000
18
#170000
08
#175000
18
#180000
08
#185000
18
#190000
08
#195000
18
#196000
0>
#200000
08
#205000
18
#210000
08
#215000
18
#220000
08
#225000
18
#230000
08
#235000
18
#240000
08
#245000
18
#250000
08
#255000
18
#260000
08
#265000
18
#270000
08
#275000
18
#276000
1>
#280000
08
#285000
18
#290000
08
#295000
18
#300000
08
#305000
18
#310000
08
#315000
18
#320000
08
#325000
18
#330000
08
#335000
18
#340000
08
#345000
18
#350000
08
#355000
18
#356000
0>
#360000
08
#365000
18
#370000
08
#375000
18
#380000
08
#385000
18
#390000
08
#395000
18
#400000
08
#405000
18
#410000
08
#415000
18
#420000
08
#425000
18
#430000
08
#435000
18
#436000
1>
#440000
08
#445000
18
#450000
08
#455000
18
#460000
08
#465000
18
#470000
08
#475000
18
#480000
08
#485000
18
#490000
08
#495000
18
#500000
08
#505000
18
#510000
08
#515000
18
#516000
0>
#520000
08
#525000
18
#530000
08
#535000
18
#540000
08
#545000
18
#550000
08
#555000
18
#560000
08
#565000
18
#570000
08
#575000
18
#580000
08
#585000
18
#590000
08
#595000
18
#596000
1>
#600000
08
#605000
18
#610000
08
#615000
18
#620000
08
#625000
18
#630000
08
#635000
18
#640000
08
#645000
18
#650000
08
#655000
18
#660000
08
#665000
18
#670000
08
#675000
18
#676000
0>
#680000
08
#685000
18
#690000
08
#695000
18
#700000
08
#705000
18
#710000
08
#715000
18
#720000
08
#725000
18
#730000
08
#735000
18
#740000
08
#745000
18
#750000
08
#755000
18
#756000
1>
#760000
08
#765000
18
#770000
08
#775000
18
#780000
08
#785000
18
#790000
08
#795000
18
#800000
08
#805000
18
#810000
08
#815000
18
#820000
08
#825000
18
#830000
08
#835000
18
#836000
0>
#837000
0A
#840000
08
#845000
18
#850000
08
#855000
18
#860000
08
#865000
18
#870000
08
#875000
18
#880000
08
#885000
18
#890000
08
#895000
18
#900000
08
#905000
18
#910000
08
#915000
18
#916000
b1 G
1>
#920000
08
#925000
18
#930000
08
#935000
18
#940000
08
#945000
18
#950000
08
#955000
18
#960000
08
#965000
18
#970000
08
#975000
18
#980000
08
#985000
18
#990000
08
#995000
18
#996000
0>
#997000
1A
#1000000
08
#1005000
18
#1010000
08
#1015000
18
#1020000
08
#1025000
18
#1030000
08
#1035000
18
#1040000
08
#1045000
18
#1050000
08
#1055000
18
#1060000
08
#1065000
18
#1070000
08
#1075000
18
#1076000
b10 G
1>
#1080000
08
#1085000
18
#1090000
08
#1095000
18
#1100000
08
#1105000
18
#1110000
08
#1115000
18
#1120000
08
#1125000
18
#1130000
08
#1135000
18
#1140000
08
#1145000
18
#1150000
08
#1155000
18
#1156000
0>
#1157000
0A
#1160000
08
#1165000
18
#1170000
08
#1175000
18
#1180000
08
#1185000
18
#1190000
08
#1195000
18
#1200000
08
#1205000
18
#1210000
08
#1215000
18
#1220000
08
#1225000
18
#1230000
08
#1235000
18
#1236000
b11 G
1>
#1240000
08
#1245000
18
#1250000
08
#1255000
18
#1260000
08
#1265000
18
#1270000
08
#1275000
18
#1280000
08
#1285000
18
#1290000
08
#1295000
18
#1300000
08
#1305000
18
#1310000
08
#1315000
18
#1316000
0>
#1320000
08
#1325000
18
#1326000
1<
b10000 :
b10000 H
1E
b10000 D
b10000 J
b1011111011101111 B
b1011111011101111 I
#1330000
08
#1335000
b1111 K
1!
1#
b10000 X
b1011111011101111 Y
1&
b1111 U
b10000 T
18
#1336000
0<
0E
#1340000
08
#1345000
18
#1350000
08
#1355000
18
#1360000
08
#1365000
18
#1370000
08
#1375000
18
#1380000
08
#1385000
18
#1390000
08
#1395000
18
#1400000
08
#1405000
18
#1410000
08
#1415000
18
#1416000
b100 G
b1010010100111100 4
1>
#1420000
08
#1425000
18
#1430000
08
#1435000
18
#1440000
08
#1445000
18
#1450000
08
#1455000
18
#1460000
08
#1465000
18
#1470000
08
#1475000
18
#1480000
08
#1485000
18
#1490000
08
#1495000
18
#1496000
1;
1@
0>
#1497000
1?
#1500000
08
#1505000
18
#1510000
08
#1515000
18
#1520000
08
#1525000
18
#1530000
08
#1535000
18
#1540000
08
#1545000
18
#1550000
08
#1555000
18
#1560000
08
#1565000
18
#1570000
08
#1575000
18
#1576000
b100101001111001 4
1>
#1580000
08
#1585000
18
#1590000
08
#1595000
18
#1600000
08
#1605000
18
#1610000
08
#1615000
18
#1620000
08
#1625000
18
#1630000
08
#1635000
18
#1640000
08
#1645000
18
#1650000
08
#1655000
18
#1656000
13
0@
0>
#1660000
08
#1665000
0!
b1110 K
b1110 U
b1 Q
b1000000000000000 V
b1 W
18
#1666000
0;
03
#1667000
0?
#1670000
08
#1675000
18
#1680000
08
#1685000
18
#1690000
08
#1695000
18
#1700000
08
#1705000
18
#1710000
08
#1715000
18
#1720000
08
#1725000
18
#1730000
08
#1735000
18
#1740000
08
#1745000
18
#1746000
b1001010011110010 4
1>
#1750000
08
#1755000
18
#1760000
08
#1765000
18
#1770000
08
#1775000
18
#1780000
08
#1785000
18
#1790000
08
#1795000
18
#1800000
08
#1805000
18
#1810000
08
#1815000
18
#1820000
08
#1825000
18
#1826000
13
1@
0>
#1830000
08
#1835000
1!
b1101 K
b10 W
b1101 U
b10 Q
18
#1836000
1;
03
#1837000
1?
#1840000
08
#1845000
18
#1850000
08
#1855000
18
#1860000
08
#1865000
18
#1870000
08
#1875000
18
#1880000
08
#1885000
18
#1890000
08
#1895000
18
#1900000
08
#1905000
18
#1910000
08
#1915000
18
#1916000
b10100111100101 4
1>
#1920000
08
#1925000
18
#1930000
08
#1935000
18
#1940000
08
#1945000
18
#1950000
08
#1955000
18
#1960000
08
#1965000
18
#1970000
08
#1975000
18
#1980000
08
#1985000
18
#1990000
08
#1995000
18
#1996000
13
0@
0>
#2000000
08
#2005000
b1100 K
b1100 U
b11 Q
b1010000000000000 V
b11 W
18
#2006000
0;
03
#2010000
08
#2015000
18
#2020000
08
#2025000
18
#2030000
08
#2035000
18
#2040000
08
#2045000
18
#2050000
08
#2055000
18
#2060000
08
#2065000
18
#2070000
08
#2075000
18
#2080000
08
#2085000
18
#2086000
b101001111001011 4
1>
#2090000
08
#2095000
18
#2100000
08
#2105000
18
#2110000
08
#2115000
18
#2120000
08
#2125000
18
#2130000
08
#2135000
18
#2140000
08
#2145000
18
#2150000
08
#2155000
18
#2160000
08
#2165000
18
#2166000
13
0>
#2170000
08
#2175000
b1011 K
b100 W
b1011 U
b100 Q
18
#2176000
03
#2180000
08
#2185000
18
#2190000
08
#2195000
18
#2200000
08
#2205000
18
#2210000
08
#2215000
18
#2220000
08
#2225000
18
#2230000
08
#2235000
18
#2240000
08
#2245000
18
#2250000
08
#2255000
18
#2256000
b1010011110010111 4
1>
#2260000
08
#2265000
18
#2270000
08
#2275000
18
#2280000
08
#2285000
18
#2290000
08
#2295000
18
#2300000
08
#2305000
18
#2310000
08
#2315000
18
#2320000
08
#2325000
18
#2330000
08
#2335000
18
#2336000
13
1@
0>
#2340000
08
#2345000
b1010 K
b1010 U
b101 Q
b101 W
18
#2346000
1;
03
#2350000
08
#2355000
18
#2360000
08
#2365000
18
#2370000
08
#2375000
18
#2380000
08
#2385000
18
#2390000
08
#2395000
18
#2400000
08
#2405000
18
#2410000
08
#2415000
18
#2420000
08
#2425000
18
#2426000
b100111100101111 4
1>
#2430000
08
#2435000
18
#2440000
08
#2445000
18
#2450000
08
#2455000
18
#2460000
08
#2465000
18
#2470000
08
#2475000
18
#2480000
08
#2485000
18
#2490000
08
#2495000
18
#2500000
08
#2505000
18
#2506000
13
0@
0>
#2510000
08
#2515000
b1001 K
b110 W
b1001 U
b110 Q
b1010010000000000 V
18
#2516000
0;
03
#2520000
08
#2525000
18
#2530000
08
#2535000
18
#2540000
08
#2545000
18
#2550000
08
#2555000
18
#2560000
08
#2565000
18
#2570000
08
#2575000
18
#2580000
08
#2585000
18
#2590000
08
#2595000
18
#2596000
b1001111001011111 4
1>
#2600000
08
#2605000
18
#2610000
08
#2615000
18
#2620000
08
#2625000
18
#2630000
08
#2635000
18
#2640000
08
#2645000
18
#2650000
08
#2655000
18
#2660000
08
#2665000
18
#2670000
08
#2675000
18
#2676000
13
1@
0>
#2680000
08
#2685000
0!
b1000 K
b1000 U
b111 Q
b111 W
18
#2686000
1;
03
#2687000
0?
#2690000
08
#2695000
18
#2700000
08
#2705000
18
#2710000
08
#2715000
18
#2720000
08
#2725000
18
#2730000
08
#2735000
18
#2740000
08
#2745000
18
#2750000
08
#2755000
18
#2760000
08
#2765000
18
#2766000
b11110010111110 4
1>
#2770000
08
#2775000
18
#2780000
08
#2785000
18
#2790000
08
#2795000
18
#2800000
08
#2805000
18
#2810000
08
#2815000
18
#2820000
08
#2825000
18
#2830000
08
#2835000
18
#2840000
08
#2845000
18
#2846000
13
0@
0>
#2850000
08
#2855000
1!
b111 K
b1000 W
b111 U
b1000 Q
b1010010100000000 V
18
#2856000
0;
03
#2857000
1?
#2860000
08
#2865000
18
#2870000
08
#2875000
18
#2880000
08
#2885000
18
#2890000
08
#2895000
18
#2900000
08
#2905000
18
#2910000
08
#2915000
18
#2920000
08
#2925000
18
#2930000
08
#2935000
18
#2936000
b111100101111101 4
1>
#2940000
08
#2945000
18
#2950000
08
#2955000
18
#2960000
08
#2965000
18
#2970000
08
#2975000
18
#2980000
08
#2985000
18
#2990000
08
#2995000
18
#3000000
08
#3005000
18
#3010000
08
#3015000
18
#3016000
13
0>
#3020000
08
#3025000
b110 K
b110 U
b1001 Q
b1001 W
18
#3026000
03
#3030000
08
#3035000
18
#3040000
08
#3045000
18
#3050000
08
#3055000
18
#3060000
08
#3065000
18
#3070000
08
#3075000
18
#3080000
08
#3085000
18
#3090000
08
#3095000
18
#3100000
08
#3105000
18
#3106000
b1111001011111011 4
1>
#3110000
08
#3115000
18
#3120000
08
#3125000
18
#3130000
08
#3135000
18
#3140000
08
#3145000
18
#3150000
08
#3155000
18
#3160000
08
#3165000
18
#3170000
08
#3175000
18
#3180000
08
#3185000
18
#3186000
13
1@
0>
#3190000
08
#3195000
b101 K
b1010 W
b101 U
b1010 Q
18
#3196000
1;
03
#3200000
08
#3205000
18
#3210000
08
#3215000
18
#3220000
08
#3225000
18
#3230000
08
#3235000
18
#3240000
08
#3245000
18
#3250000
08
#3255000
18
#3260000
08
#3265000
18
#3270000
08
#3275000
18
#3276000
b1110010111110111 4
1>
#3280000
08
#3285000
18
#3290000
08
#3295000
18
#3300000
08
#3305000
18
#3310000
08
#3315000
18
#3320000
08
#3325000
18
#3330000
08
#3335000
18
#3340000
08
#3345000
18
#3350000
08
#3355000
18
#3356000
13
0>
#3360000
08
#3365000
0!
b100 K
b100 U
b1011 Q
b1010010100100000 V
b1011 W
18
#3366000
03
#3367000
0?
#3370000
08
#3375000
18
#3380000
08
#3385000
18
#3390000
08
#3395000
18
#3400000
08
#3405000
18
#3410000
08
#3415000
18
#3420000
08
#3425000
18
#3430000
08
#3435000
18
#3440000
08
#3445000
18
#3446000
b1100101111101110 4
1>
#3450000
08
#3455000
18
#3460000
08
#3465000
18
#3470000
08
#3475000
18
#3480000
08
#3485000
18
#3490000
08
#3495000
18
#3500000
08
#3505000
18
#3510000
08
#3515000
18
#3520000
08
#3525000
18
#3526000
13
0>
#3530000
08
#3535000
1!
b11 K
b1100 W
b11 U
b1100 Q
b1010010100110000 V
18
#3536000
03
#3537000
1?
#3540000
08
#3545000
18
#3550000
08
#3555000
18
#3560000
08
#3565000
18
#3570000
08
#3575000
18
#3580000
08
#3585000
18
#3590000
08
#3595000
18
#3600000
08
#3605000
18
#3610000
08
#3615000
18
#3616000
b1001011111011101 4
1>
#3620000
08
#3625000
18
#3630000
08
#3635000
18
#3640000
08
#3645000
18
#3650000
08
#3655000
18
#3660000
08
#3665000
18
#3670000
08
#3675000
18
#3680000
08
#3685000
18
#3690000
08
#3695000
18
#3696000
13
0>
#3700000
08
#3705000
b10 K
b10 U
b1101 Q
b1010010100111000 V
b1101 W
18
#3706000
03
#3710000
08
#3715000
18
#3720000
08
#3725000
18
#3730000
08
#3735000
18
#3740000
08
#3745000
18
#3750000
08
#3755000
18
#3760000
08
#3765000
18
#3770000
08
#3775000
18
#3780000
08
#3785000
18
#3786000
b10111110111011 4
1>
#3790000
08
#3795000
18
#3800000
08
#3805000
18
#3810000
08
#3815000
18
#3820000
08
#3825000
18
#3830000
08
#3835000
18
#3840000
08
#3845000
18
#3850000
08
#3855000
18
#3860000
08
#3865000
18
#3866000
13
0@
0>
#3870000
08
#3875000
b1 K
b1110 W
b1 U
b1110 Q
b1010010100111100 V
18
#3876000
0;
03
#3880000
08
#3885000
18
#3890000
08
#3895000
18
#3900000
08
#3905000
18
#3910000
08
#3915000
18
#3920000
08
#3925000
18
#3930000
08
#3935000
18
#3940000
08
#3945000
18
#3950000
08
#3955000
18
#3956000
b101111101110111 4
1>
#3960000
08
#3965000
18
#3970000
08
#3975000
18
#3980000
08
#3985000
18
#3990000
08
#3995000
18
#4000000
08
#4005000
18
#4010000
08
#4015000
18
#4020000
08
#4025000
18
#4030000
08
#4035000
18
#4036000
13
0>
#4040000
08
#4045000
b0 K
b0 U
b1111 Q
b1111 W
18
#4046000
03
#4047000
1A
#4050000
08
#4055000
18
#4060000
08
#4065000
18
#4070000
08
#4075000
18
#4080000
08
#4085000
18
#4090000
08
#4095000
18
#4100000
08
#4105000
18
#4110000
08
#4115000
18
#4120000
08
#4125000
18
#4126000
b101 G
b1011111011101111 4
1>
#4130000
08
#4135000
18
#4140000
08
#4145000
18
#4150000
08
#4155000
18
#4160000
08
#4165000
18
#4170000
08
#4175000
18
#4180000
08
#4185000
18
#4190000
08
#4195000
18
#4200000
08
#4205000
18
#4206000
13
1@
0>
#4210000
08
#4215000
1"
0#
1S
0&
18
#4216000
03
#4220000
08
#4225000
1C
b1010010100111100 %
b1010010100111100 R
1$
0S
0"
18
#4230000
08
#4235000
0$
1=
18
#4237000
0?
#4240000
08
#4245000
18
#4250000
08
#4255000
18
#4260000
08
#4265000
18
#4270000
08
#4275000
18
#4280000
08
#4285000
18
#4290000
08
#4295000
18
#4300000
08
#4305000
18
#4310000
08
#4315000
18
#4316000
b110 G
1>
#4320000
08
#4325000
18
#4330000
08
#4335000
18
#4340000
08
#4345000
18
#4350000
08
#4355000
18
#4360000
08
#4365000
18
#4370000
08
#4375000
18
#4380000
08
#4385000
18
#4390000
08
#4395000
18
#4396000
0@
0>
#4397000
0A
#4400000
08
#4405000
18
#4410000
08
#4415000
18
#4420000
08
#4425000
18
#4430000
08
#4435000
18
#4440000
08
#4445000
18
#4450000
08
#4455000
18
#4460000
08
#4465000
18
#4470000
08
#4475000
18
#4476000
b1 G
1>
#4480000
08
#4485000
18
#4490000
08
#4495000
18
#4500000
08
#4505000
18
#4510000
08
#4515000
18
#4520000
08
#4525000
18
#4530000
08
#4535000
18
#4540000
08
