rtl/pe_serdes.v
// pe_serdes.v — protocol-emulator shared serializer / deserializer.
// Signal meanings: wiki/reference/signal-names.md#pe_serdes
//
// One shift engine serves every target protocol (UART, SPI, I2C, JTAG, SWD,
// PS/2, CAN, USB-LS, 10BASE-T): firmware works at the word level, this block
// handles bit order and bit counting.
//
// * Bit order is SNAPSHOT at tx_load / rx_start into per-side registers, so
//   cfg_lsb_first may be rewritten by the core at any time without
//   corrupting an in-flight transfer (cfg = 1 UART LSB-first, 0 SPI-style).
// * Transfer length 1..MAXLEN bits, captured on load/start. Lengths above
//   MAXLEN or 0 are out of contract (0 is ignored; >MAXLEN is not clamped).
// * bit_en is the per-bit-cell strobe from the core/DRU timing logic.
//   The RX serial input is expected to be already synchronized (latch-pair
//   dual-edge capture flop, ADR-002); this block is single-edge.
// * tx_ser idles HIGH (suits UART; SPI is CS-gated; I2C/SWD direction is
//   handled by the pin-matrix OE logic, not here).
// * A load/start while busy restarts the transfer (start on the final bit
//   cell drops that bit; start one cycle later still completes the word).
// * Valid RX payload lands in rx_data[rx_len-1:0]: first-received bit sits
//   at [0] when LSB-first, at [rx_len-1] when MSB-first.
// * RX completion is delayed one cycle from the final strobe (rx_busy drops
//   first, rx_valid/rx_data follow) so rx_data can copy rx_shreg directly
//   instead of paying for a variable-shift forward path.
// * Parameter constraint: MAXLEN >= 2 (IDXW would otherwise be 0).

module pe_serdes #(
  parameter int MAXLEN = 32,
  parameter int LENW   = $clog2(MAXLEN + 1),
  parameter int IDXW   = $clog2(MAXLEN)
) (
  input  logic                 clk,
  input  logic                 rst_n,

  input  logic                 cfg_lsb_first,
  input  logic                 bit_en,

  // Transmit side
  input  logic                 tx_load,
  input  logic [MAXLEN-1:0]    tx_data,
  input  logic [LENW-1:0]      tx_len,
  output logic                 tx_ser,
  output logic                 tx_busy,
  output logic                 tx_done,

  // Receive side
  input  logic                 rx_ser,
  input  logic                 rx_start,
  input  logic [LENW-1:0]      rx_len,
  output logic [MAXLEN-1:0]    rx_data,
  output logic                 rx_busy,
  output logic                 rx_valid
);

  // Elaboration guard: MAXLEN=1 would make IDXW=0 (illegal range).
  if (IDXW < 1) $error("pe_serdes: MAXLEN must be >= 2");

  // ---------------- Transmit ----------------
  logic [MAXLEN-1:0] tx_shreg;
  logic [LENW-1:0]   tx_nbits;   // snapshot of tx_len at load
  logic [LENW-1:0]   tx_cnt;     // index of the bit currently on tx_ser
  logic              cfg_lsb_tx; // snapshot of cfg_lsb_first at load

  // Index width only needs $clog2(MAXLEN); LENW expressions truncate cleanly.
  logic [IDXW-1:0] tx_rd_idx;
  assign tx_rd_idx = cfg_lsb_tx
    ? IDXW'(tx_cnt)
    : IDXW'(tx_nbits - 1'b1 - tx_cnt);
  assign tx_ser = tx_busy ? tx_shreg[tx_rd_idx] : 1'b1;

  always_ff @(posedge clk or negedge rst_n) begin
    if (!rst_n) begin
      tx_shreg   <= '0;
      tx_nbits   <= '0;
      tx_cnt     <= '0;
      cfg_lsb_tx <= 1'b0;
      tx_busy    <= 1'b0;
      tx_done    <= 1'b0;
    end else begin
      tx_done <= 1'b0;
      if (tx_load && (|tx_len)) begin
        tx_shreg   <= tx_data;
        tx_nbits   <= tx_len;
        tx_cnt     <= '0;
        cfg_lsb_tx <= cfg_lsb_first;
        tx_busy    <= 1'b1;
      end else if (bit_en && tx_busy) begin
        if (tx_cnt == tx_nbits - 1'b1) begin
          tx_busy <= 1'b0;
          tx_done <= 1'b1;
        end else begin
          tx_cnt <= tx_cnt + 1'b1;
        end
      end
    end
  end

  // ---------------- Receive ----------------
  // Bit-placer (not a shifter): bit k of the transfer is written straight
  // to rx_shreg[pos], with pos counting 0..len-1 when LSB-first and
  // len-1..0 when MSB-first. Payload always ends up in [len-1:0].
  logic [MAXLEN-1:0] rx_shreg;
  logic [LENW-1:0]   rx_nbits;   // snapshot of rx_len at start
  logic [LENW-1:0]   rx_cnt;     // number of bits captured so far
  logic [IDXW-1:0]   rx_pos;     // write position for the incoming bit
  logic              cfg_lsb_rx; // snapshot of cfg_lsb_first at start
  logic              rx_fin;     // final bit seen; complete next cycle

  always_ff @(posedge clk or negedge rst_n) begin
    if (!rst_n) begin
      rx_shreg   <= '0;
      rx_nbits   <= '0;
      rx_cnt     <= '0;
      rx_pos     <= '0;
      cfg_lsb_rx <= 1'b0;
      rx_fin     <= 1'b0;
      rx_data    <= '0;
      rx_busy    <= 1'b0;
      rx_valid   <= 1'b0;
    end else begin
      rx_valid <= 1'b0;
      // Delayed completion: rx_shreg holds the full word by now, so the
      // copy needs no variable-shift forward path. Deliberately ordered
      // before rx_start handling so a start on this exact cycle still
      // delivers the old word (no register conflict: disjoint targets).
      if (rx_fin) begin
        rx_fin   <= 1'b0;
        rx_valid <= 1'b1;
        rx_data  <= rx_shreg;
      end
      if (rx_start && (|rx_len)) begin
        rx_shreg   <= '0;
        rx_nbits   <= rx_len;
        rx_cnt     <= '0;
        rx_pos     <= cfg_lsb_first ? '0 : IDXW'(rx_len - 1'b1);
        cfg_lsb_rx <= cfg_lsb_first;
        rx_busy    <= 1'b1;
      end else if (bit_en && rx_busy) begin
        rx_shreg[rx_pos] <= rx_ser;
        if (rx_cnt == rx_nbits - 1'b1) begin
          rx_busy <= 1'b0;
          rx_fin  <= 1'b1;
        end else begin
          rx_cnt <= rx_cnt + 1'b1;
          rx_pos <= cfg_lsb_rx ? rx_pos + 1'b1 : rx_pos - 1'b1;
        end
      end
    end
  end

endmodule

tb/tb_pe_swd.v
// tb_pe_swd.v — Serial Wire Debug line framing around pe_serdes.
//
// SWDP: request = 8 bits MSB-first; ACK = 3 bits; data = 32 bits
// MSB-first (parity handled by the core, not the SERDES — it rides in
// the 33rd bit position on the wire, outside the SERDES word). One-bit
// turnaround (line released) between fields.

`timescale 1ns / 1ps

module tb_pe_swd;

  localparam int MAXLEN = 32;
  localparam int LENW = $clog2(MAXLEN + 1);
  localparam int H = 8;  // clk cycles per SWD bit

  logic              clk, rst_n;
  logic              cfg_lsb_first, bit_en;
  logic              tx_load, tx_ser, tx_busy, tx_done;
  logic [MAXLEN-1:0] tx_data;
  logic [LENW-1:0]   tx_len;
  logic              rx_ser, rx_start, rx_busy, rx_valid;
  logic [MAXLEN-1:0] rx_data;
  logic [LENW-1:0]   rx_len;
  logic              swdio;
  logic              host_drives;

  pe_serdes #(.MAXLEN(MAXLEN)) dut (.*);

  initial clk = 0;
  always #5 clk = ~clk;

  integer errors = 0;

  // Sticky event flags for the single-cycle pulses.
  logic tx_done_seen, rx_valid_seen;
  always @(posedge clk or negedge rst_n)
    if (!rst_n) begin tx_done_seen <= 0; rx_valid_seen <= 0; end
    else begin
      if (tx_done)  tx_done_seen  <= 1'b1;
      if (rx_valid) rx_valid_seen <= 1'b1;
    end

  task automatic check(input bit c, input string m);
    if (!c) begin $display("FAIL: %s @%0t", m, $time); errors++; end
  endtask

  task automatic bit_cell();
    repeat (H) @(posedge clk); #1;
  endtask

  function automatic bit parity32(input [31:0] d);
    return ^d;
  endfunction

  // Host -> target request (8b MSB-first via SERDES).
  task automatic send_req(input [7:0] req);
    @(posedge clk); #1;
    host_drives = 1'b1;
    cfg_lsb_first = 1'b0;  // SWD: MSB first
    tx_data = req; tx_len = 8; tx_load = 1'b1;
    tx_done_seen = 1'b0;
    @(posedge clk); #1; tx_load = 1'b0;
    for (int k = 0; k < 8; k++) begin
      swdio = tx_ser;
      check(swdio === req[7-k], $sformatf("swd req: bit %0d", k));
      bit_cell();
      bit_en = 1'b1; @(posedge clk); #1; bit_en = 1'b0;
    end
    repeat (2) @(posedge clk); #1;
    check(tx_done_seen === 1'b1, "swd req: tx_done");
    host_drives = 1'b0; swdio = 1'b1; bit_cell();  // turnaround
  endtask

  // Target -> host field (3b ACK or 32b data) via SERDES rx. Parity bit
  // rides on the wire after the word but is not part of the SERDES field.
  task automatic recv_field(input [MAXLEN-1:0] field, input int n,
                            input bit par, input string tag);
    @(posedge clk); #1;
    cfg_lsb_first = 1'b0;
    rx_len = LENW'(n); rx_start = 1'b1;
    rx_valid_seen = 1'b0;
    @(posedge clk); #1; rx_start = 1'b0;
    for (int k = 0; k < n; k++) begin
      swdio = field[n-1-k];  // MSB-first on the wire
      rx_ser = swdio;
      bit_cell();
      bit_en = 1'b1; @(posedge clk); #1; bit_en = 1'b0;
    end
    if (par !== 1'bx) begin  // trailing parity bit on the wire (n==32)
      swdio = par;
      bit_cell();
    end
    repeat (2) @(posedge clk); #1;
    check(rx_valid_seen === 1'b1, {tag, ": rx_valid"});
  endtask

  // Full read transaction: request, ACK=OK(100), 32b data + parity, turn.
  task automatic rd_txn(input [7:0] req, input [31:0] data);
    send_req(req);
    recv_field(3'b100, 3, 1'bx, "swd ack");
    check(rx_data[2:0] === 3'b100, "swd ack: OK code");
    recv_field(data, 32, parity32(data), "swd data");
    check(rx_data[31:0] === data, "swd data: payload");
    host_drives = 1'b0; swdio = 1'b1; bit_cell();  // turnaround
    host_drives = 1'b1;
  endtask

  initial begin
    $dumpfile("tb_pe_swd.vcd");
    $dumpvars(0, tb_pe_swd);
    rst_n = 0; swdio = 1; host_drives = 1; bit_en = 0;
    cfg_lsb_first = 0; tx_load = 0; tx_data = 0; tx_len = 0;
    rx_ser = 0; rx_start = 0; rx_len = 0;
    repeat (3) @(posedge clk); #1; rst_n = 1;
    @(posedge clk); #1;

    rd_txn(8'hA5, 32'h12345678);
    rd_txn(8'h8D, 32'hDEADBEEF);
    rd_txn(8'hA9, 32'h00000000);
    rd_txn(8'hBD, 32'hFFFFFFFF);

    if (errors == 0) $display("PASS: tb_pe_swd");
    else $display("FAILURES: %0d", errors);
    $finish;
  end

endmodule

sim/tb_pe_swd.vcd
$date
	Fri Sep 18 10:36:06 2026
$end
$version
	Icarus Verilog
$end
$timescale
	1ps
$end
$scope module tb_pe_swd $end
$var wire 1 ! tx_ser $end
$var wire 1 " tx_done $end
$var wire 1 # tx_busy $end
$var wire 1 $ rx_valid $end
$var wire 32 % rx_data [31:0] $end
$var wire 1 & rx_busy $end
$var parameter 32 ' H $end
$var parameter 32 ( LENW $end
$var parameter 32 ) MAXLEN $end
$var reg 1 * bit_en $end
$var reg 1 + cfg_lsb_first $end
$var reg 1 , clk $end
$var reg 1 - host_drives $end
$var reg 1 . rst_n $end
$var reg 6 / rx_len [5:0] $end
$var reg 1 0 rx_ser $end
$var reg 1 1 rx_start $end
$var reg 1 2 rx_valid_seen $end
$var reg 1 3 swdio $end
$var reg 32 4 tx_data [31:0] $end
$var reg 1 5 tx_done_seen $end
$var reg 6 6 tx_len [5:0] $end
$var reg 1 7 tx_load $end
$var integer 32 8 errors [31:0] $end
$scope function parity32 $end
$upscope $end
$scope module dut $end
$var wire 1 * bit_en $end
$var wire 1 + cfg_lsb_first $end
$var wire 1 , clk $end
$var wire 1 . rst_n $end
$var wire 6 9 rx_len [5:0] $end
$var wire 1 0 rx_ser $end
$var wire 1 1 rx_start $end
$var wire 32 : tx_data [31:0] $end
$var wire 6 ; tx_len [5:0] $end
$var wire 1 7 tx_load $end
$var wire 1 ! tx_ser $end
$var wire 5 < tx_rd_idx [4:0] $end
$var parameter 32 = IDXW $end
$var parameter 32 > LENW $end
$var parameter 32 ? MAXLEN $end
$var reg 1 @ cfg_lsb_rx $end
$var reg 1 A cfg_lsb_tx $end
$var reg 1 & rx_busy $end
$var reg 6 B rx_cnt [5:0] $end
$var reg 32 C rx_data [31:0] $end
$var reg 1 D rx_fin $end
$var reg 6 E rx_nbits [5:0] $end
$var reg 5 F rx_pos [4:0] $end
$var reg 32 G rx_shreg [31:0] $end
$var reg 1 $ rx_valid $end
$var reg 1 # tx_busy $end
$var reg 6 H tx_cnt [5:0] $end
$var reg 1 " tx_done $end
$var reg 6 I tx_nbits [5:0] $end
$var reg 32 J tx_shreg [31:0] $end
$upscope $end
$scope task bit_cell $end
$upscope $end
$scope task check $end
$upscope $end
$scope task rd_txn $end
$upscope $end
$scope task recv_field $end
$scope begin $ivl_for_loop1 $end
$upscope $end
$upscope $end
$scope task send_req $end
$scope begin $ivl_for_loop0 $end
$upscope $end
$upscope $end
$upscope $end
$enddefinitions $end
$comment Show the parameter values. $end
$dumpall
b100000 ?
b110 >
b101 =
b100000 )
b110 (
b1000 '
$end
#0
$dumpvars
b0 J
b0 I
b0 H
b0 G
b0 F
b0 E
0D
b0 C
b0 B
0A
0@
b11111 <
b0 ;
b0 :
b0 9
b0 8
07
b0 6
05
b0 4
13
02
01
00
b0 /
0.
1-
0,
0+
0*
0&
b0 %
0$
0#
0"
1!
$end
#5000
1,
#10000
0,
#15000
1,
#20000
0,
#25000
1,
#26000
1.
#30000
0,
#35000
1,
#40000
0,
#45000
1,
#46000
17
b1000 6
b1000 ;
b10100101 4
b10100101 :
#50000
0,
#55000
b111 <
1!
1#
b1000 I
b10100101 J
1,
#56000
07
#60000
0,
#65000
1,
#70000
0,
#75000
1,
#80000
0,
#85000
1,
#90000
0,
#95000
1,
#100000
0,
#105000
1,
#110000
0,
#115000
1,
#120000
0,
#125000
1,
#130000
0,
#135000
1,
#136000
1*
#140000
0,
#145000
0!
b110 <
b1 H
1,
#146000
03
0*
#150000
0,
#155000
1,
#160000
0,
#165000
1,
#170000
0,
#175000
1,
#180000
0,
#185000
1,
#190000
0,
#195000
1,
#200000
0,
#205000
1,
#210000
0,
#215000
1,
#220000
0,
#225000
1,
#226000
1*
#230000
0,
#235000
1!
b101 <
b10 H
1,
#236000
13
0*
#240000
0,
#245000
1,
#250000
0,
#255000
1,
#260000
0,
#265000
1,
#270000
0,
#275000
1,
#280000
0,
#285000
1,
#290000
0,
#295000
1,
#300000
0,
#305000
1,
#310000
0,
#315000
1,
#316000
1*
#320000
0,
#325000
0!
b100 <
b11 H
1,
#326000
03
0*
#330000
0,
#335000
1,
#340000
0,
#345000
1,
#350000
0,
#355000
1,
#360000
0,
#365000
1,
#370000
0,
#375000
1,
#380000
0,
#385000
1,
#390000
0,
#395000
1,
#400000
0,
#405000
1,
#406000
1*
#410000
0,
#415000
b11 <
b100 H
1,
#416000
0*
#420000
0,
#425000
1,
#430000
0,
#435000
1,
#440000
0,
#445000
1,
#450000
0,
#455000
1,
#460000
0,
#465000
1,
#470000
0,
#475000
1,
#480000
0,
#485000
1,
#490000
0,
#495000
1,
#496000
1*
#500000
0,
#505000
1!
b10 <
b101 H
1,
#506000
13
0*
#510000
0,
#515000
1,
#520000
0,
#525000
1,
#530000
0,
#535000
1,
#540000
0,
#545000
1,
#550000
0,
#555000
1,
#560000
0,
#565000
1,
#570000
0,
#575000
1,
#580000
0,
#585000
1,
#586000
1*
#590000
0,
#595000
0!
b1 <
b110 H
1,
#596000
03
0*
#600000
0,
#605000
1,
#610000
0,
#615000
1,
#620000
0,
#625000
1,
#630000
0,
#635000
1,
#640000
0,
#645000
1,
#650000
0,
#655000
1,
#660000
0,
#665000
1,
#670000
0,
#675000
1,
#676000
1*
#680000
0,
#685000
1!
b0 <
b111 H
1,
#686000
13
0*
#690000
0,
#695000
1,
#700000
0,
#705000
1,
#710000
0,
#715000
1,
#720000
0,
#725000
1,
#730000
0,
#735000
1,
#740000
0,
#745000
1,
#750000
0,
#755000
1,
#760000
0,
#765000
1,
#766000
1*
#770000
0,
#775000
1"
0#
1,
#776000
0*
#780000
0,
#785000
15
0"
1,
#790000
0,
#795000
1,
#796000
0-
#800000
0,
#805000
1,
#810000
0,
#815000
1,
#820000
0,
#825000
1,
#830000
0,
#835000
1,
#840000
0,
#845000
1,
#850000
0,
#855000
1,
#860000
0,
#865000
1,
#870000
0,
#875000
1,
#880000
0,
#885000
1,
#886000
11
b11 /
b11 9
#890000
0,
#895000
1&
b10 F
b11 E
1,
#896000
10
01
#900000
0,
#905000
1,
#910000
0,
#915000
1,
#920000
0,
#925000
1,
#930000
0,
#935000
1,
#940000
0,
#945000
1,
#950000
0,
#955000
1,
#960000
0,
#965000
1,
#970000
0,
#975000
1,
#976000
1*
#980000
0,
#985000
b1 F
b1 B
b100 G
1,
#986000
00
03
0*
#990000
0,
#995000
1,
#1000000
0,
#1005000
1,
#1010000
0,
#1015000
1,
#1020000
0,
#1025000
1,
#1030000
0,
#1035000
1,
#1040000
0,
#1045000
1,
#1050000
0,
#1055000
1,
#1060000
0,
#1065000
1,
#1066000
1*
#1070000
0,
#1075000
b0 F
b10 B
1,
#1076000
0*
#1080000
0,
#1085000
1,
#1090000
0,
#1095000
1,
#1100000
0,
#1105000
1,
#1110000
0,
#1115000
1,
#1120000
0,
#1125000
1,
#1130000
0,
#1135000
1,
#1140000
0,
#1145000
1,
#1150000
0,
#1155000
1,
#1156000
1*
#1160000
0,
#1165000
1D
0&
1,
#1166000
0*
#1170000
0,
#1175000
b100 %
b100 C
1$
0D
1,
#1180000
0,
#1185000
12
0$
1,
#1190000
0,
#1195000
1,
#1200000
0,
#1205000
1,
#1210000
0,
#1215000
1,
#1220000
0,
#1225000
1,
#1230000
0,
#1235000
1,
#1240000
0,
#1245000
1,
#1250000
0,
#1255000
1,
#1260000
0,
#1265000
1,
#1270000
0,
#1275000
1,
#1276000
02
11
b100000 /
b100000 9
#1280000
0,
#1285000
1&
b11111 F
b0 B
b100000 E
b0 G
1,
#1286000
01
#1290000
0,
#1295000
1,
#1300000
0,
#1305000
1,
#1310000
0,
#1315000
1,
#1320000
0,
#1325000
1,
#1330000
0,
#1335000
1,
#1340000
0,
#1345000
1,
#1350000
0,
#1355000
1,
#1360000
0,
#1365000
1,
#1366000
1*
#1370000
0,
#1375000
b11110 F
b1 B
1,
#1376000
0*
#1380000
0,
#1385000
1,
#1390000
0,
#1395000
1,
#1400000
0,
#1405000
1,
#1410000
0,
#1415000
1,
#1420000
0,
#1425000
1,
#1430000
0,
#1435000
1,
#1440000
0,
#1445000
1,
#1450000
0,
#1455000
1,
#1456000
1*
#1460000
0,
#1465000
b11101 F
b10 B
1,
#1466000
0*
#1470000
0,
#1475000
1,
#1480000
0,
#1485000
1,
#1490000
0,
#1495000
1,
#1500000
0,
#1505000
1,
#1510000
0,
#1515000
1,
#1520000
0,
#1525000
1,
#1530000
0,
#1535000
1,
#1540000
0,
#1545000
1,
#1546000
1*
#1550000
0,
#1555000
b11100 F
b11 B
1,
#1556000
10
13
0*
#1560000
0,
#1565000
1,
#1570000
0,
#1575000
1,
#1580000
0,
#1585000
1,
#1590000
0,
#1595000
1,
#1600000
0,
#1605000
1,
#1610000
0,
#1615000
1,
#1620000
0,
#1625000
1,
#1630000
0,
#1635000
1,
#1636000
1*
#1640000
0,
#1645000
b11011 F
b100 B
b10000000000000000000000000000 G
1,
#1646000
00
03
0*
#1650000
0,
#1655000
1,
#1660000
0,
#1665000
1,
#1670000
0,
#1675000
1,
#1680000
0,
#1685000
1,
#1690000
0,
#1695000
1,
#1700000
0,
#1705000
1,
#1710000
0,
#1715000
1,
#1720000
0,
#1725000
1,
#1726000
1*
#1730000
0,
#1735000
b11010 F
b101 B
1,
#1736000
0*
#1740000
0,
#1745000
1,
#1750000
0,
#1755000
1,
#1760000
0,
#1765000
1,
#1770000
0,
#1775000
1,
#1780000
0,
#1785000
1,
#1790000
0,
#1795000
1,
#1800000
0,
#1805000
1,
#1810000
0,
#1815000
1,
#1816000
1*
#1820000
0,
#1825000
b11001 F
b110 B
1,
#1826000
10
13
0*
#1830000
0,
#1835000
1,
#1840000
0,
#1845000
1,
#1850000
0,
#1855000
1,
#1860000
0,
#1865000
1,
#1870000
0,
#1875000
1,
#1880000
0,
#1885000
1,
#1890000
0,
#1895000
1,
#1900000
0,
#1905000
1,
#1906000
1*
#1910000
0,
#1915000
b11000 F
b111 B
b10010000000000000000000000000 G
1,
#1916000
00
03
0*
#1920000
0,
#1925000
1,
#1930000
0,
#1935000
1,
#1940000
0,
#1945000
1,
#1950000
0,
#1955000
1,
#1960000
0,
#1965000
1,
#1970000
0,
#1975000
1,
#1980000
0,
#1985000
1,
#1990000
0,
#1995000
1,
#1996000
1*
#2000000
0,
#2005000
b10111 F
b1000 B
1,
#2006000
0*
#2010000
0,
#2015000
1,
#2020000
0,
#2025000
1,
#2030000
0,
#2035000
1,
#2040000
0,
#2045000
1,
#2050000
0,
#2055000
1,
#2060000
0,
#2065000
1,
#2070000
0,
#2075000
1,
#2080000
0,
#2085000
1,
#2086000
1*
#2090000
0,
#2095000
b10110 F
b1001 B
1,
#2096000
0*
#2100000
0,
#2105000
1,
#2110000
0,
#2115000
1,
#2120000
0,
#2125000
1,
#2130000
0,
#2135000
1,
#2140000
0,
#2145000
1,
#2150000
0,
#2155000
1,
#2160000
0,
#2165000
1,
#2170000
0,
#2175000
1,
#2176000
1*
#2180000
0,
#2185000
b10101 F
b1010 B
1,
#2186000
10
13
0*
#2190000
0,
#2195000
1,
#2200000
0,
#2205000
1,
#2210000
0,
#2215000
1,
#2220000
0,
#2225000
1,
#2230000
0,
#2235000
1,
#2240000
0,
#2245000
1,
#2250000
0,
#2255000
1,
#2260000
0,
#2265000
1,
#2266000
1*
#2270000
0,
#2275000
b10100 F
b1011 B
b10010001000000000000000000000 G
1,
#2276000
0*
#2280000
0,
#2285000
1,
#2290000
0,
#2295000
1,
#2300000
0,
#2305000
1,
#2310000
0,
#2315000
1,
#2320000
0,
#2325000
1,
#2330000
0,
#2335000
1,
#2340000
0,
#2345000
1,
#2350000
0,
#2355000
1,
#2356000
1*
#2360000
0,
#2365000
b10011 F
b1100 B
b10010001100000000000000000000 G
1,
#2366000
00
03
0*
#2370000
0,
#2375000
1,
#2380000
0,
#2385000
1,
#2390000
0,
#2395000
1,
#2400000
0,
#2405000
1,
#2410000
0,
#2415000
1,
#2420000
0,
#2425000
1,
#2430000
0,
#2435000
1,
#2440000
0,
#2445000
1,
#2446000
1*
#2450000
0,
#2455000
b10010 F
b1101 B
1,
#2456000
10
13
0*
#2460000
0,
#2465000
1,
#2470000
0,
#2475000
1,
#2480000
0,
#2485000
1,
#2490000
0,
#2495000
1,
#2500000
0,
#2505000
1,
#2510000
0,
#2515000
1,
#2520000
0,
#2525000
1,
#2530000
0,
#2535000
1,
#2536000
1*
#2540000
0,
#2545000
b10001 F
b1110 B
b10010001101000000000000000000 G
1,
#2546000
00
03
0*
#2550000
0,
#2555000
1,
#2560000
0,
#2565000
1,
#2570000
0,
#2575000
1,
#2580000
0,
#2585000
1,
#2590000
0,
#2595000
1,
#2600000
0,
#2605000
1,
#2610000
0,
#2615000
1,
#2620000
0,
#2625000
1,
#2626000
1*
#2630000
0,
#2635000
b10000 F
b1111 B
1,
#2636000
0*
#2640000
0,
#2645000
1,
#2650000
0,
#2655000
1,
#2660000
0,
#2665000
1,
#2670000
0,
#2675000
1,
#2680000
0,
#2685000
1,
#2690000
0,
#2695000
1,
#2700000
0,
#2705000
1,
#2710000
0,
#2715000
1,
#2716000
1*
#2720000
0,
#2725000
b1111 F
b10000 B
1,
#2726000
0*
#2730000
0,
#2735000
1,
#2740000
0,
#2745000
1,
#2750000
0,
#2755000
1,
#2760000
0,
#2765000
1,
#2770000
0,
#2775000
1,
#2780000
0,
#2785000
1,
#2790000
0,
#2795000
1,
#2800000
0,
#2805000
1,
#2806000
1*
#2810000
0,
#2815000
b1110 F
b10001 B
1,
#2816000
10
13
0*
#2820000
0,
#2825000
1,
#2830000
0,
#2835000
1,
#2840000
0,
#2845000
1,
#2850000
0,
#2855000
1,
#2860000
0,
#2865000
1,
#2870000
0,
#2875000
1,
#2880000
0,
#2885000
1,
#2890000
0,
#2895000
1,
#2896000
1*
#2900000
0,
#2905000
b1101 F
b10010 B
b10010001101000100000000000000 G
1,
#2906000
00
03
0*
#2910000
0,
#2915000
1,
#2920000
0,
#2925000
1,
#2930000
0,
#2935000
1,
#2940000
0,
#2945000
1,
#2950000
0,
#2955000
1,
#2960000
0,
#2965000
1,
#2970000
0,
#2975000
1,
#2980000
0,
#2985000
1,
#2986000
1*
#2990000
0,
#2995000
b1100 F
b10011 B
1,
#2996000
10
13
0*
#3000000
0,
#3005000
1,
#3010000
0,
#3015000
1,
#3020000
0,
#3025000
1,
#3030000
0,
#3035000
1,
#3040000
0,
#3045000
1,
#3050000
0,
#3055000
1,
#3060000
0,
#3065000
1,
#3070000
0,
#3075000
1,
#3076000
1*
#3080000
0,
#3085000
b1011 F
b10100 B
b10010001101000101000000000000 G
1,
#3086000
00
03
0*
#3090000
0,
#3095000
1,
#3100000
0,
#3105000
1,
#3110000
0,
#3115000
1,
#3120000
0,
#3125000
1,
#3130000
0,
#3135000
1,
#3140000
0,
#3145000
1,
#3150000
0,
#3155000
1,
#3160000
0,
#3165000
1,
#3166000
1*
#3170000
0,
#3175000
b1010 F
b10101 B
1,
#3176000
10
13
0*
#3180000
0,
#3185000
1,
#3190000
0,
#3195000
1,
#3200000
0,
#3205000
1,
#3210000
0,
#3215000
1,
#3220000
0,
#3225000
1,
#3230000
0,
#3235000
1,
#3240000
0,
#3245000
1,
#3250000
0,
#3255000
1,
#3256000
1*
#3260000
0,
#3265000
b1001 F
b10110 B
b10010001101000101010000000000 G
1,
#3266000
0*
#3270000
0,
#3275000
1,
#3280000
0,
#3285000
1,
#3290000
0,
#3295000
1,
#3300000
0,
#3305000
1,
#3310000
0,
#3315000
1,
#3320000
0,
#3325000
1,
#3330000
0,
#3335000
1,
#3340000
0,
#3345000
1,
#3346000
1*
#3350000
0,
#3355000
b1000 F
b10111 B
b10010001101000101011000000000 G
1,
#3356000
00
03
0*
#3360000
0,
#3365000
1,
#3370000
0,
#3375000
1,
#3380000
0,
#3385000
1,
#3390000
0,
#3395000
1,
#3400000
0,
#3405000
1,
#3410000
0,
#3415000
1,
#3420000
0,
#3425000
1,
#3430000
0,
#3435000
1,
#3436000
1*
#3440000
0,
#3445000
b111 F
b11000 B
1,
#3446000
0*
#3450000
0,
#3455000
1,
#3460000
0,
#3465000
1,
#3470000
0,
#3475000
1,
#3480000
0,
#3485000
1,
#3490000
0,
#3495000
1,
#3500000
0,
#3505000
1,
#3510000
0,
#3515000
1,
#3520000
0,
#3525000
1,
#3526000
1*
#3530000
0,
#3535000
b110 F
b11001 B
1,
#3536000
10
13
0*
#3540000
0,
#3545000
1,
#3550000
0,
#3555000
1,
#3560000
0,
#3565000
1,
#3570000
0,
#3575000
1,
#3580000
0,
#3585000
1,
#3590000
0,
#3595000
1,
#3600000
0,
#3605000
1,
#3610000
0,
#3615000
1,
#3616000
1*
#3620000
0,
#3625000
b101 F
b11010 B
b10010001101000101011001000000 G
1,
#3626000
0*
#3630000
0,
#3635000
1,
#3640000
0,
#3645000
1,
#3650000
0,
#3655000
1,
#3660000
0,
#3665000
1,
#3670000
0,
#3675000
1,
#3680000
0,
#3685000
1,
#3690000
0,
#3695000
1,
#3700000
0,
#3705000
1,
#3706000
1*
#3710000
0,
#3715000
b100 F
b11011 B
b10010001101000101011001100000 G
1,
#3716000
0*
#3720000
0,
#3725000
1,
#3730000
0,
#3735000
1,
#3740000
0,
#3745000
1,
#3750000
0,
#3755000
1,
#3760000
0,
#3765000
1,
#3770000
0,
#3775000
1,
#3780000
0,
#3785000
1,
#3790000
0,
#3795000
1,
#3796000
1*
#3800000
0,
#3805000
b11 F
b11100 B
b10010001101000101011001110000 G
1,
#3806000
0*
#3810000
0,
#3815000
1,
#3820000
0,
#3825000
1,
#3830000
0,
#3835000
1,
#3840000
0,
#3845000
1,
#3850000
0,
#3855000
1,
#3860000
0,
#3865000
1,
#3870000
0,
#3875000
1,
#3880000
0,
#3885000
1,
#3886000
1*
#3890000
0,
#3895000
b10 F
b11101 B
b10010001101000101011001111000 G
1,
#3896000
00
03
0*
#3900000
0,
#3905000
1,
#3910000
0,
#3915000
1,
#3920000
0,
#3925000
1,
#3930000
0,
#3935000
1,
#3940000
0,
#3945000
1,
#3950000
0,
#3955000
1,
#3960000
0,
#3965000
1,
#3970000
0,
#3975000
1,
#3976000
1*
#3980000
0,
#3985000
b1 F
b11110 B
1,
#3986000
0*
#3990000
0,
#3995000
1,
#4000000
0,
#4005000
1,
#4010000
0,
#4015000
1,
#4020000
0,
#4025000
1,
#4030000
0,
#4035000
1,
#4040000
0,
#4045000
1,
#4050000
0,
#4055000
1,
#4060000
0,
#4065000
1,
#4066000
1*
#4070000
0,
#4075000
b0 F
b11111 B
1,
#4076000
0*
#4080000
0,
#4085000
1,
#4090000
0,
#4095000
1,
#4100000
0,
#4105000
1,
#4110000
0,
#4115000
1,
#4120000
0,
#4125000
1,
#4130000
0,
#4135000
1,
#4140000
0,
#4145000
1,
#4150000
0,
#4155000
1,
#4156000
1*
#4160000
0,
#4165000
1D
0&
1,
#4166000
13
0*
#4170000
0,
#4175000
b10010001101000101011001111000 %
b10010001101000101011001111000 C
1$
0D
1,
#4180000
0,
#4185000
12
0$
1,
#4190000
0,
#4195000
1,
#4200000
0,
#4205000
1,
#4210000
0,
#4215000
1,
#4220000
0,
#4225000
1,
#4230000
0,
#4235000
1,
#4240000
0,
#4245000
1,
#4250000
0,
#4255000
1,
#4260000
0,
#4265000
1,
#4270000
0,
#4275000
1,
#4280000
0,
#4285000
1,
#4290000
0,
#4295000
1,
#4300000
0,
#4305000
1,
#4310000
0,
#4315000
1,
#4320000
0,
#4325000
1,
#4330000
0,
#4335000
1,
#4340000
0,
#4345000
1,
#4346000
1-
#4350000
0,
#4355000
1,
#4356000
05
17
b10001101 4
b10001101 :
#4360000
0,
#4365000
b111 <
1#
b0 H
b10001101 J
1,
#4366000
07
#4370000
0,
#4375000
1,
#4380000
0,
#4385000
1,
#4390000
0,
#4395000
1,
#4400000
0,
#4405000
1,
#4410000
0,
#4415000
1,
#4420000
0,
#4425000
1,
#4430000
0,
#4435000
1,
#4440000
0,
#4445000
1,
#4446000
1*
#4450000
0,
