rtl/pe_line_codec.v
// pe_line_codec.v — Tier-1 line-code codecs: NRZI, Manchester, bit-stuffing.
//
// These sit between the SM/SERDES (plain NRZ bits, one per bit_en strobe)
// and the pin matrix (wire levels). Each stage is runtime-bypassable so a
// config register can mux any subset into the pipeline (see pe_codec_mux).
//
//   pe_nrzi      TX: raw 0 -> toggle line, raw 1 -> hold (USB-LS).
//                RX: separate sampled-level register — a receiver cannot
//                see the transmitter's state. raw = wire XOR prev_level.
//   pe_manch     TX: half_phase selects which half-cell is driven;
//                raw 0 -> H then L, raw 1 -> L then H (IEEE 802.3).
//                RX: decodes from the two half-cell samples the DRU
//                captured; equal halves = illegal (no mid-bit edge).
//   pe_bitstuff  Insert/drop a complementary bit after run_cfg identical
//                consecutive bits (5 = CAN, 6 = USB). TX emits the real
//                bit first, then consumes a FOLLOWING strobe for the stuff
//                bit (tx_stuffed flags that strobe; raw input is ignored).
//                RX flags the stuffed bit (rx_raw_valid=0) and errors if
//                the bit after a full run is not complementary.
//
// None of these know protocols; config bits and one runtime parameter only.

module pe_nrzi (
  input  logic clk, rst_n,
  input  logic bit_en,
  input  logic bypass,
  input  logic tx_raw,
  output logic tx_wire,
  input  logic rx_wire,
  output logic rx_raw,
  output logic tx_lvl
);
  logic tx_level;   // line level we drive
  logic rx_level;   // last wire level we sampled (receiver state)

  assign tx_lvl  = tx_level;
  assign tx_wire = bypass ? tx_raw : tx_level;
  // Decode: a transition is a 0, no transition is a 1 (XNOR).
  assign rx_raw  = bypass ? rx_wire : ~(rx_wire ^ rx_level);

  always_ff @(posedge clk or negedge rst_n) begin
    if (!rst_n) begin
      tx_level <= 1'b1;   // idle J
      rx_level <= 1'b1;   // idle J
    end else if (bit_en) begin
      if (!bypass && (tx_raw == 1'b0)) tx_level <= ~tx_level;
      rx_level <= rx_wire;
    end
  end
endmodule


module pe_manch (
  input  logic clk, rst_n,
  input  logic bit_en,
  input  logic bypass,
  input  logic half_phase,      // 0 = first half-cell, 1 = second half-cell
  input  logic tx_raw,
  output logic tx_wire,
  input  logic rx_wire,
  input  logic rx_first,        // DRU half-cell sample, first half
  input  logic rx_second,       // DRU half-cell sample, second half
  output logic rx_raw,
  output logic rx_err
);
  // TX: raw 0 -> first half high, second low (H->L mid-bit).
  //     raw 1 -> first half low,  second high (L->H mid-bit).
  assign tx_wire = bypass ? tx_raw : (half_phase ? tx_raw : ~tx_raw);
  // RX: the second-half level carries the bit (a 0's second half is low).
  assign rx_raw  = bypass ? rx_wire : rx_second;
  assign rx_err  = bypass ? 1'b0 : (rx_first == rx_second);
endmodule


module pe_bitstuff (
  input  logic       clk, rst_n,
  input  logic       bit_en,
  input  logic       bypass,
  input  logic       clr,          // frame/SOF boundary: reset run tracking
  input  logic [3:0] run_cfg,      // stuff after this many identical bits
  input  logic       tx_raw,
  output logic       tx_wire,
  output logic       tx_stuffed,   // this strobe emits a stuff bit (raw ignored)
  input  logic       rx_wire,
  output logic       rx_raw,
  output logic       rx_raw_valid, // 0 => this wire bit was a stuff bit
  output logic       rx_err        // bit after a full run not complementary
);
  // ---------------- TX ----------------
  logic [3:0] tx_run;    // identical consecutive raw bits emitted
  logic       tx_lvl;    // value of that run
  logic       tx_pend;   // a stuff bit is owed on the NEXT strobe

  assign tx_stuffed = !bypass && tx_pend;
  assign tx_wire    = bypass ? tx_raw : (tx_pend ? ~tx_lvl : tx_raw);

  always_ff @(posedge clk or negedge rst_n) begin
    if (!rst_n) begin
      tx_run <= 4'd0; tx_lvl <= 1'b0; tx_pend <= 1'b0;
    end else if (clr) begin
      tx_run <= 4'd0; tx_lvl <= 1'b0; tx_pend <= 1'b0;
    end else if (bit_en && !bypass) begin
      if (tx_pend) begin
        tx_pend <= 1'b0;
        tx_run  <= 4'd1;      // the stuff bit opens a new run
        tx_lvl  <= ~tx_lvl;
      end else if (tx_raw == tx_lvl) begin
        if (tx_run == run_cfg - 4'd1) tx_pend <= 1'b1;
        tx_run <= tx_run + 4'd1;
      end else begin
        tx_lvl <= tx_raw;
        tx_run <= 4'd1;
      end
    end
  end

  // ---------------- RX ----------------
  logic [3:0] rx_run;    // identical consecutive WIRE bits seen
  logic       rx_lvl;
  logic       rx_is_stuff;

  assign rx_is_stuff  = !bypass && (rx_run == run_cfg);
  assign rx_raw       = rx_wire;
  assign rx_raw_valid = bypass ? 1'b1 : !rx_is_stuff;

  always_ff @(posedge clk or negedge rst_n) begin
    if (!rst_n) begin
      rx_run <= 4'd0; rx_lvl <= 1'b0; rx_err <= 1'b0;
    end else if (clr) begin
      rx_run <= 4'd0; rx_lvl <= 1'b0; rx_err <= 1'b0;
    end else if (bit_en && !bypass) begin
      rx_err <= 1'b0;
      if (rx_run == run_cfg) begin
        // this wire bit is the stuffed one: it must be complementary
        if (rx_wire == rx_lvl) rx_err <= 1'b1;
        rx_run <= 4'd1;
        rx_lvl <= rx_wire;
      end else if (rx_wire == rx_lvl) begin
        rx_run <= rx_run + 4'd1;
      end else begin
        rx_run <= 4'd1;
        rx_lvl <= rx_wire;
      end
    end
  end
endmodule

tb/tb_pe_line_codec.v
// tb_pe_line_codec.v — self-checking testbenches for the Tier-1 codec trio.
//
// Timing discipline: drive inputs, #1 to settle combinational outputs,
// sample BEFORE the strobe that commits state.
//
// pe_nrzi:     TX and RX as two instances joined by an explicit wire (a
//              real receiver cannot see TX state). Fixed + adversarial
//              (all-ones = no transitions, all-zeros) + random vectors.
// pe_manch:    both half-cells of every bit; decode; error injection.
// pe_bitstuff: run_cfg 5 (CAN) and 6 (USB), TX stuff placement, RX
//              destuff, wire-stream round trip, violation, bypass, clr.

`timescale 1ns / 1ps

// ---------------------------------------------------------------- NRZI
module tb_pe_nrzi;
  logic clk=0, rst_n;
  logic tx_en, tx_bypass, tx_raw, tx_wire, tx_lvl;
  logic rx_en, rx_bypass, rx_wire, rx_raw, rx_lvl_unused;
  logic wire_lvl;

  pe_nrzi u_tx (.clk(clk), .rst_n(rst_n), .bit_en(tx_en), .bypass(tx_bypass),
                .tx_raw(tx_raw), .tx_wire(tx_wire), .rx_wire(1'b0),
                .rx_raw(), .tx_lvl(tx_lvl));
  pe_nrzi u_rx (.clk(clk), .rst_n(rst_n), .bit_en(rx_en), .bypass(rx_bypass),
                .tx_raw(1'b1), .tx_wire(), .rx_wire(rx_wire),
                .rx_raw(rx_raw), .tx_lvl(rx_lvl_unused));

  always #5 clk = ~clk;
  integer errors = 0;
  integer seed = 42;

  task automatic check(input bit c, input string m);
    if (!c) begin $display("FAIL nrzi: %s @%0t", m, $time); errors++; end
  endtask

  task automatic strobe_tx(); tx_en = 1; @(posedge clk); #1; tx_en = 0; endtask
  task automatic strobe_rx(); rx_en = 1; @(posedge clk); #1; rx_en = 0; endtask

  // Send one raw bit: TX strobes (may toggle the line), wire settles,
  // RX decodes against its previous sample, then commits it.
  task automatic send_bit(input bit b, output bit decoded);
    tx_raw = b;
    strobe_tx();
    #1;
    wire_lvl = tx_wire;
    rx_wire  = wire_lvl;
    #1;
    decoded = rx_raw;
    strobe_rx();
  endtask

  initial begin
    $dumpfile("tb_pe_nrzi.vcd"); $dumpvars(0, tb_pe_nrzi);
    rst_n=0; tx_en=0; rx_en=0; tx_bypass=0; rx_bypass=0;
    tx_raw=0; rx_wire=0; wire_lvl=0;
    repeat(3) @(posedge clk); #1; rst_n=1; @(posedge clk); #1;

    // Fixed vector: runs, alternation, and boundaries
    begin
      logic [63:0] v; bit d;
      v = 64'b1011_0001_1111_1110_0101_0101_0000_0000_1100_1100_1010_1010_1110_0001_0110_1001;
      for (int k = 63; k >= 0; k--) begin
        send_bit(v[k], d);
        check(d === v[k], $sformatf("fixed bit %0d", k));
      end
    end

    // Worst case: all ones (no transitions at all)
    begin
      bit d;
      for (int k = 0; k < 24; k++) begin
        send_bit(1'b1, d);
        check(d === 1'b1, $sformatf("ones run bit %0d", k));
      end
    end

    // All zeros (transition every bit)
    begin
      bit d;
      for (int k = 0; k < 24; k++) begin
        send_bit(1'b0, d);
        check(d === 1'b0, $sformatf("zeros run bit %0d", k));
      end
    end

    // Random soak
    for (int t = 0; t < 12; t++) begin
      logic [31:0] rv; bit d;
      rv = $random(seed);
      for (int k = 31; k >= 0; k--) begin
        send_bit(rv[k], d);
        check(d === rv[k], $sformatf("rand %0d bit %0d", t, k));
      end
    end

    // Bypass passthrough
    tx_bypass = 1; rx_bypass = 1;
    tx_raw = 1'b1; #1; check(tx_wire === 1'b1, "bypass tx passthrough");
    rx_wire = 1'b0; #1; check(rx_raw === 1'b0, "bypass rx passthrough");
    tx_bypass = 0; rx_bypass = 0;

    if (errors == 0) $display("PASS: tb_pe_nrzi");
    else $display("FAILURES nrzi: %0d", errors);
    $finish;
  end
endmodule


// ------------------------------------------------------------- Manchester
module tb_pe_manch;
  logic clk=0, rst_n, bit_en, bypass, half_phase, tx_raw, tx_wire;
  logic rx_wire, rx_first, rx_second, rx_raw, rx_err;
  pe_manch dut (.*);
  always #5 clk = ~clk;
  integer errors = 0;

  task automatic check(input bit c, input string m);
    if (!c) begin $display("FAIL manch: %s @%0t", m, $time); errors++; end
  endtask

  // Check both half-cells of one transmitted bit.
  task automatic tx_bit(input bit b);
    half_phase = 1'b0; tx_raw = b; #1;
    check(tx_wire === (b ? 1'b0 : 1'b1), $sformatf("bit %b first half", b));
    half_phase = 1'b1; #1;
    check(tx_wire === (b ? 1'b1 : 1'b0), $sformatf("bit %b second half", b));
  endtask

  initial begin
    $dumpfile("tb_pe_manch.vcd"); $dumpvars(0, tb_pe_manch);
    rst_n=0; bit_en=0; bypass=0; half_phase=0; tx_raw=0;
    rx_wire=0; rx_first=0; rx_second=0;
    repeat(3) @(posedge clk); #1; rst_n=1; @(posedge clk); #1;

    tx_bit(1'b0);   // H then L
    tx_bit(1'b1);   // L then H
    tx_bit(1'b0);

    // RX decode from DRU half-cell samples
    rx_first=1'b1; rx_second=1'b0; #1;
    check(rx_raw === 1'b0, "rx H->L decodes 0");
    check(rx_err === 1'b0, "rx H->L legal");
    rx_first=1'b0; rx_second=1'b1; #1;
    check(rx_raw === 1'b1, "rx L->H decodes 1");
    check(rx_err === 1'b0, "rx L->H legal");
    rx_first=1'b1; rx_second=1'b1; #1;
    check(rx_err === 1'b1, "rx high no-transition flagged");
    rx_first=1'b0; rx_second=1'b0; #1;
    check(rx_err === 1'b1, "rx low no-transition flagged");

    // Bypass
    bypass = 1; tx_raw = 1'b1; rx_wire = 1'b0;
    rx_first=1'b1; rx_second=1'b1; #1;
    check(tx_wire === 1'b1, "bypass tx passthrough");
    check(rx_raw === 1'b0, "bypass rx passthrough");
    check(rx_err === 1'b0, "bypass suppresses error");

    if (errors == 0) $display("PASS: tb_pe_manch");
    else $display("FAILURES manch: %0d", errors);
    $finish;
  end
endmodule


// ----------------------------------------------------------- Bit stuffing
module tb_pe_bitstuff;
  logic clk=0, rst_n, bit_en, bypass, clr;
  logic [3:0] run_cfg;
  logic tx_raw, tx_wire, tx_stuffed;
  logic rx_wire, rx_raw, rx_raw_valid, rx_err;
  pe_bitstuff dut (.*);
  always #5 clk = ~clk;
  integer errors = 0;
  integer seed = 7;

  task automatic check(input bit c, input string m);
    if (!c) begin $display("FAIL stuff: %s @%0t", m, $time); errors++; end
  endtask

  task automatic strobe(); bit_en = 1; @(posedge clk); #1; bit_en = 0; #1; endtask

  // TX one raw bit; returns the wire bit this strobe emitted.
  task automatic tx_bit(input bit b, output bit w);
    tx_raw = b; #1;
    w = tx_wire;
    strobe();
  endtask

  // Emit the owed stuff bit (raw input ignored on this strobe).
  task automatic tx_stuff(output bit w);
    #1;
    check(tx_stuffed === 1'b1, "stuff strobe flagged");
    w = tx_wire;
    strobe();
    #1;
    check(tx_stuffed === 1'b0, "stuff flag clears after the strobe");
  endtask

  initial begin
    $dumpfile("tb_pe_bitstuff.vcd"); $dumpvars(0, tb_pe_bitstuff);
    rst_n=0; bit_en=0; bypass=0; clr=0; run_cfg=4'd5;
    tx_raw=0; rx_wire=0;
    repeat(3) @(posedge clk); #1; rst_n=1; @(posedge clk); #1;

    // ---- CAN (run_cfg=5): five 1s then a stuffed 0 ----
    begin
      bit w;
      clr = 1; @(posedge clk); #1; clr = 0;
      for (int k = 0; k < 5; k++) begin
        tx_bit(1'b1, w);
        check(w === 1'b1, $sformatf("can: data 1 at %0d", k));
      end
      check(tx_stuffed === 1'b1, "can: stuff owed after 5 ones");
      tx_stuff(w);
      check(w === 1'b0, "can: stuff bit complementary (0)");
      tx_bit(1'b0, w);
      check(w === 1'b0, "can: data resumes after stuff");
    end

    // ---- CAN: five 0s ----
    begin
      bit w;
      clr = 1; @(posedge clk); #1; clr = 0;
      for (int k = 0; k < 5; k++) begin
        tx_bit(1'b0, w);
        check(w === 1'b0, $sformatf("can0: data 0 at %0d", k));
      end
      tx_stuff(w);
      check(w === 1'b1, "can0: stuff bit complementary (1)");
    end

    // ---- USB (run_cfg=6): six 1s then a stuffed 0 ----
    begin
      bit w;
      run_cfg = 4'd6;
      clr = 1; @(posedge clk); #1; clr = 0;
      for (int k = 0; k < 6; k++) begin
        tx_bit(1'b1, w);
        check(w === 1'b1, $sformatf("usb: data 1 at %0d", k));
      end
      check(tx_stuffed === 1'b1, "usb: stuff owed after 6 ones");
      tx_stuff(w);
      check(w === 1'b0, "usb: stuff bit complementary");
    end

    // ---- Wire-stream round trip: TX all-ones (max stuffing), replay RX ----
    begin
      bit w; int nwire; logic wbits [128]; int nraw; logic rec [128];
      run_cfg = 4'd5;
      clr = 1; @(posedge clk); #1; clr = 0;
      nwire = 0;
      for (int k = 0; k < 64; k++) begin
        tx_bit(1'b1, w);
        wbits[nwire] = w; nwire++;
        if (tx_stuffed) begin
          tx_stuff(w);
          wbits[nwire] = w; nwire++;
        end
      end
      check(nwire > 64, "stuffing inserted extra wire bits");

      clr = 1; @(posedge clk); #1; clr = 0;
      nraw = 0;
      for (int i = 0; i < nwire; i++) begin
        rx_wire = wbits[i]; #1;
        if (rx_raw_valid) begin rec[nraw] = rx_raw; nraw++; end
        strobe();
      end
      check(nraw == 64, $sformatf("rx recovered 64 raw bits (got %0d)", nraw));
      for (int i = 0; i < 64; i++)
        check(rec[i] === 1'b1, $sformatf("rx recovered bit %0d = 1", i));
    end

    // ---- RX violation: bit after a full run is not complementary ----
    begin
      run_cfg = 4'd5;
      clr = 1; @(posedge clk); #1; clr = 0;
      for (int k = 0; k < 5; k++) begin
        rx_wire = 1'b1; #1; strobe();
      end
      rx_wire = 1'b1; #1;   // illegal: should have been a stuffed 0
      check(rx_raw_valid === 1'b0, "violating bit occupies the stuff slot");
      strobe(); #1;
      check(rx_err === 1'b1, "violation detected");
    end

    // ---- bypass ----
    begin
      bypass = 1; tx_raw = 1'b1; rx_wire = 1'b0; #1;
      check(tx_wire === 1'b1, "bypass tx passthrough");
      check(tx_stuffed === 1'b0, "bypass: no stuff");
      check(rx_raw_valid === 1'b1, "bypass: rx always valid");
      bypass = 0;
    end

    if (errors == 0) $display("PASS: tb_pe_bitstuff");
    else $display("FAILURES stuff: %0d", errors);
    $finish;
  end
endmodule

sim/tb_pe_manch.vcd
$date
	Fri Sep 18 20:43:40 2026
$end
$version
	Icarus Verilog
$end
$timescale
	1ps
$end
$scope module tb_pe_manch $end
$var wire 1 ! tx_wire $end
$var wire 1 " rx_raw $end
$var wire 1 # rx_err $end
$var reg 1 $ bit_en $end
$var reg 1 % bypass $end
$var reg 1 & clk $end
$var reg 1 ' half_phase $end
$var reg 1 ( rst_n $end
$var reg 1 ) rx_first $end
$var reg 1 * rx_second $end
$var reg 1 + rx_wire $end
$var reg 1 , tx_raw $end
$var integer 32 - errors [31:0] $end
$scope module dut $end
$var wire 1 $ bit_en $end
$var wire 1 % bypass $end
$var wire 1 & clk $end
$var wire 1 ' half_phase $end
$var wire 1 ( rst_n $end
$var wire 1 ) rx_first $end
$var wire 1 * rx_second $end
$var wire 1 + rx_wire $end
$var wire 1 , tx_raw $end
$var wire 1 ! tx_wire $end
$var wire 1 " rx_raw $end
$var wire 1 # rx_err $end
$upscope $end
$scope task check $end
$upscope $end
$scope task tx_bit $end
$upscope $end
$upscope $end
$enddefinitions $end
$comment Show the parameter values. $end
$dumpall
$end
#0
$dumpvars
b0 -
0,
0+
0*
0)
0(
0'
0&
0%
0$
1#
0"
1!
$end
#5000
1&
#10000
0&
#15000
1&
#20000
0&
#25000
1&
#26000
1(
#30000
0&
#35000
1&
#37000
0!
1'
#38000
0!
1,
0'
#39000
1!
1'
#40000
1!
0,
0'
0&
#41000
0!
1'
#42000
0#
1)
#43000
1"
1*
0)
#44000
1#
1)
#45000
0"
0*
0)
1&
#46000
1!
0#
1*
1)
1,
1%
