rtl/pe_line_codec.v
// pe_line_codec.v — Tier-1 line-code codecs: NRZI, Manchester, bit-stuffing.
//
// These sit between the SM/SERDES (plain NRZ bits, one per bit_en strobe)
// and the pin matrix (wire levels). Each stage is runtime-bypassable so a
// config register can mux any subset into the pipeline (see pe_codec_mux).
//
//   pe_nrzi      TX: raw 0 -> toggle line, raw 1 -> hold (USB-LS).
//                RX: separate sampled-level register — a receiver cannot
//                see the transmitter's state. raw = wire XOR prev_level.
//   pe_manch     TX: half_phase selects which half-cell is driven;
//                raw 0 -> H then L, raw 1 -> L then H (IEEE 802.3).
//                RX: decodes from the two half-cell samples the DRU
//                captured; equal halves = illegal (no mid-bit edge).
//   pe_bitstuff  Insert/drop a complementary bit after run_cfg identical
//                consecutive bits (5 = CAN, 6 = USB). TX emits the real
//                bit first, then consumes a FOLLOWING strobe for the stuff
//                bit (tx_stuffed flags that strobe; raw input is ignored).
//                RX flags the stuffed bit (rx_raw_valid=0) and errors if
//                the bit after a full run is not complementary.
//
// None of these know protocols; config bits and one runtime parameter only.

module pe_nrzi (
  input  logic clk, rst_n,
  input  logic bit_en,
  input  logic bypass,
  input  logic tx_raw,
  output logic tx_wire,
  input  logic rx_wire,
  output logic rx_raw,
  output logic tx_lvl
);
  logic tx_level;   // line level we drive
  logic rx_level;   // last wire level we sampled (receiver state)

  assign tx_lvl  = tx_level;
  assign tx_wire = bypass ? tx_raw : tx_level;
  // Decode: a transition is a 0, no transition is a 1 (XNOR).
  assign rx_raw  = bypass ? rx_wire : ~(rx_wire ^ rx_level);

  always_ff @(posedge clk or negedge rst_n) begin
    if (!rst_n) begin
      tx_level <= 1'b1;   // idle J
      rx_level <= 1'b1;   // idle J
    end else if (bit_en) begin
      if (!bypass && (tx_raw == 1'b0)) tx_level <= ~tx_level;
      rx_level <= rx_wire;
    end
  end
endmodule


module pe_manch (
  input  logic clk, rst_n,
  input  logic bit_en,
  input  logic bypass,
  input  logic half_phase,      // 0 = first half-cell, 1 = second half-cell
  input  logic tx_raw,
  output logic tx_wire,
  input  logic rx_wire,
  input  logic rx_first,        // DRU half-cell sample, first half
  input  logic rx_second,       // DRU half-cell sample, second half
  output logic rx_raw,
  output logic rx_err
);
  // TX: raw 0 -> first half high, second low (H->L mid-bit).
  //     raw 1 -> first half low,  second high (L->H mid-bit).
  assign tx_wire = bypass ? tx_raw : (half_phase ? tx_raw : ~tx_raw);
  // RX: the second-half level carries the bit (a 0's second half is low).
  assign rx_raw  = bypass ? rx_wire : rx_second;
  assign rx_err  = bypass ? 1'b0 : (rx_first == rx_second);
endmodule


module pe_bitstuff (
  input  logic       clk, rst_n,
  input  logic       bit_en,
  input  logic       bypass,
  input  logic       clr,          // frame/SOF boundary: reset run tracking
  input  logic [3:0] run_cfg,      // stuff after this many identical bits
  input  logic       tx_raw,
  output logic       tx_wire,
  output logic       tx_stuffed,   // this strobe emits a stuff bit (raw ignored)
  input  logic       rx_wire,
  output logic       rx_raw,
  output logic       rx_raw_valid, // 0 => this wire bit was a stuff bit
  output logic       rx_err        // bit after a full run not complementary
);
  // ---------------- TX ----------------
  logic [3:0] tx_run;    // identical consecutive raw bits emitted
  logic       tx_lvl;    // value of that run
  logic       tx_pend;   // a stuff bit is owed on the NEXT strobe

  assign tx_stuffed = !bypass && tx_pend;
  assign tx_wire    = bypass ? tx_raw : (tx_pend ? ~tx_lvl : tx_raw);

  always_ff @(posedge clk or negedge rst_n) begin
    if (!rst_n) begin
      tx_run <= 4'd0; tx_lvl <= 1'b0; tx_pend <= 1'b0;
    end else if (clr) begin
      tx_run <= 4'd0; tx_lvl <= 1'b0; tx_pend <= 1'b0;
    end else if (bit_en && !bypass) begin
      if (tx_pend) begin
        tx_pend <= 1'b0;
        tx_run  <= 4'd1;      // the stuff bit opens a new run
        tx_lvl  <= ~tx_lvl;
      end else if (tx_raw == tx_lvl) begin
        if (tx_run == run_cfg - 4'd1) tx_pend <= 1'b1;
        tx_run <= tx_run + 4'd1;
      end else begin
        tx_lvl <= tx_raw;
        tx_run <= 4'd1;
      end
    end
  end

  // ---------------- RX ----------------
  logic [3:0] rx_run;    // identical consecutive WIRE bits seen
  logic       rx_lvl;
  logic       rx_is_stuff;

  assign rx_is_stuff  = !bypass && (rx_run == run_cfg);
  assign rx_raw       = rx_wire;
  assign rx_raw_valid = bypass ? 1'b1 : !rx_is_stuff;

  always_ff @(posedge clk or negedge rst_n) begin
    if (!rst_n) begin
      rx_run <= 4'd0; rx_lvl <= 1'b0; rx_err <= 1'b0;
    end else if (clr) begin
      rx_run <= 4'd0; rx_lvl <= 1'b0; rx_err <= 1'b0;
    end else if (bit_en && !bypass) begin
      rx_err <= 1'b0;
      if (rx_run == run_cfg) begin
        // this wire bit is the stuffed one: it must be complementary
        if (rx_wire == rx_lvl) rx_err <= 1'b1;
        rx_run <= 4'd1;
        rx_lvl <= rx_wire;
      end else if (rx_wire == rx_lvl) begin
        rx_run <= rx_run + 4'd1;
      end else begin
        rx_run <= 4'd1;
        rx_lvl <= rx_wire;
      end
    end
  end
endmodule

rtl/pe_codec_mux.v
// pe_codec_mux.v — config-driven codec pipeline (SERDES <-> pin matrix).
//
// Composes the Tier-1 codecs into one pipeline. Every stage is
// runtime-bypassable from the cfg register, so firmware muxes any subset
// in or out:
//
//   cfg[0]    stuff_en     bit stuffing/unstuffing
//   cfg[1]    nrzi_en      NRZI line coding (USB-LS)
//   cfg[2]    manch_en     Manchester line coding (10BASE-T)
//   cfg[3]    half_phase   Manchester half-cell select (SM/timing driven)
//   cfg[7:4]  run_cfg      stuff run length (0 => default 5; CAN 5, USB 6)
//
// TX order:  tx_bit -> [stuff] -> [nrzi] -> [manch] -> tx_wire
// RX order:  rx_wire -> [manch] -> [nrzi] -> [stuff] -> rx_bit
//
// The ORDER is fixed (it is the physically correct composition for these
// codes: stuffing is defined in the raw/encoded domain, line coding last).
// "Arbitrary muxing" therefore means any SUBSET of stages, which covers
// every protocol in the target set. A protocol needing a different order
// needs a different pipeline, not a config bit.
//
// Note: the active codec sets the strobe cadence the timing block must
// supply — one strobe per raw bit for plain/NRZI/stuffed modes, one per
// HALF-cell (with half_phase toggling) for Manchester.

module pe_codec_mux (
  input  logic       clk, rst_n,
  input  logic [7:0] cfg,
  input  logic       bit_en,
  input  logic       clr,
  // TX: from SM/SERDES
  input  logic       tx_bit,
  output logic       tx_wire,
  output logic       tx_stuffed,
  // RX: from pin matrix / DRU
  input  logic       rx_wire,
  input  logic       rx_first,
  input  logic       rx_second,
  output logic       rx_bit,
  output logic       rx_bit_valid,
  output logic       rx_err
);
  logic       stuff_en, nrzi_en, manch_en;
  logic [3:0] run_cfg;

  assign stuff_en = cfg[0];
  assign nrzi_en  = cfg[1];
  assign manch_en = cfg[2];
  assign run_cfg  = (cfg[7:4] == 4'd0) ? 4'd5 : cfg[7:4];

  // ---- TX cascade: stuff -> nrzi -> manch ----
  logic s_wire, n_wire, m_rx_out, n_rx_out, st_rx_err, m_rx_err;

  pe_bitstuff u_stuff (
    .clk(clk), .rst_n(rst_n), .bit_en(bit_en),
    .bypass(~stuff_en), .clr(clr), .run_cfg(run_cfg),
    .tx_raw(tx_bit), .tx_wire(s_wire), .tx_stuffed(tx_stuffed),
    .rx_wire(n_rx_out), .rx_raw(rx_bit), .rx_raw_valid(rx_bit_valid),
    .rx_err(st_rx_err)
  );

  pe_nrzi u_nrzi (
    .clk(clk), .rst_n(rst_n), .bit_en(bit_en), .bypass(~nrzi_en),
    .tx_raw(s_wire), .tx_wire(n_wire), .tx_lvl(),
    .rx_wire(m_rx_out), .rx_raw(n_rx_out)
  );

  pe_manch u_manch (
    .clk(clk), .rst_n(rst_n), .bit_en(bit_en), .bypass(~manch_en),
    .half_phase(cfg[3]),
    .tx_raw(n_wire), .tx_wire(tx_wire),
    .rx_wire(rx_wire), .rx_first(rx_first), .rx_second(rx_second),
    .rx_raw(m_rx_out), .rx_err(m_rx_err)
  );

  // ---- error aggregation ----
  assign rx_err = st_rx_err | m_rx_err;

endmodule

tb/tb_pe_codec_mux.v
// tb_pe_codec_mux.v — config-driven pipeline muxing.
//
// cfg[0]=stuff_en  cfg[1]=nrzi_en  cfg[2]=manch_en  cfg[3]=half_phase
// cfg[7:4]=stuff run length (0 => default 5; CAN 5, USB 6)
//
// TX: tx_bit -> [stuff] -> [nrzi] -> [manch] -> tx_wire
// RX: rx_wire -> [manch] -> [nrzi] -> [stuff] -> rx_bit
//
// Sampling note: the stuff and manch stages are COMBINATIONAL, so their
// outputs are valid before the strobe; the NRZI stage's line level is
// REGISTERED, so its wire output for bit k appears at the strobe. TX
// checks therefore sample per-stage; RX checks sample the settled
// cascade before the strobe commits state.

`timescale 1ns / 1ps

module tb_pe_codec_mux;
  logic       clk=0, rst_n, bit_en, clr;
  logic [7:0] cfg;
  logic       tx_bit, tx_wire, tx_stuffed;
  logic       rx_wire, rx_first, rx_second, rx_bit, rx_bit_valid, rx_err;

  pe_codec_mux dut (.*);
  always #5 clk = ~clk;

  integer errors = 0;

  task automatic check(input bit c, input string m);
    if (!c) begin $display("FAIL mux: %s @%0t", m, $time); errors++; end
  endtask

  task automatic strobe(); bit_en = 1; @(posedge clk); #1; bit_en = 0; #1; endtask
  task automatic reset_run(); clr = 1; @(posedge clk); #1; clr = 0; endtask

  // --- TX steps -------------------------------------------------------
  // Combinational stages: the emitted wire bit is visible pre-strobe.
  task automatic tx_step_comb(input bit b, output bit w, output bit st);
    tx_bit = b; #1;
    w  = tx_wire;
    st = tx_stuffed;
    strobe();
  endtask
  // NRZI: the line level for this bit is committed AT the strobe.
  task automatic tx_step_nrzi(input bit b, output bit lvl);
    tx_bit = b;
    strobe();
    #1;
    lvl = tx_wire;
  endtask

  // --- RX step: settled cascade sampled before the state commit --------
  task automatic rx_step(input bit wv, output bit rb, output bit rv);
    rx_wire = wv; #1;
    rb = rx_bit;
    rv = rx_bit_valid;
    strobe();
  endtask

  logic w, st, lvl, rb, rv;

  initial begin
    $dumpfile("tb_pe_codec_mux.vcd"); $dumpvars(0, tb_pe_codec_mux);
    rst_n=0; bit_en=0; clr=0; cfg=8'h00;
    tx_bit=0; rx_wire=0; rx_first=0; rx_second=0;
    repeat(3) @(posedge clk); #1; rst_n=1; @(posedge clk); #1;

    // ================= cfg=0x00: everything bypassed =================
    begin
      cfg = 8'h00;
      tx_bit = 1'b1; rx_wire = 1'b0; #1;
      check(tx_wire === 1'b1, "bypass: tx passthrough high");
      check(rx_bit === 1'b0, "bypass: rx passthrough low");
      check(rx_bit_valid === 1'b1, "bypass: rx always valid");
      tx_bit = 1'b0; #1;
      check(tx_wire === 1'b0, "bypass: tx passthrough low");
    end

    // ============ cfg=0x01: stuff only, run 5 (CAN) =================
    begin
      cfg = 8'h01; reset_run();
      for (int k = 0; k < 5; k++) begin
        tx_step_comb(1'b1, w, st);
        check(w === 1'b1, $sformatf("can tx: data bit %0d", k));
        check(st === 1'b0, $sformatf("can tx: no stuff at %0d", k));
      end
      check(tx_stuffed === 1'b1, "can tx: stuff owed after 5 identical");
      tx_step_comb(1'b0, w, st);      // stuff strobe (raw ignored)
      check(st === 1'b1, "can tx: stuff strobe flagged");
      check(w === 1'b0, "can tx: stuff bit complementary");
      tx_step_comb(1'b1, w, st);
      check(w === 1'b1, "can tx: data resumes after stuff");
    end

    // RX: five 1s then the stuff slot
    begin
      cfg = 8'h01; reset_run();
      for (int k = 0; k < 5; k++) begin
        rx_step(1'b1, rb, rv);
        check(rv === 1'b1, $sformatf("can rx: bit %0d valid", k));
        check(rb === 1'b1, $sformatf("can rx: bit %0d = 1", k));
      end
      rx_step(1'b0, rb, rv);          // stuff slot
      check(rv === 1'b0, "can rx: stuff slot flagged invalid");
      rx_step(1'b1, rb, rv);
      check(rv === 1'b1, "can rx: data resumes");
      check(rb === 1'b1, "can rx: resumed bit = 1");
    end

    // ============ cfg=0x61: stuff only, run 6 (USB) =================
    begin
      cfg = 8'h61; reset_run();
      for (int k = 0; k < 6; k++) begin
        tx_step_comb(1'b1, w, st);
        check(st === 1'b0, $sformatf("usb tx: no stuff at %0d", k));
      end
      check(tx_stuffed === 1'b1, "usb tx: owed after 6 identical");
      tx_step_comb(1'b0, w, st);
      check(st === 1'b1, "usb tx: stuff strobe flagged");
      check(w === 1'b0, "usb tx: stuff bit complementary");
    end

    // ================= cfg=0x02: NRZI only ==========================
    begin
      bit prev;
      cfg = 8'h02; reset_run();
      tx_step_nrzi(1'b0, lvl);            // raw 0 -> toggle from idle J
      check(lvl === 1'b0, "nrzi tx: raw 0 toggles the line");
      prev = lvl;
      tx_step_nrzi(1'b1, lvl);            // raw 1 -> hold
      check(lvl === prev, "nrzi tx: raw 1 holds the line");
      tx_step_nrzi(1'b0, lvl);            // raw 0 -> toggle
      check(lvl !== prev, "nrzi tx: raw 0 toggles again");
    end

    // RX: decode a level sequence back to raw bits
    begin
      // levels: start J=1; 0 -> toggle to 0; 1 -> hold 0; 0 -> toggle 1
      cfg = 8'h02; reset_run();
      rx_step(1'b0, rb, rv); check(rb === 1'b0, "nrzi rx: 1->0 decodes 0");
      rx_step(1'b0, rb, rv); check(rb === 1'b1, "nrzi rx: hold decodes 1");
      rx_step(1'b1, rb, rv); check(rb === 1'b0, "nrzi rx: 0->1 decodes 0");
      rx_step(1'b1, rb, rv); check(rb === 1'b1, "nrzi rx: hold decodes 1");
    end

    // =============== cfg=0x04: Manchester only ======================
    begin
      cfg = 8'h04;
      tx_bit = 1'b0; cfg[3] = 1'b0; #1;
      check(tx_wire === 1'b1, "manch: bit 0 first half high");
      cfg[3] = 1'b1; #1;
      check(tx_wire === 1'b0, "manch: bit 0 second half low (H->L)");
      tx_bit = 1'b1; cfg[3] = 1'b0; #1;
      check(tx_wire === 1'b0, "manch: bit 1 first half low");
      cfg[3] = 1'b1; #1;
      check(tx_wire === 1'b1, "manch: bit 1 second half high (L->H)");

      rx_first = 1'b1; rx_second = 1'b0; #1;
      check(rx_bit === 1'b0, "manch rx: decodes 0");
      check(rx_err === 1'b0, "manch rx: legal bit");
      rx_first = 1'b0; rx_second = 1'b1; #1;
      check(rx_bit === 1'b1, "manch rx: decodes 1");
      rx_first = 1'b1; rx_second = 1'b1; #1;
      check(rx_err === 1'b1, "manch rx: no mid-bit edge flagged");
    end

    // ====== cfg=0x63: stuff(run 6) + NRZI, USB-LS composition =======
    begin
      int nraw; logic rec [64]; bit rbv, rvv;
      logic [79:0] wire_lv;   // level per wire bit
      int nwv; bit lv; bit raw_exp [64]; int nraw_exp;
      logic stuffed [128]; int ns; int run; bit last;
      cfg = 8'h63; reset_run();

      // Build the stuffed raw stream (run counter resets after each
      // inserted bit, exactly like the RTL), then NRZI-encode it.
      nraw_exp = 0; ns = 0; run = 0; last = 1'b0;
      for (int k = 0; k < 48; k++) begin
        bit b;
        b = (k % 10 < 7) ? 1'b1 : ((k / 10) % 2);   // long one-runs
        raw_exp[nraw_exp] = b; nraw_exp++;
        stuffed[ns] = b; ns++;
        if (b == last) run++; else begin last = b; run = 1; end
        if (run == 6) begin
          stuffed[ns] = ~b; ns++;      // stuffed bit
          last = ~b; run = 1;          // it opens a new run
        end
      end
      lv = 1'b1; nwv = 0;
      for (int i = 0; i < ns; i++) begin
        if (stuffed[i] == 1'b0) lv = ~lv;
        wire_lv[nwv] = lv; nwv++;
      end
      check(nwv > 48, "usb: stuffing added wire bits");

      // Feed the levels to the RX cascade and recover the raw stream.
      nraw = 0;
      for (int i = 0; i < nwv; i++) begin
        rx_step(wire_lv[i], rbv, rvv);
        if (rvv) begin rec[nraw] = rbv; nraw++; end
      end
      check(nraw == nraw_exp,
            $sformatf("usb: recovered %0d raw bits (expected %0d)", nraw, nraw_exp));
      for (int i = 0; i < nraw_exp && i < nraw; i++)
        check(rec[i] === raw_exp[i], $sformatf("usb: bit %0d round trip", i));
    end

    // ====== cfg=0x02: NRZI round trip, long no-transition run =======
    begin
      int nraw; logic rec [64]; bit rbv, rvv; bit lv; bit exp_b;
      cfg = 8'h02; reset_run();
      lv = 1'b1; nraw = 0;
      for (int k = 0; k < 40; k++) begin
        exp_b = (k < 20) ? 1'b1 : ~(k % 2);   // 20 ones (no transitions), then toggling
        if (exp_b == 1'b0) lv = ~lv;
        rx_step(lv, rbv, rvv);
        if (rvv) begin
          check(rbv === exp_b, $sformatf("nrzi rt: bit %0d", k));
          nraw++;
        end
      end
      check(nraw == 40, $sformatf("nrzi rt: recovered %0d bits", nraw));
    end

    // ============ clr resets run tracking mid-stream ================
    begin
      cfg = 8'h01;
      reset_run();
      for (int k = 0; k < 4; k++) tx_step_comb(1'b1, w, st);
      reset_run();                       // clears the run counter
      for (int k = 0; k < 4; k++) begin
        tx_step_comb(1'b1, w, st);
        check(st === 1'b0, $sformatf("clr: no stuff at %0d after clear", k));
      end
      tx_step_comb(1'b1, w, st);
      check(tx_stuffed === 1'b1, "clr: run tracking restarted from the clear");
    end

    if (errors == 0) $display("PASS: tb_pe_codec_mux");
    else $display("FAILURES mux: %0d", errors);
    $finish;
  end
endmodule

sim/tb_pe_codec_mux.vcd
$date
	Fri Sep 18 20:43:40 2026
$end
$version
	Icarus Verilog
$end
$timescale
	1ps
$end
$scope module tb_pe_codec_mux $end
$var wire 1 ! tx_wire $end
$var wire 1 " tx_stuffed $end
$var wire 1 # rx_err $end
$var wire 1 $ rx_bit_valid $end
$var wire 1 % rx_bit $end
$var reg 1 & bit_en $end
$var reg 8 ' cfg [7:0] $end
$var reg 1 ( clk $end
$var reg 1 ) clr $end
$var reg 1 * lvl $end
$var reg 1 + rb $end
$var reg 1 , rst_n $end
$var reg 1 - rv $end
$var reg 1 . rx_first $end
$var reg 1 / rx_second $end
$var reg 1 0 rx_wire $end
$var reg 1 1 st $end
$var reg 1 2 tx_bit $end
$var reg 1 3 w $end
$var integer 32 4 errors [31:0] $end
$scope module dut $end
$var wire 1 & bit_en $end
$var wire 8 5 cfg [7:0] $end
$var wire 1 ( clk $end
$var wire 1 ) clr $end
$var wire 1 , rst_n $end
$var wire 1 # rx_err $end
$var wire 1 . rx_first $end
$var wire 1 / rx_second $end
$var wire 1 0 rx_wire $end
$var wire 1 2 tx_bit $end
$var wire 1 ! tx_wire $end
$var wire 1 " tx_stuffed $end
$var wire 1 6 stuff_en $end
$var wire 1 7 st_rx_err $end
$var wire 1 8 s_wire $end
$var wire 1 $ rx_bit_valid $end
$var wire 1 % rx_bit $end
$var wire 4 9 run_cfg [3:0] $end
$var wire 1 : nrzi_en $end
$var wire 1 ; n_wire $end
$var wire 1 < n_rx_out $end
$var wire 1 = manch_en $end
$var wire 1 > m_rx_out $end
$var wire 1 ? m_rx_err $end
$scope module u_manch $end
$var wire 1 & bit_en $end
$var wire 1 @ bypass $end
$var wire 1 ( clk $end
$var wire 1 A half_phase $end
$var wire 1 , rst_n $end
$var wire 1 . rx_first $end
$var wire 1 / rx_second $end
$var wire 1 0 rx_wire $end
$var wire 1 ! tx_wire $end
$var wire 1 ; tx_raw $end
$var wire 1 > rx_raw $end
$var wire 1 ? rx_err $end
$upscope $end
$scope module u_nrzi $end
$var wire 1 & bit_en $end
$var wire 1 B bypass $end
$var wire 1 ( clk $end
$var wire 1 , rst_n $end
$var wire 1 > rx_wire $end
$var wire 1 C tx_lvl $end
$var wire 1 ; tx_wire $end
$var wire 1 8 tx_raw $end
$var wire 1 < rx_raw $end
$var reg 1 D rx_level $end
$var reg 1 E tx_level $end
$upscope $end
$scope module u_stuff $end
$var wire 1 & bit_en $end
$var wire 1 F bypass $end
$var wire 1 ( clk $end
$var wire 1 ) clr $end
$var wire 1 , rst_n $end
$var wire 4 G run_cfg [3:0] $end
$var wire 1 H rx_is_stuff $end
$var wire 1 % rx_raw $end
$var wire 1 < rx_wire $end
$var wire 1 2 tx_raw $end
$var wire 1 " tx_stuffed $end
$var wire 1 8 tx_wire $end
$var wire 1 $ rx_raw_valid $end
$var reg 1 7 rx_err $end
$var reg 1 I rx_lvl $end
$var reg 4 J rx_run [3:0] $end
$var reg 1 K tx_lvl $end
$var reg 1 L tx_pend $end
$var reg 4 M tx_run [3:0] $end
$upscope $end
$upscope $end
$scope begin $ivl_for_loop0 $end
$var integer 32 N k [31:0] $end
$upscope $end
$scope begin $ivl_for_loop1 $end
$var integer 32 O k [31:0] $end
$upscope $end
$scope begin $ivl_for_loop2 $end
$var integer 32 P k [31:0] $end
$upscope $end
$scope begin $ivl_for_loop8 $end
$var integer 32 Q k [31:0] $end
$upscope $end
$scope begin $ivl_for_loop9 $end
$var integer 32 R k [31:0] $end
$upscope $end
$scope begin $unm_blk_27 $end
$var reg 1 S prev $end
$upscope $end
$scope begin $unm_blk_30 $end
$var reg 80 T wire_lv [79:0] $end
$var reg 1 U last $end
$var reg 1 V lv $end
$var integer 32 W nraw [31:0] $end
$var integer 32 X nraw_exp [31:0] $end
$var integer 32 Y ns [31:0] $end
$var integer 32 Z nwv [31:0] $end
$var reg 1 [ rbv $end
$var integer 32 \ run [31:0] $end
$var reg 1 ] rvv $end
$scope begin $ivl_for_loop3 $end
$var integer 32 ^ k [31:0] $end
$scope begin $unm_blk_31 $end
$var reg 1 _ b $end
$upscope $end
$upscope $end
$scope begin $ivl_for_loop4 $end
$var integer 32 ` i [31:0] $end
$upscope $end
$scope begin $ivl_for_loop5 $end
$var integer 32 a i [31:0] $end
$upscope $end
$scope begin $ivl_for_loop6 $end
$var integer 32 b i [31:0] $end
$upscope $end
$upscope $end
$scope begin $unm_blk_37 $end
$var reg 1 c exp_b $end
$var reg 1 d lv $end
$var integer 32 e nraw [31:0] $end
$var reg 1 f rbv $end
$var reg 1 g rvv $end
$scope begin $ivl_for_loop7 $end
$var integer 32 h k [31:0] $end
$upscope $end
$upscope $end
$scope task check $end
$upscope $end
$scope task reset_run $end
$upscope $end
$scope task rx_step $end
$upscope $end
$scope task strobe $end
$upscope $end
$scope task tx_step_comb $end
$upscope $end
$scope task tx_step_nrzi $end
$upscope $end
$upscope $end
$enddefinitions $end
$comment Show the parameter values. $end
$dumpall
$end
#0
$dumpvars
b0 h
0g
0f
b0 e
0d
0c
b0 b
b0 a
b0 `
0_
b0 ^
0]
b0 \
0[
b0 Z
b0 Y
b0 X
b0 W
0V
0U
bx T
0S
b0 R
b0 Q
b0 P
b0 O
b0 N
b0 M
0L
0K
b0 J
0I
0H
b101 G
1F
1E
1D
1C
1B
0A
1@
0?
0>
0=
0<
0;
0:
b101 9
08
07
06
b0 5
b0 4
x3
02
x1
00
0/
0.
x-
0,
x+
x*
0)
0(
b0 '
0&
0%
1$
0#
0"
0!
$end
#5000
1(
#10000
0(
#15000
1(
#20000
0(
#25000
1(
#26000
1,
#30000
0(
#35000
1(
#36000
1!
1;
18
12
#37000
0!
0;
08
02
#38000
0F
16
1)
b1 '
b1 5
#40000
0(
#45000
1(
#46000
1!
1;
18
12
0)
#47000
1&
#50000
0(
#55000
b1 M
1K
b1 J
0D
1(
#56000
0&
#57000
b1 N
01
13
#58000
1&
#60000
0(
#65000
b10 J
b10 M
1(
#66000
0&
#67000
b10 N
#68000
1&
#70000
0(
#75000
b11 M
b11 J
1(
#76000
0&
#77000
b11 N
#78000
1&
#80000
0(
#85000
b100 J
b100 M
1(
#86000
0&
#87000
b100 N
#88000
1&
#90000
0(
#95000
0!
0;
08
0$
1"
1H
b101 M
1L
b101 J
1(
#96000
0&
#97000
02
b101 N
#98000
1&
#100000
0(
#105000
1$
0H
1#
0"
b1 J
17
0K
b1 M
0L
1(
#106000
0&
#107000
1!
1;
18
12
11
03
#108000
1&
#110000
0(
#115000
0#
1K
b10 J
07
1(
#116000
0&
#117000
1)
01
13
#120000
0(
#125000
b0 J
0K
b0 M
1(
#126000
1%
1<
1>
10
0)
#127000
1&
#130000
0(
#135000
b1 M
1K
1I
b1 J
1D
1(
#136000
0&
#137000
b1 O
1-
1+
#138000
1&
#140000
0(
#145000
b10 J
b10 M
1(
#146000
0&
#147000
b10 O
#148000
1&
#150000
0(
#155000
b11 M
b11 J
1(
#156000
0&
#157000
b11 O
#158000
1&
#160000
0(
#165000
b100 J
b100 M
1(
#166000
0&
#167000
b100 O
#168000
1&
#170000
0(
#175000
0!
0;
08
0$
1"
1H
b101 M
1L
b101 J
1(
#176000
0&
#177000
0%
0<
0>
00
b101 O
#178000
1&
#180000
0(
#185000
1!
1;
1$
18
0H
0"
0D
0I
b1 J
0K
b1 M
0L
1(
#186000
0&
#187000
1%
1<
1>
10
0-
0+
#188000
1&
#190000
0(
#195000
1K
1I
1D
1(
#196000
0&
#197000
b110 9
b110 G
1)
b1100001 '
b1100001 5
1-
1+
#200000
0(
#205000
0I
b0 J
0K
b0 M
1(
#206000
0)
#207000
1&
#210000
0(
#215000
b1 M
1K
1I
b1 J
1(
#216000
0&
#217000
b1 P
#218000
1&
#220000
0(
#225000
b10 J
b10 M
1(
#226000
0&
#227000
b10 P
#228000
1&
#230000
0(
#235000
b11 M
b11 J
1(
#236000
0&
#237000
b11 P
#238000
1&
#240000
0(
#245000
b100 J
b100 M
1(
#246000
0&
#247000
b100 P
#248000
1&
#250000
0(
#255000
b101 M
b101 J
1(
#256000
0&
#257000
b101 P
#258000
1&
#260000
0(
#265000
0!
0;
0$
08
1H
1"
b110 J
b110 M
1L
1(
#266000
0&
#267000
02
b110 P
#268000
1&
#270000
0(
#275000
1$
0"
0H
1#
0K
b1 M
0L
b1 J
17
1(
#276000
0&
#277000
1!
1;
1F
0B
b101 9
b101 G
06
1:
1)
b10 '
b10 5
11
03
#280000
0(
#285000
0#
07
0I
b0 J
b0 M
1(
#286000
1&
0)
#290000
0(
#295000
0!
0;
0C
0E
1(
#296000
0&
#298000
18
1&
12
0*
#300000
0(
#305000
1(
#306000
0&
#308000
08
1&
02
#310000
0(
#315000
1!
1;
1C
1E
1(
#316000
0&
#318000
1)
1*
#320000
0(
#325000
1(
#326000
0%
0<
0>
00
0)
#327000
1&
#330000
0(
#335000
1%
1<
0!
0;
0D
0C
0E
1(
#336000
0&
#337000
0+
#338000
1&
#340000
0(
#345000
1!
1;
1C
1E
1(
#346000
0&
#347000
0%
0<
1>
10
1+
#348000
1&
#350000
0(
#355000
1%
1<
0!
0;
1D
0C
0E
1(
#356000
0&
#357000
0+
#358000
1&
#360000
0(
#365000
1!
1;
1C
1E
1(
#366000
0&
#367000
1#
0;
0%
0<
1!
0>
1?
1B
0@
0:
1=
b100 '
b100 5
1+
#368000
0!
1A
b1100 '
b1100 5
#369000
0!
1;
0A
18
b100 '
b100 5
12
#370000
1!
1A
b1100 '
b1100 5
0(
#371000
0#
0?
1.
#372000
1%
1<
1>
1/
0.
#373000
1#
1?
1.
#374000
0#
0?
0F
0B
1@
b110 9
b110 G
16
1:
0=
0A
1)
b1100011 '
b1100011 5
#375000
1(
#376000
b110101 `
b110101 Z
bx10000001111111000000010111111000000011111110100111111 T
1V
b110000 ^
b1 \
0U
b110101 Y
b110000 X
0_
0)
#377000
1&
#380000
0(
#385000
1I
b1 J
b1 M
1K
1(
#386000
0&
#387000
b1 a
b1 W
1]
1[
#388000
1&
#390000
0(
#395000
b10 M
b10 J
1(
#396000
0&
#397000
b10 a
b10 W
#398000
1&
#400000
0(
#405000
b11 J
b11 M
1(
#406000
0&
#407000
b11 a
b11 W
#408000
1&
#410000
0(
#415000
b100 M
b100 J
1(
#416000
0&
#417000
b100 a
b100 W
#418000
1&
#420000
0(
#425000
b101 J
b101 M
1(
#426000
0&
#427000
b101 a
b101 W
#428000
1&
#430000
0(
#435000
08
0$
1"
1H
b110 M
1L
b110 J
1(
#436000
0&
#437000
0%
0<
0>
00
b110 a
b110 W
#438000
1&
#440000
0(
#445000
1%
1<
0!
1$
18
0;
0H
0"
0D
0C
0E
0I
b1 J
0K
b1 M
0L
1(
#446000
0&
#447000
b111 a
0]
0[
#448000
1&
#450000
0(
#455000
1K
1I
1(
#456000
0&
#457000
0%
0<
1>
10
b1000 a
b111 W
1]
1[
#458000
1&
#460000
0(
#465000
1%
1<
1D
0I
b10 M
1(
#466000
0&
#467000
0%
0<
0>
00
b1001 a
b1000 W
0[
#468000
1&
#470000
0(
#475000
1%
1<
b11 M
b10 J
0D
1(
#476000
0&
#477000
0%
0<
1>
10
b1010 a
b1001 W
#478000
1&
#480000
0(
#485000
1%
1<
1D
b11 J
b100 M
1(
#486000
0&
#487000
b1011 a
b1010 W
#488000
1&
#490000
0(
#495000
b101 M
1I
b1 J
1(
#496000
0&
#497000
b1100 a
b1011 W
1[
#498000
1&
#500000
0(
#505000
08
1"
b10 J
b110 M
1L
1(
#506000
0&
#507000
b1101 a
b1100 W
#508000
1&
#510000
0(
#515000
18
1!
0"
1;
0K
b1 M
0L
b11 J
1C
1E
1(
#516000
0&
#517000
b1110 a
b1101 W
#518000
1&
#520000
0(
#525000
b100 J
1K
1(
#526000
0&
#527000
b1111 a
b1110 W
#528000
1&
#530000
0(
#535000
b10 M
b101 J
1(
#536000
0&
#537000
b10000 a
b1111 W
#538000
1&
#540000
0(
#545000
0$
1H
b110 J
b11 M
1(
#546000
0&
#547000
0%
0<
0>
00
b10001 a
b10000 W
#548000
1&
#550000
0(
#555000
1%
1<
1$
0H
b100 M
0I
b1 J
0D
1(
#556000
0&
#557000
b10010 a
0]
0[
#558000
1&
#560000
0(
#565000
1I
b101 M
1(
#566000
0&
#567000
b10011 a
b10001 W
1]
1[
#568000
1&
#570000
0(
#575000
08
1"
b110 M
1L
b10 J
1(
#576000
0&
#577000
b10100 a
b10010 W
#578000
1&
#580000
0(
#585000
0!
18
0;
0"
0C
0E
b11 J
0K
b1 M
0L
1(
#586000
0&
#587000
b10101 a
b10011 W
#588000
1&
#590000
0(
#595000
1K
b100 J
1(
#596000
0&
#597000
b10110 a
b10100 W
