rtl/pe_line_codec.v
// pe_line_codec.v — Tier-1 line-code codecs: NRZI, Manchester, bit-stuffing.
//
// These sit between the SM/SERDES (plain NRZ bits, one per bit_en strobe)
// and the pin matrix (wire levels). Each stage is runtime-bypassable so a
// config register can mux any subset into the pipeline (see pe_codec_mux).
//
//   pe_nrzi      TX: raw 0 -> toggle line, raw 1 -> hold (USB-LS).
//                RX: separate sampled-level register — a receiver cannot
//                see the transmitter's state. raw = wire XOR prev_level.
//   pe_manch     TX: half_phase selects which half-cell is driven;
//                raw 0 -> H then L, raw 1 -> L then H (IEEE 802.3).
//                RX: decodes from the two half-cell samples the DRU
//                captured; equal halves = illegal (no mid-bit edge).
//   pe_bitstuff  Insert/drop a complementary bit after run_cfg identical
//                consecutive bits (5 = CAN, 6 = USB). TX emits the real
//                bit first, then consumes a FOLLOWING strobe for the stuff
//                bit (tx_stuffed flags that strobe; raw input is ignored).
//                RX flags the stuffed bit (rx_raw_valid=0) and errors if
//                the bit after a full run is not complementary.
//
// None of these know protocols; config bits and one runtime parameter only.

module pe_nrzi (
  input  logic clk, rst_n,
  input  logic bit_en,
  input  logic bypass,
  input  logic tx_raw,
  output logic tx_wire,
  input  logic rx_wire,
  output logic rx_raw,
  output logic tx_lvl
);
  logic tx_level;   // line level we drive
  logic rx_level;   // last wire level we sampled (receiver state)

  assign tx_lvl  = tx_level;
  assign tx_wire = bypass ? tx_raw : tx_level;
  // Decode: a transition is a 0, no transition is a 1 (XNOR).
  assign rx_raw  = bypass ? rx_wire : ~(rx_wire ^ rx_level);

  always_ff @(posedge clk or negedge rst_n) begin
    if (!rst_n) begin
      tx_level <= 1'b1;   // idle J
      rx_level <= 1'b1;   // idle J
    end else if (bit_en) begin
      if (!bypass && (tx_raw == 1'b0)) tx_level <= ~tx_level;
      rx_level <= rx_wire;
    end
  end
endmodule


module pe_manch (
  input  logic clk, rst_n,
  input  logic bit_en,
  input  logic bypass,
  input  logic half_phase,      // 0 = first half-cell, 1 = second half-cell
  input  logic tx_raw,
  output logic tx_wire,
  input  logic rx_wire,
  input  logic rx_first,        // DRU half-cell sample, first half
  input  logic rx_second,       // DRU half-cell sample, second half
  output logic rx_raw,
  output logic rx_err
);
  // TX: raw 0 -> first half high, second low (H->L mid-bit).
  //     raw 1 -> first half low,  second high (L->H mid-bit).
  assign tx_wire = bypass ? tx_raw : (half_phase ? tx_raw : ~tx_raw);
  // RX: the second-half level carries the bit (a 0's second half is low).
  assign rx_raw  = bypass ? rx_wire : rx_second;
  assign rx_err  = bypass ? 1'b0 : (rx_first == rx_second);
endmodule


module pe_bitstuff (
  input  logic       clk, rst_n,
  input  logic       bit_en,
  input  logic       bypass,
  input  logic       clr,          // frame/SOF boundary: reset run tracking
  input  logic [3:0] run_cfg,      // stuff after this many identical bits
  input  logic       tx_raw,
  output logic       tx_wire,
  output logic       tx_stuffed,   // this strobe emits a stuff bit (raw ignored)
  input  logic       rx_wire,
  output logic       rx_raw,
  output logic       rx_raw_valid, // 0 => this wire bit was a stuff bit
  output logic       rx_err        // bit after a full run not complementary
);
  // ---------------- TX ----------------
  logic [3:0] tx_run;    // identical consecutive raw bits emitted
  logic       tx_lvl;    // value of that run
  logic       tx_pend;   // a stuff bit is owed on the NEXT strobe

  assign tx_stuffed = !bypass && tx_pend;
  assign tx_wire    = bypass ? tx_raw : (tx_pend ? ~tx_lvl : tx_raw);

  always_ff @(posedge clk or negedge rst_n) begin
    if (!rst_n) begin
      tx_run <= 4'd0; tx_lvl <= 1'b0; tx_pend <= 1'b0;
    end else if (clr) begin
      tx_run <= 4'd0; tx_lvl <= 1'b0; tx_pend <= 1'b0;
    end else if (bit_en && !bypass) begin
      if (tx_pend) begin
        tx_pend <= 1'b0;
        tx_run  <= 4'd1;      // the stuff bit opens a new run
        tx_lvl  <= ~tx_lvl;
      end else if (tx_raw == tx_lvl) begin
        if (tx_run == run_cfg - 4'd1) tx_pend <= 1'b1;
        tx_run <= tx_run + 4'd1;
      end else begin
        tx_lvl <= tx_raw;
        tx_run <= 4'd1;
      end
    end
  end

  // ---------------- RX ----------------
  logic [3:0] rx_run;    // identical consecutive WIRE bits seen
  logic       rx_lvl;
  logic       rx_is_stuff;

  assign rx_is_stuff  = !bypass && (rx_run == run_cfg);
  assign rx_raw       = rx_wire;
  assign rx_raw_valid = bypass ? 1'b1 : !rx_is_stuff;

  always_ff @(posedge clk or negedge rst_n) begin
    if (!rst_n) begin
      rx_run <= 4'd0; rx_lvl <= 1'b0; rx_err <= 1'b0;
    end else if (clr) begin
      rx_run <= 4'd0; rx_lvl <= 1'b0; rx_err <= 1'b0;
    end else if (bit_en && !bypass) begin
      rx_err <= 1'b0;
      if (rx_run == run_cfg) begin
        // this wire bit is the stuffed one: it must be complementary
        if (rx_wire == rx_lvl) rx_err <= 1'b1;
        rx_run <= 4'd1;
        rx_lvl <= rx_wire;
      end else if (rx_wire == rx_lvl) begin
        rx_run <= rx_run + 4'd1;
      end else begin
        rx_run <= 4'd1;
        rx_lvl <= rx_wire;
      end
    end
  end
endmodule

tb/tb_pe_line_codec.v
// tb_pe_line_codec.v — self-checking testbenches for the Tier-1 codec trio.
//
// Timing discipline: drive inputs, #1 to settle combinational outputs,
// sample BEFORE the strobe that commits state.
//
// pe_nrzi:     TX and RX as two instances joined by an explicit wire (a
//              real receiver cannot see TX state). Fixed + adversarial
//              (all-ones = no transitions, all-zeros) + random vectors.
// pe_manch:    both half-cells of every bit; decode; error injection.
// pe_bitstuff: run_cfg 5 (CAN) and 6 (USB), TX stuff placement, RX
//              destuff, wire-stream round trip, violation, bypass, clr.

`timescale 1ns / 1ps

// ---------------------------------------------------------------- NRZI
module tb_pe_nrzi;
  logic clk=0, rst_n;
  logic tx_en, tx_bypass, tx_raw, tx_wire, tx_lvl;
  logic rx_en, rx_bypass, rx_wire, rx_raw, rx_lvl_unused;
  logic wire_lvl;

  pe_nrzi u_tx (.clk(clk), .rst_n(rst_n), .bit_en(tx_en), .bypass(tx_bypass),
                .tx_raw(tx_raw), .tx_wire(tx_wire), .rx_wire(1'b0),
                .rx_raw(), .tx_lvl(tx_lvl));
  pe_nrzi u_rx (.clk(clk), .rst_n(rst_n), .bit_en(rx_en), .bypass(rx_bypass),
                .tx_raw(1'b1), .tx_wire(), .rx_wire(rx_wire),
                .rx_raw(rx_raw), .tx_lvl(rx_lvl_unused));

  always #5 clk = ~clk;
  integer errors = 0;
  integer seed = 42;

  task automatic check(input bit c, input string m);
    if (!c) begin $display("FAIL nrzi: %s @%0t", m, $time); errors++; end
  endtask

  task automatic strobe_tx(); tx_en = 1; @(posedge clk); #1; tx_en = 0; endtask
  task automatic strobe_rx(); rx_en = 1; @(posedge clk); #1; rx_en = 0; endtask

  // Send one raw bit: TX strobes (may toggle the line), wire settles,
  // RX decodes against its previous sample, then commits it.
  task automatic send_bit(input bit b, output bit decoded);
    tx_raw = b;
    strobe_tx();
    #1;
    wire_lvl = tx_wire;
    rx_wire  = wire_lvl;
    #1;
    decoded = rx_raw;
    strobe_rx();
  endtask

  initial begin
    $dumpfile("tb_pe_nrzi.vcd"); $dumpvars(0, tb_pe_nrzi);
    rst_n=0; tx_en=0; rx_en=0; tx_bypass=0; rx_bypass=0;
    tx_raw=0; rx_wire=0; wire_lvl=0;
    repeat(3) @(posedge clk); #1; rst_n=1; @(posedge clk); #1;

    // Fixed vector: runs, alternation, and boundaries
    begin
      logic [63:0] v; bit d;
      v = 64'b1011_0001_1111_1110_0101_0101_0000_0000_1100_1100_1010_1010_1110_0001_0110_1001;
      for (int k = 63; k >= 0; k--) begin
        send_bit(v[k], d);
        check(d === v[k], $sformatf("fixed bit %0d", k));
      end
    end

    // Worst case: all ones (no transitions at all)
    begin
      bit d;
      for (int k = 0; k < 24; k++) begin
        send_bit(1'b1, d);
        check(d === 1'b1, $sformatf("ones run bit %0d", k));
      end
    end

    // All zeros (transition every bit)
    begin
      bit d;
      for (int k = 0; k < 24; k++) begin
        send_bit(1'b0, d);
        check(d === 1'b0, $sformatf("zeros run bit %0d", k));
      end
    end

    // Random soak
    for (int t = 0; t < 12; t++) begin
      logic [31:0] rv; bit d;
      rv = $random(seed);
      for (int k = 31; k >= 0; k--) begin
        send_bit(rv[k], d);
        check(d === rv[k], $sformatf("rand %0d bit %0d", t, k));
      end
    end

    // Bypass passthrough
    tx_bypass = 1; rx_bypass = 1;
    tx_raw = 1'b1; #1; check(tx_wire === 1'b1, "bypass tx passthrough");
    rx_wire = 1'b0; #1; check(rx_raw === 1'b0, "bypass rx passthrough");
    tx_bypass = 0; rx_bypass = 0;

    if (errors == 0) $display("PASS: tb_pe_nrzi");
    else $display("FAILURES nrzi: %0d", errors);
    $finish;
  end
endmodule


// ------------------------------------------------------------- Manchester
module tb_pe_manch;
  logic clk=0, rst_n, bit_en, bypass, half_phase, tx_raw, tx_wire;
  logic rx_wire, rx_first, rx_second, rx_raw, rx_err;
  pe_manch dut (.*);
  always #5 clk = ~clk;
  integer errors = 0;

  task automatic check(input bit c, input string m);
    if (!c) begin $display("FAIL manch: %s @%0t", m, $time); errors++; end
  endtask

  // Check both half-cells of one transmitted bit.
  task automatic tx_bit(input bit b);
    half_phase = 1'b0; tx_raw = b; #1;
    check(tx_wire === (b ? 1'b0 : 1'b1), $sformatf("bit %b first half", b));
    half_phase = 1'b1; #1;
    check(tx_wire === (b ? 1'b1 : 1'b0), $sformatf("bit %b second half", b));
  endtask

  initial begin
    $dumpfile("tb_pe_manch.vcd"); $dumpvars(0, tb_pe_manch);
    rst_n=0; bit_en=0; bypass=0; half_phase=0; tx_raw=0;
    rx_wire=0; rx_first=0; rx_second=0;
    repeat(3) @(posedge clk); #1; rst_n=1; @(posedge clk); #1;

    tx_bit(1'b0);   // H then L
    tx_bit(1'b1);   // L then H
    tx_bit(1'b0);

    // RX decode from DRU half-cell samples
    rx_first=1'b1; rx_second=1'b0; #1;
    check(rx_raw === 1'b0, "rx H->L decodes 0");
    check(rx_err === 1'b0, "rx H->L legal");
    rx_first=1'b0; rx_second=1'b1; #1;
    check(rx_raw === 1'b1, "rx L->H decodes 1");
    check(rx_err === 1'b0, "rx L->H legal");
    rx_first=1'b1; rx_second=1'b1; #1;
    check(rx_err === 1'b1, "rx high no-transition flagged");
    rx_first=1'b0; rx_second=1'b0; #1;
    check(rx_err === 1'b1, "rx low no-transition flagged");

    // Bypass
    bypass = 1; tx_raw = 1'b1; rx_wire = 1'b0;
    rx_first=1'b1; rx_second=1'b1; #1;
    check(tx_wire === 1'b1, "bypass tx passthrough");
    check(rx_raw === 1'b0, "bypass rx passthrough");
    check(rx_err === 1'b0, "bypass suppresses error");

    if (errors == 0) $display("PASS: tb_pe_manch");
    else $display("FAILURES manch: %0d", errors);
    $finish;
  end
endmodule


// ----------------------------------------------------------- Bit stuffing
module tb_pe_bitstuff;
  logic clk=0, rst_n, bit_en, bypass, clr;
  logic [3:0] run_cfg;
  logic tx_raw, tx_wire, tx_stuffed;
  logic rx_wire, rx_raw, rx_raw_valid, rx_err;
  pe_bitstuff dut (.*);
  always #5 clk = ~clk;
  integer errors = 0;
  integer seed = 7;

  task automatic check(input bit c, input string m);
    if (!c) begin $display("FAIL stuff: %s @%0t", m, $time); errors++; end
  endtask

  task automatic strobe(); bit_en = 1; @(posedge clk); #1; bit_en = 0; #1; endtask

  // TX one raw bit; returns the wire bit this strobe emitted.
  task automatic tx_bit(input bit b, output bit w);
    tx_raw = b; #1;
    w = tx_wire;
    strobe();
  endtask

  // Emit the owed stuff bit (raw input ignored on this strobe).
  task automatic tx_stuff(output bit w);
    #1;
    check(tx_stuffed === 1'b1, "stuff strobe flagged");
    w = tx_wire;
    strobe();
    #1;
    check(tx_stuffed === 1'b0, "stuff flag clears after the strobe");
  endtask

  initial begin
    $dumpfile("tb_pe_bitstuff.vcd"); $dumpvars(0, tb_pe_bitstuff);
    rst_n=0; bit_en=0; bypass=0; clr=0; run_cfg=4'd5;
    tx_raw=0; rx_wire=0;
    repeat(3) @(posedge clk); #1; rst_n=1; @(posedge clk); #1;

    // ---- CAN (run_cfg=5): five 1s then a stuffed 0 ----
    begin
      bit w;
      clr = 1; @(posedge clk); #1; clr = 0;
      for (int k = 0; k < 5; k++) begin
        tx_bit(1'b1, w);
        check(w === 1'b1, $sformatf("can: data 1 at %0d", k));
      end
      check(tx_stuffed === 1'b1, "can: stuff owed after 5 ones");
      tx_stuff(w);
      check(w === 1'b0, "can: stuff bit complementary (0)");
      tx_bit(1'b0, w);
      check(w === 1'b0, "can: data resumes after stuff");
    end

    // ---- CAN: five 0s ----
    begin
      bit w;
      clr = 1; @(posedge clk); #1; clr = 0;
      for (int k = 0; k < 5; k++) begin
        tx_bit(1'b0, w);
        check(w === 1'b0, $sformatf("can0: data 0 at %0d", k));
      end
      tx_stuff(w);
      check(w === 1'b1, "can0: stuff bit complementary (1)");
    end

    // ---- USB (run_cfg=6): six 1s then a stuffed 0 ----
    begin
      bit w;
      run_cfg = 4'd6;
      clr = 1; @(posedge clk); #1; clr = 0;
      for (int k = 0; k < 6; k++) begin
        tx_bit(1'b1, w);
        check(w === 1'b1, $sformatf("usb: data 1 at %0d", k));
      end
      check(tx_stuffed === 1'b1, "usb: stuff owed after 6 ones");
      tx_stuff(w);
      check(w === 1'b0, "usb: stuff bit complementary");
    end

    // ---- Wire-stream round trip: TX all-ones (max stuffing), replay RX ----
    begin
      bit w; int nwire; logic wbits [128]; int nraw; logic rec [128];
      run_cfg = 4'd5;
      clr = 1; @(posedge clk); #1; clr = 0;
      nwire = 0;
      for (int k = 0; k < 64; k++) begin
        tx_bit(1'b1, w);
        wbits[nwire] = w; nwire++;
        if (tx_stuffed) begin
          tx_stuff(w);
          wbits[nwire] = w; nwire++;
        end
      end
      check(nwire > 64, "stuffing inserted extra wire bits");

      clr = 1; @(posedge clk); #1; clr = 0;
      nraw = 0;
      for (int i = 0; i < nwire; i++) begin
        rx_wire = wbits[i]; #1;
        if (rx_raw_valid) begin rec[nraw] = rx_raw; nraw++; end
        strobe();
      end
      check(nraw == 64, $sformatf("rx recovered 64 raw bits (got %0d)", nraw));
      for (int i = 0; i < 64; i++)
        check(rec[i] === 1'b1, $sformatf("rx recovered bit %0d = 1", i));
    end

    // ---- RX violation: bit after a full run is not complementary ----
    begin
      run_cfg = 4'd5;
      clr = 1; @(posedge clk); #1; clr = 0;
      for (int k = 0; k < 5; k++) begin
        rx_wire = 1'b1; #1; strobe();
      end
      rx_wire = 1'b1; #1;   // illegal: should have been a stuffed 0
      check(rx_raw_valid === 1'b0, "violating bit occupies the stuff slot");
      strobe(); #1;
      check(rx_err === 1'b1, "violation detected");
    end

    // ---- bypass ----
    begin
      bypass = 1; tx_raw = 1'b1; rx_wire = 1'b0; #1;
      check(tx_wire === 1'b1, "bypass tx passthrough");
      check(tx_stuffed === 1'b0, "bypass: no stuff");
      check(rx_raw_valid === 1'b1, "bypass: rx always valid");
      bypass = 0;
    end

    if (errors == 0) $display("PASS: tb_pe_bitstuff");
    else $display("FAILURES stuff: %0d", errors);
    $finish;
  end
endmodule

sim/tb_pe_nrzi.vcd
$date
	Fri Sep 18 20:43:40 2026
$end
$version
	Icarus Verilog
$end
$timescale
	1ps
$end
$scope module tb_pe_nrzi $end
$var wire 1 ! tx_wire $end
$var wire 1 " tx_lvl $end
$var wire 1 # rx_raw $end
$var wire 1 $ rx_lvl_unused $end
$var reg 1 % clk $end
$var reg 1 & rst_n $end
$var reg 1 ' rx_bypass $end
$var reg 1 ( rx_en $end
$var reg 1 ) rx_wire $end
$var reg 1 * tx_bypass $end
$var reg 1 + tx_en $end
$var reg 1 , tx_raw $end
$var reg 1 - wire_lvl $end
$var integer 32 . errors [31:0] $end
$var integer 32 / seed [31:0] $end
$scope module u_rx $end
$var wire 1 ( bit_en $end
$var wire 1 ' bypass $end
$var wire 1 % clk $end
$var wire 1 & rst_n $end
$var wire 1 ) rx_wire $end
$var wire 1 $ tx_lvl $end
$var wire 1 0 tx_raw $end
$var wire 1 1 tx_wire $end
$var wire 1 # rx_raw $end
$var reg 1 2 rx_level $end
$var reg 1 3 tx_level $end
$upscope $end
$scope module u_tx $end
$var wire 1 + bit_en $end
$var wire 1 * bypass $end
$var wire 1 % clk $end
$var wire 1 & rst_n $end
$var wire 1 4 rx_wire $end
$var wire 1 " tx_lvl $end
$var wire 1 , tx_raw $end
$var wire 1 ! tx_wire $end
$var wire 1 5 rx_raw $end
$var reg 1 6 rx_level $end
$var reg 1 7 tx_level $end
$upscope $end
$scope begin $ivl_for_loop3 $end
$var integer 32 8 t [31:0] $end
$scope begin $unm_blk_26 $end
$var reg 32 9 rv [31:0] $end
$var reg 1 : d $end
$scope begin $ivl_for_loop4 $end
$var integer 32 ; k [31:0] $end
$upscope $end
$upscope $end
$upscope $end
$scope begin $unm_blk_20 $end
$var reg 64 < v [63:0] $end
$var reg 1 = d $end
$scope begin $ivl_for_loop0 $end
$var integer 32 > k [31:0] $end
$upscope $end
$upscope $end
$scope begin $unm_blk_22 $end
$var reg 1 ? d $end
$scope begin $ivl_for_loop1 $end
$var integer 32 @ k [31:0] $end
$upscope $end
$upscope $end
$scope begin $unm_blk_24 $end
$var reg 1 A d $end
$scope begin $ivl_for_loop2 $end
$var integer 32 B k [31:0] $end
$upscope $end
$upscope $end
$scope task check $end
$upscope $end
$scope task send_bit $end
$upscope $end
$scope task strobe_rx $end
$upscope $end
$scope task strobe_tx $end
$upscope $end
$upscope $end
$enddefinitions $end
$comment Show the parameter values. $end
$dumpall
$end
#0
$dumpvars
b0 B
0A
b0 @
0?
b0 >
0=
bx <
b0 ;
0:
bx 9
b0 8
17
16
05
04
13
12
11
10
b101010 /
b0 .
0-
0,
0+
0*
0)
0(
0'
0&
0%
1$
0#
1"
1!
$end
#5000
1%
#10000
0%
#15000
1%
#20000
0%
#25000
1%
#26000
1&
#30000
0%
#35000
1%
#36000
1+
1,
b111111 >
b1011000111111110010101010000000011001100101010101110000101101001 <
#40000
0%
#45000
15
06
1%
#46000
0+
#47000
1#
1)
1-
#48000
1(
#50000
0%
#55000
1%
#56000
1+
0,
b111110 >
1=
0(
#60000
0%
#65000
0!
0"
07
1%
#66000
0+
#67000
0#
0)
0-
#68000
1(
#70000
0%
#75000
1#
02
1%
#76000
1+
1,
b111101 >
0=
0(
#80000
0%
#85000
1%
#86000
0+
#88000
1(
#90000
0%
#95000
1%
#96000
1+
b111100 >
1=
0(
#100000
0%
#105000
1%
#106000
0+
#108000
1(
#110000
0%
#115000
1%
#116000
1+
0,
b111011 >
0(
#120000
0%
#125000
1!
1"
17
1%
#126000
0+
#127000
0#
1)
1-
#128000
1(
#130000
0%
#135000
1#
12
1%
#136000
1+
b111010 >
0=
0(
#140000
0%
#145000
0!
0"
07
1%
#146000
0+
#147000
0#
0)
0-
#148000
1(
#150000
0%
#155000
1#
02
1%
#156000
1+
b111001 >
0(
#160000
0%
#165000
1!
1"
17
1%
#166000
0+
#167000
0#
1)
1-
#168000
1(
#170000
0%
#175000
1#
12
1%
#176000
1+
1,
b111000 >
0(
#180000
0%
#185000
1%
#186000
0+
#188000
1(
#190000
0%
#195000
1%
#196000
1+
b110111 >
1=
0(
#200000
0%
#205000
1%
#206000
0+
#208000
1(
#210000
0%
#215000
1%
#216000
1+
b110110 >
0(
#220000
0%
#225000
1%
#226000
0+
#228000
1(
#230000
0%
#235000
1%
#236000
1+
b110101 >
0(
#240000
0%
#245000
1%
#246000
0+
#248000
1(
#250000
0%
#255000
1%
#256000
1+
b110100 >
0(
#260000
0%
#265000
1%
#266000
0+
#268000
1(
#270000
0%
#275000
1%
#276000
1+
b110011 >
0(
#280000
0%
#285000
1%
#286000
0+
#288000
1(
#290000
0%
#295000
1%
#296000
1+
b110010 >
0(
#300000
0%
#305000
1%
#306000
0+
#308000
1(
#310000
0%
#315000
1%
#316000
1+
b110001 >
0(
#320000
0%
#325000
1%
#326000
0+
#328000
1(
#330000
0%
#335000
1%
#336000
1+
0,
b110000 >
0(
#340000
0%
#345000
0!
0"
07
1%
#346000
0+
#347000
0#
0)
0-
#348000
1(
#350000
0%
#355000
1#
02
1%
#356000
1+
b101111 >
0=
0(
#360000
0%
#365000
1!
1"
17
1%
#366000
0+
#367000
0#
1)
1-
#368000
1(
#370000
0%
#375000
1#
12
1%
#376000
1+
1,
b101110 >
0(
#380000
0%
#385000
1%
#386000
0+
#388000
1(
#390000
0%
#395000
1%
#396000
1+
0,
b101101 >
1=
0(
#400000
0%
#405000
0!
0"
07
1%
#406000
0+
#407000
0#
0)
0-
#408000
1(
#410000
0%
#415000
1#
02
1%
#416000
1+
1,
b101100 >
0=
0(
#420000
0%
#425000
1%
#426000
0+
#428000
1(
#430000
0%
#435000
1%
#436000
1+
0,
b101011 >
1=
0(
#440000
0%
#445000
1!
1"
17
1%
#446000
0+
#447000
0#
1)
1-
#448000
1(
#450000
0%
#455000
1#
12
1%
#456000
1+
1,
b101010 >
0=
0(
#460000
0%
#465000
1%
#466000
0+
#468000
1(
#470000
0%
#475000
1%
#476000
1+
0,
b101001 >
1=
0(
#480000
0%
#485000
0!
0"
07
1%
#486000
0+
#487000
0#
0)
0-
#488000
1(
#490000
0%
#495000
1#
02
1%
#496000
1+
1,
b101000 >
0=
0(
#500000
0%
#505000
1%
#506000
0+
#508000
1(
#510000
0%
#515000
1%
#516000
1+
0,
b100111 >
1=
0(
#520000
0%
#525000
1!
1"
17
1%
#526000
0+
#527000
0#
1)
1-
#528000
1(
#530000
0%
#535000
1#
12
1%
#536000
1+
b100110 >
0=
0(
#540000
0%
#545000
0!
0"
07
1%
#546000
0+
#547000
0#
0)
0-
#548000
1(
#550000
0%
#555000
1#
02
1%
#556000
1+
b100101 >
0(
#560000
0%
#565000
1!
1"
17
1%
#566000
0+
#567000
0#
1)
1-
#568000
1(
#570000
0%
#575000
1#
12
1%
#576000
1+
b100100 >
0(
#580000
0%
#585000
0!
0"
07
1%
#586000
0+
#587000
0#
0)
0-
#588000
1(
#590000
0%
#595000
1#
02
1%
#596000
1+
b100011 >
0(
#600000
0%
#605000
1!
1"
17
1%
#606000
0+
#607000
0#
1)
1-
#608000
1(
#610000
0%
#615000
1#
12
1%
#616000
1+
b100010 >
0(
#620000
0%
#625000
0!
0"
07
1%
#626000
0+
#627000
0#
0)
0-
#628000
1(
#630000
0%
#635000
1#
02
1%
#636000
1+
b100001 >
0(
#640000
0%
#645000
1!
1"
17
1%
#646000
0+
#647000
0#
1)
1-
#648000
1(
#650000
0%
#655000
1#
12
1%
#656000
1+
b100000 >
0(
#660000
0%
#665000
0!
0"
07
1%
#666000
0+
#667000
0#
0)
0-
#668000
1(
#670000
0%
#675000
1#
02
1%
#676000
1+
1,
b11111 >
0(
#680000
0%
#685000
1%
#686000
0+
#688000
1(
#690000
0%
#695000
1%
#696000
1+
b11110 >
1=
0(
#700000
0%
#705000
1%
#706000
0+
#708000
1(
#710000
0%
#715000
1%
#716000
1+
0,
b11101 >
0(
#720000
0%
#725000
1!
1"
17
1%
#726000
0+
#727000
0#
1)
1-
#728000
1(
#730000
0%
#735000
1#
12
1%
#736000
1+
b11100 >
0=
0(
#740000
0%
#745000
0!
0"
07
1%
#746000
0+
#747000
0#
0)
0-
#748000
1(
#750000
0%
#755000
1#
02
1%
#756000
1+
1,
b11011 >
0(
#760000
0%
#765000
1%
#766000
0+
#768000
1(
#770000
0%
#775000
1%
#776000
1+
b11010 >
1=
0(
#780000
0%
#785000
1%
#786000
0+
#788000
1(
#790000
0%
#795000
1%
#796000
1+
0,
b11001 >
0(
#800000
0%
#805000
1!
1"
17
1%
#806000
0+
#807000
0#
1)
1-
#808000
1(
#810000
0%
#815000
1#
12
1%
#816000
1+
b11000 >
0=
0(
#820000
0%
#825000
0!
0"
07
1%
#826000
0+
#827000
0#
0)
0-
#828000
1(
#830000
0%
#835000
1#
02
1%
#836000
1+
1,
b10111 >
0(
#840000
0%
#845000
1%
#846000
0+
#848000
1(
#850000
0%
#855000
1%
#856000
1+
0,
b10110 >
1=
0(
#860000
0%
#865000
1!
1"
17
1%
#866000
0+
#867000
0#
1)
1-
#868000
1(
#870000
0%
#875000
1#
12
1%
#876000
1+
1,
b10101 >
0=
0(
#880000
0%
#885000
1%
#886000
0+
#888000
1(
#890000
0%
#895000
1%
#896000
1+
0,
b10100 >
1=
0(
#900000
0%
#905000
0!
0"
07
1%
#906000
0+
#907000
0#
0)
0-
#908000
1(
#910000
0%
#915000
1#
02
1%
#916000
1+
1,
b10011 >
0=
0(
#920000
0%
#925000
1%
#926000
0+
#928000
1(
#930000
0%
#935000
1%
#936000
1+
0,
b10010 >
1=
0(
#940000
0%
#945000
1!
1"
17
1%
#946000
0+
#947000
0#
1)
1-
#948000
1(
#950000
0%
#955000
1#
12
1%
#956000
1+
1,
b10001 >
0=
0(
#960000
0%
#965000
1%
#966000
0+
#968000
1(
#970000
0%
#975000
1%
#976000
1+
0,
b10000 >
1=
0(
#980000
0%
#985000
0!
0"
07
1%
#986000
0+
#987000
0#
0)
0-
#988000
1(
#990000
0%
#995000
1#
02
1%
#996000
1+
1,
b1111 >
0=
0(
#1000000
0%
#1005000
1%
#1006000
0+
#1008000
1(
#1010000
0%
#1015000
1%
#1016000
1+
b1110 >
1=
0(
#1020000
0%
#1025000
1%
#1026000
0+
#1028000
1(
#1030000
0%
#1035000
1%
#1036000
1+
b1101 >
0(
#1040000
0%
#1045000
1%
#1046000
0+
#1048000
1(
#1050000
0%
#1055000
1%
#1056000
1+
0,
b1100 >
0(
#1060000
0%
#1065000
1!
1"
17
1%
#1066000
0+
#1067000
0#
1)
1-
#1068000
1(
#1070000
0%
#1075000
1#
12
1%
#1076000
1+
b1011 >
0=
0(
#1080000
0%
#1085000
0!
0"
07
1%
#1086000
0+
#1087000
0#
0)
0-
#1088000
1(
#1090000
0%
#1095000
1#
02
1%
#1096000
1+
b1010 >
0(
#1100000
0%
#1105000
1!
1"
17
1%
#1106000
0+
#1107000
0#
1)
1-
#1108000
1(
#1110000
0%
#1115000
1#
12
1%
#1116000
1+
b1001 >
0(
#1120000
0%
#1125000
0!
0"
07
1%
#1126000
0+
#1127000
0#
0)
0-
#1128000
1(
#1130000
0%
#1135000
1#
02
1%
#1136000
1+
1,
b1000 >
0(
#1140000
0%
#1145000
1%
#1146000
0+
#1148000
1(
#1150000
0%
#1155000
1%
#1156000
1+
0,
b111 >
1=
0(
#1160000
0%
#1165000
1!
1"
17
1%
#1166000
0+
#1167000
0#
1)
1-
#1168000
1(
#1170000
0%
#1175000
1#
12
1%
#1176000
1+
1,
b110 >
0=
0(
#1180000
0%
#1185000
1%
#1186000
0+
#1188000
1(
#1190000
0%
#1195000
1%
#1196000
1+
b101 >
1=
0(
#1200000
0%
#1205000
1%
#1206000
0+
#1208000
1(
#1210000
0%
#1215000
1%
#1216000
1+
0,
b100 >
0(
#1220000
0%
#1225000
0!
0"
07
1%
#1226000
0+
#1227000
0#
0)
0-
#1228000
1(
#1230000
0%
#1235000
1#
02
1%
#1236000
1+
1,
b11 >
0=
0(
#1240000
0%
#1245000
1%
#1246000
0+
#1248000
1(
#1250000
0%
#1255000
1%
#1256000
1+
0,
b10 >
1=
0(
#1260000
0%
#1265000
1!
1"
17
1%
#1266000
0+
#1267000
0#
1)
1-
#1268000
1(
#1270000
0%
#1275000
1#
12
1%
#1276000
1+
b1 >
0=
0(
#1280000
0%
#1285000
0!
0"
07
1%
#1286000
0+
#1287000
0#
0)
0-
#1288000
1(
#1290000
0%
#1295000
1#
02
1%
#1296000
1+
1,
b0 >
0(
#1300000
0%
#1305000
1%
#1306000
0+
#1308000
1(
#1310000
0%
#1315000
1%
#1316000
1+
b11111111111111111111111111111111 >
1=
0(
#1320000
0%
#1325000
1%
#1326000
0+
#1328000
1(
#1330000
0%
#1335000
1%
#1336000
1+
b1 @
1?
0(
#1340000
0%
#1345000
1%
#1346000
0+
#1348000
1(
#1350000
0%
#1355000
1%
#1356000
1+
b10 @
0(
#1360000
0%
#1365000
1%
#1366000
0+
#1368000
1(
#1370000
0%
#1375000
1%
#1376000
1+
b11 @
0(
#1380000
0%
#1385000
1%
#1386000
0+
#1388000
1(
#1390000
0%
#1395000
1%
#1396000
1+
b100 @
0(
#1400000
0%
#1405000
1%
#1406000
0+
#1408000
1(
#1410000
0%
#1415000
1%
#1416000
1+
b101 @
0(
#1420000
0%
#1425000
1%
#1426000
0+
#1428000
1(
#1430000
0%
#1435000
1%
#1436000
1+
b110 @
0(
#1440000
0%
#1445000
1%
#1446000
0+
#1448000
1(
#1450000
0%
#1455000
1%
#1456000
1+
b111 @
0(
#1460000
0%
#1465000
1%
#1466000
0+
#1468000
1(
#1470000
0%
#1475000
1%
#1476000
1+
b1000 @
0(
#1480000
0%
#1485000
1%
#1486000
0+
#1488000
1(
#1490000
0%
#1495000
1%
#1496000
1+
b1001 @
0(
#1500000
0%
#1505000
1%
#1506000
0+
#1508000
1(
#1510000
0%
#1515000
1%
#1516000
1+
b1010 @
0(
#1520000
0%
#1525000
1%
#1526000
0+
#1528000
1(
#1530000
0%
#1535000
1%
#1536000
1+
b1011 @
0(
#1540000
0%
#1545000
1%
#1546000
0+
#1548000
1(
#1550000
0%
#1555000
1%
#1556000
1+
b1100 @
0(
#1560000
0%
#1565000
1%
#1566000
0+
#1568000
1(
#1570000
0%
#1575000
1%
#1576000
1+
b1101 @
0(
#1580000
0%
#1585000
1%
#1586000
0+
#1588000
1(
#1590000
0%
#1595000
1%
#1596000
1+
b1110 @
0(
#1600000
0%
#1605000
1%
#1606000
0+
#1608000
1(
#1610000
0%
#1615000
1%
#1616000
1+
b1111 @
0(
#1620000
0%
#1625000
1%
#1626000
0+
#1628000
1(
#1630000
0%
