rtl/pe_serdes.v
// pe_serdes.v — protocol-emulator shared serializer / deserializer.
// Signal meanings: wiki/reference/signal-names.md#pe_serdes
//
// One shift engine serves every target protocol (UART, SPI, I2C, JTAG, SWD,
// PS/2, CAN, USB-LS, 10BASE-T): firmware works at the word level, this block
// handles bit order and bit counting.
//
// * Bit order is SNAPSHOT at tx_load / rx_start into per-side registers, so
//   cfg_lsb_first may be rewritten by the core at any time without
//   corrupting an in-flight transfer (cfg = 1 UART LSB-first, 0 SPI-style).
// * Transfer length 1..MAXLEN bits, captured on load/start. Lengths above
//   MAXLEN or 0 are out of contract (0 is ignored; >MAXLEN is not clamped).
// * bit_en is the per-bit-cell strobe from the core/DRU timing logic.
//   The RX serial input is expected to be already synchronized (latch-pair
//   dual-edge capture flop, ADR-002); this block is single-edge.
// * tx_ser idles HIGH (suits UART; SPI is CS-gated; I2C/SWD direction is
//   handled by the pin-matrix OE logic, not here).
// * A load/start while busy restarts the transfer (start on the final bit
//   cell drops that bit; start one cycle later still completes the word).
// * Valid RX payload lands in rx_data[rx_len-1:0]: first-received bit sits
//   at [0] when LSB-first, at [rx_len-1] when MSB-first.
// * RX completion is delayed one cycle from the final strobe (rx_busy drops
//   first, rx_valid/rx_data follow) so rx_data can copy rx_shreg directly
//   instead of paying for a variable-shift forward path.
// * Parameter constraint: MAXLEN >= 2 (IDXW would otherwise be 0).

module pe_serdes #(
  parameter int MAXLEN = 32,
  parameter int LENW   = $clog2(MAXLEN + 1),
  parameter int IDXW   = $clog2(MAXLEN)
) (
  input  logic                 clk,
  input  logic                 rst_n,

  input  logic                 cfg_lsb_first,
  input  logic                 bit_en,

  // Transmit side
  input  logic                 tx_load,
  input  logic [MAXLEN-1:0]    tx_data,
  input  logic [LENW-1:0]      tx_len,
  output logic                 tx_ser,
  output logic                 tx_busy,
  output logic                 tx_done,

  // Receive side
  input  logic                 rx_ser,
  input  logic                 rx_start,
  input  logic [LENW-1:0]      rx_len,
  output logic [MAXLEN-1:0]    rx_data,
  output logic                 rx_busy,
  output logic                 rx_valid
);

  // Elaboration guard: MAXLEN=1 would make IDXW=0 (illegal range).
  if (IDXW < 1) $error("pe_serdes: MAXLEN must be >= 2");

  // ---------------- Transmit ----------------
  logic [MAXLEN-1:0] tx_shreg;
  logic [LENW-1:0]   tx_nbits;   // snapshot of tx_len at load
  logic [LENW-1:0]   tx_cnt;     // index of the bit currently on tx_ser
  logic              cfg_lsb_tx; // snapshot of cfg_lsb_first at load

  // Index width only needs $clog2(MAXLEN); LENW expressions truncate cleanly.
  logic [IDXW-1:0] tx_rd_idx;
  assign tx_rd_idx = cfg_lsb_tx
    ? IDXW'(tx_cnt)
    : IDXW'(tx_nbits - 1'b1 - tx_cnt);
  assign tx_ser = tx_busy ? tx_shreg[tx_rd_idx] : 1'b1;

  always_ff @(posedge clk or negedge rst_n) begin
    if (!rst_n) begin
      tx_shreg   <= '0;
      tx_nbits   <= '0;
      tx_cnt     <= '0;
      cfg_lsb_tx <= 1'b0;
      tx_busy    <= 1'b0;
      tx_done    <= 1'b0;
    end else begin
      tx_done <= 1'b0;
      if (tx_load && (|tx_len)) begin
        tx_shreg   <= tx_data;
        tx_nbits   <= tx_len;
        tx_cnt     <= '0;
        cfg_lsb_tx <= cfg_lsb_first;
        tx_busy    <= 1'b1;
      end else if (bit_en && tx_busy) begin
        if (tx_cnt == tx_nbits - 1'b1) begin
          tx_busy <= 1'b0;
          tx_done <= 1'b1;
        end else begin
          tx_cnt <= tx_cnt + 1'b1;
        end
      end
    end
  end

  // ---------------- Receive ----------------
  // Bit-placer (not a shifter): bit k of the transfer is written straight
  // to rx_shreg[pos], with pos counting 0..len-1 when LSB-first and
  // len-1..0 when MSB-first. Payload always ends up in [len-1:0].
  logic [MAXLEN-1:0] rx_shreg;
  logic [LENW-1:0]   rx_nbits;   // snapshot of rx_len at start
  logic [LENW-1:0]   rx_cnt;     // number of bits captured so far
  logic [IDXW-1:0]   rx_pos;     // write position for the incoming bit
  logic              cfg_lsb_rx; // snapshot of cfg_lsb_first at start
  logic              rx_fin;     // final bit seen; complete next cycle

  always_ff @(posedge clk or negedge rst_n) begin
    if (!rst_n) begin
      rx_shreg   <= '0;
      rx_nbits   <= '0;
      rx_cnt     <= '0;
      rx_pos     <= '0;
      cfg_lsb_rx <= 1'b0;
      rx_fin     <= 1'b0;
      rx_data    <= '0;
      rx_busy    <= 1'b0;
      rx_valid   <= 1'b0;
    end else begin
      rx_valid <= 1'b0;
      // Delayed completion: rx_shreg holds the full word by now, so the
      // copy needs no variable-shift forward path. Deliberately ordered
      // before rx_start handling so a start on this exact cycle still
      // delivers the old word (no register conflict: disjoint targets).
      if (rx_fin) begin
        rx_fin   <= 1'b0;
        rx_valid <= 1'b1;
        rx_data  <= rx_shreg;
      end
      if (rx_start && (|rx_len)) begin
        rx_shreg   <= '0;
        rx_nbits   <= rx_len;
        rx_cnt     <= '0;
        rx_pos     <= cfg_lsb_first ? '0 : IDXW'(rx_len - 1'b1);
        cfg_lsb_rx <= cfg_lsb_first;
        rx_busy    <= 1'b1;
      end else if (bit_en && rx_busy) begin
        rx_shreg[rx_pos] <= rx_ser;
        if (rx_cnt == rx_nbits - 1'b1) begin
          rx_busy <= 1'b0;
          rx_fin  <= 1'b1;
        end else begin
          rx_cnt <= rx_cnt + 1'b1;
          rx_pos <= cfg_lsb_rx ? rx_pos + 1'b1 : rx_pos - 1'b1;
        end
      end
    end
  end

endmodule

tb/tb_pe_eth.v
// tb_pe_eth.v — 10BASE-T Manchester framing around pe_serdes.
//
// Manchester (802.3): 0 = H->L mid-bit, 1 = L->H. Preamble (56
// alternating) + SFD + MAC frame. The SERDES carries ONE 32-bit word
// (4 bytes, MSB-first) per transfer — longer payloads chunk per word,
// which is how the core drives it. FCS/CRC-32 is computed in the model
// (hardware LFSR block's job, not the SERDES').

`timescale 1ns / 1ps

module tb_pe_eth;

  localparam int MAXLEN = 32;
  localparam int LENW = $clog2(MAXLEN + 1);
  localparam int H = 8;

  logic              clk, rst_n;
  logic              cfg_lsb_first, bit_en;
  logic              tx_load, tx_ser, tx_busy, tx_done;
  logic [MAXLEN-1:0] tx_data;
  logic [LENW-1:0]   tx_len;
  logic              rx_ser, rx_start, rx_busy, rx_valid;
  logic [MAXLEN-1:0] rx_data;
  logic [LENW-1:0]   rx_len;
  logic              wire_lvl;

  pe_serdes #(.MAXLEN(MAXLEN)) dut (.*);

  initial clk = 0;
  always #5 clk = ~clk;

  integer errors = 0;

  logic tx_done_seen, rx_valid_seen;
  always @(posedge clk or negedge rst_n)
    if (!rst_n) begin tx_done_seen <= 0; rx_valid_seen <= 0; end
    else begin
      if (tx_done)  tx_done_seen  <= 1'b1;
      if (rx_valid) rx_valid_seen <= 1'b1;
    end

  task automatic check(input bit c, input string m);
    if (!c) begin $display("FAIL: %s @%0t", m, $time); errors++; end
  endtask

  task automatic bit_cell();
    repeat (H) @(posedge clk); #1;
  endtask

  task automatic man_send(input bit b);
    if (b == 1'b0) begin
      wire_lvl = 1'b1; bit_cell();
      wire_lvl = 1'b0; bit_cell();  // H->L mid-bit
    end else begin
      wire_lvl = 1'b0; bit_cell();
      wire_lvl = 1'b1; bit_cell();  // L->H mid-bit
    end
  endtask

  // CRC-32 (FCS: reflected, init FFFFFFFF, final xor).
  function automatic [31:0] crc32(input [127:0] bits, input int n);
    logic [31:0] crc;
    logic b, fb;
    crc = 32'hFFFFFFFF;
    for (int i = n - 1; i >= 0; i--) begin
      b   = bits[i];
      fb  = b ^ crc[0];
      crc = {1'b0, crc[31:1]};
      if (fb) crc ^= 32'hEDB88320;
    end
    return ~crc;
  endfunction

  // One frame: preamble + SFD + dst/src/len header + 4-byte payload
  // (one SERDES word, MSB-first) + FCS. Loopback checks payload.
  logic [127:0] fcs_seq;
  int           fcs_n;
  logic [31:0]  fcs;

  task automatic eth_frame(input [31:0] payload, input string tag);
    for (int i = 0; i < 28; i++) begin
      man_send(1'b1); man_send(1'b0);  // preamble
    end
    man_send(1'b1); man_send(1'b1);    // SFD
    fcs_seq = '0; fcs_n = 0;
    for (int i = 0; i < 6; i++)         // dst FF:FF:FF:FF:FF:FF
      for (int k = 7; k >= 0; k--) begin
        fcs_seq[fcs_n++] = 1'b1; man_send(1'b1);
      end
    for (int i = 0; i < 6; i++)         // src 02:00:00:00:00:00
      for (int k = 7; k >= 0; k--) begin
        fcs_seq[fcs_n++] = (i == 0 && k == 1);
        man_send((i == 0 && k == 1));
      end
    for (int k = 15; k >= 0; k--) begin // length = 4
      fcs_seq[fcs_n++] = (k == 2);      // 0x0004
      man_send((k == 2));
    end
    // payload: one 32-bit SERDES word, MSB-first
    @(posedge clk); #1;
    cfg_lsb_first = 1'b0;
    tx_data = payload; tx_len = 32; tx_load = 1'b1;
    rx_len = 32; rx_start = 1'b1;
    tx_done_seen = 1'b0; rx_valid_seen = 1'b0;
    @(posedge clk); #1; tx_load = 1'b0; rx_start = 1'b0;
    for (int k = 31; k >= 0; k--) begin
      rx_ser = tx_ser;  // loopback at the bit level
      fcs_seq[fcs_n++] = tx_ser;
      man_send(tx_ser);
      bit_en = 1'b1; @(posedge clk); #1; bit_en = 1'b0;
    end
    // FCS on the wire
    fcs = crc32(fcs_seq, fcs_n);
    for (int k = 31; k >= 0; k--) man_send(fcs[k]);
    // IPG
    wire_lvl = 1'b0; repeat (8) bit_cell();

    repeat (2) @(posedge clk); #1;
    check(rx_valid_seen === 1'b1, {tag, ": rx_valid"});
    check(tx_done_seen === 1'b1, {tag, ": tx_done"});
    check(rx_data[31:0] === payload, {tag, ": payload word"});
  endtask

  initial begin
    $dumpfile("tb_pe_eth.vcd");
    $dumpvars(0, tb_pe_eth);
    rst_n = 0; wire_lvl = 0; bit_en = 0;
    cfg_lsb_first = 0; tx_load = 0; tx_data = 0; tx_len = 0;
    rx_ser = 0; rx_start = 0; rx_len = 0; fcs_seq = '0; fcs_n = 0;
    repeat (3) @(posedge clk); #1; rst_n = 1;
    @(posedge clk); #1;

    eth_frame(32'h11223344, "eth w1");
    eth_frame(32'h000000FF, "eth w2");
    eth_frame(32'hFFFFFFFF, "eth w3");
    eth_frame(32'h80000001, "eth w4");

    if (errors == 0) $display("PASS: tb_pe_eth");
    else $display("FAILURES: %0d", errors);
    $finish;
  end

endmodule

sim/tb_pe_eth.vcd
$date
	Fri Sep 18 10:36:06 2026
$end
$version
	Icarus Verilog
$end
$timescale
	1ps
$end
$scope module tb_pe_eth $end
$var wire 1 ! tx_ser $end
$var wire 1 " tx_done $end
$var wire 1 # tx_busy $end
$var wire 1 $ rx_valid $end
$var wire 32 % rx_data [31:0] $end
$var wire 1 & rx_busy $end
$var parameter 32 ' H $end
$var parameter 32 ( LENW $end
$var parameter 32 ) MAXLEN $end
$var reg 1 * bit_en $end
$var reg 1 + cfg_lsb_first $end
$var reg 1 , clk $end
$var reg 32 - fcs [31:0] $end
$var reg 128 . fcs_seq [127:0] $end
$var reg 1 / rst_n $end
$var reg 6 0 rx_len [5:0] $end
$var reg 1 1 rx_ser $end
$var reg 1 2 rx_start $end
$var reg 1 3 rx_valid_seen $end
$var reg 32 4 tx_data [31:0] $end
$var reg 1 5 tx_done_seen $end
$var reg 6 6 tx_len [5:0] $end
$var reg 1 7 tx_load $end
$var reg 1 8 wire_lvl $end
$var integer 32 9 errors [31:0] $end
$var integer 32 : fcs_n [31:0] $end
$scope function crc32 $end
$scope begin $ivl_for_loop0 $end
$upscope $end
$upscope $end
$scope module dut $end
$var wire 1 * bit_en $end
$var wire 1 + cfg_lsb_first $end
$var wire 1 , clk $end
$var wire 1 / rst_n $end
$var wire 6 ; rx_len [5:0] $end
$var wire 1 1 rx_ser $end
$var wire 1 2 rx_start $end
$var wire 32 < tx_data [31:0] $end
$var wire 6 = tx_len [5:0] $end
$var wire 1 7 tx_load $end
$var wire 1 ! tx_ser $end
$var wire 5 > tx_rd_idx [4:0] $end
$var parameter 32 ? IDXW $end
$var parameter 32 @ LENW $end
$var parameter 32 A MAXLEN $end
$var reg 1 B cfg_lsb_rx $end
$var reg 1 C cfg_lsb_tx $end
$var reg 1 & rx_busy $end
$var reg 6 D rx_cnt [5:0] $end
$var reg 32 E rx_data [31:0] $end
$var reg 1 F rx_fin $end
$var reg 6 G rx_nbits [5:0] $end
$var reg 5 H rx_pos [4:0] $end
$var reg 32 I rx_shreg [31:0] $end
$var reg 1 $ rx_valid $end
$var reg 1 # tx_busy $end
$var reg 6 J tx_cnt [5:0] $end
$var reg 1 " tx_done $end
$var reg 6 K tx_nbits [5:0] $end
$var reg 32 L tx_shreg [31:0] $end
$upscope $end
$scope task bit_cell $end
$upscope $end
$scope task check $end
$upscope $end
$scope task eth_frame $end
$scope begin $ivl_for_loop1 $end
$upscope $end
$scope begin $ivl_for_loop2 $end
$scope begin $ivl_for_loop3 $end
$upscope $end
$upscope $end
$scope begin $ivl_for_loop4 $end
$scope begin $ivl_for_loop5 $end
$upscope $end
$upscope $end
$scope begin $ivl_for_loop6 $end
$upscope $end
$scope begin $ivl_for_loop7 $end
$upscope $end
$scope begin $ivl_for_loop8 $end
$upscope $end
$upscope $end
$scope task man_send $end
$upscope $end
$upscope $end
$enddefinitions $end
$comment Show the parameter values. $end
$dumpall
b100000 A
b110 @
b101 ?
b100000 )
b110 (
b1000 '
$end
#0
$dumpvars
b0 L
b0 K
b0 J
b0 I
b0 H
b0 G
0F
b0 E
b0 D
0C
0B
b11111 >
b0 =
b0 <
b0 ;
b0 :
b0 9
08
07
b0 6
05
b0 4
03
02
01
b0 0
0/
b0 .
bx -
0,
0+
0*
0&
b0 %
0$
0#
0"
1!
$end
#5000
1,
#10000
0,
#15000
1,
#20000
0,
#25000
1,
#26000
1/
#30000
0,
#35000
1,
#40000
0,
#45000
1,
#50000
0,
#55000
1,
#60000
0,
#65000
1,
#70000
0,
#75000
1,
#80000
0,
#85000
1,
#90000
0,
#95000
1,
#100000
0,
#105000
1,
#110000
0,
#115000
1,
#116000
18
#120000
0,
#125000
1,
#130000
0,
#135000
1,
#140000
0,
#145000
1,
#150000
0,
#155000
1,
#160000
0,
#165000
1,
#170000
0,
#175000
1,
#180000
0,
#185000
1,
#190000
0,
#195000
1,
#200000
0,
#205000
1,
#210000
0,
#215000
1,
#220000
0,
#225000
1,
#230000
0,
#235000
1,
#240000
0,
#245000
1,
#250000
0,
#255000
1,
#260000
0,
#265000
1,
#270000
0,
#275000
1,
#276000
08
#280000
0,
#285000
1,
#290000
0,
#295000
1,
#300000
0,
#305000
1,
#310000
0,
#315000
1,
#320000
0,
#325000
1,
#330000
0,
#335000
1,
#340000
0,
#345000
1,
#350000
0,
#355000
1,
#360000
0,
#365000
1,
#370000
0,
#375000
1,
#380000
0,
#385000
1,
#390000
0,
#395000
1,
#400000
0,
#405000
1,
#410000
0,
#415000
1,
#420000
0,
#425000
1,
#430000
0,
#435000
1,
#436000
18
#440000
0,
#445000
1,
#450000
0,
#455000
1,
#460000
0,
#465000
1,
#470000
0,
#475000
1,
#480000
0,
#485000
1,
#490000
0,
#495000
1,
#500000
0,
#505000
1,
#510000
0,
#515000
1,
#520000
0,
#525000
1,
#530000
0,
#535000
1,
#540000
0,
#545000
1,
#550000
0,
#555000
1,
#560000
0,
#565000
1,
#570000
0,
#575000
1,
#580000
0,
#585000
1,
#590000
0,
#595000
1,
#596000
08
#600000
0,
#605000
1,
#610000
0,
#615000
1,
#620000
0,
#625000
1,
#630000
0,
#635000
1,
#640000
0,
#645000
1,
#650000
0,
#655000
1,
#660000
0,
#665000
1,
#670000
0,
#675000
1,
#680000
0,
#685000
1,
#690000
0,
#695000
1,
#700000
0,
#705000
1,
#710000
0,
#715000
1,
#720000
0,
#725000
1,
#730000
0,
#735000
1,
#740000
0,
#745000
1,
#750000
0,
#755000
1,
#756000
18
#760000
0,
#765000
1,
#770000
0,
#775000
1,
#780000
0,
#785000
1,
#790000
0,
#795000
1,
#800000
0,
#805000
1,
#810000
0,
#815000
1,
#820000
0,
#825000
1,
#830000
0,
#835000
1,
#840000
0,
#845000
1,
#850000
0,
#855000
1,
#860000
0,
#865000
1,
#870000
0,
#875000
1,
#880000
0,
#885000
1,
#890000
0,
#895000
1,
#900000
0,
#905000
1,
#910000
0,
#915000
1,
#916000
08
#920000
0,
#925000
1,
#930000
0,
#935000
1,
#940000
0,
#945000
1,
#950000
0,
#955000
1,
#960000
0,
#965000
1,
#970000
0,
#975000
1,
#980000
0,
#985000
1,
#990000
0,
#995000
1,
#1000000
0,
#1005000
1,
#1010000
0,
#1015000
1,
#1020000
0,
#1025000
1,
#1030000
0,
#1035000
1,
#1040000
0,
#1045000
1,
#1050000
0,
#1055000
1,
#1060000
0,
#1065000
1,
#1070000
0,
#1075000
1,
#1076000
18
#1080000
0,
#1085000
1,
#1090000
0,
#1095000
1,
#1100000
0,
#1105000
1,
#1110000
0,
#1115000
1,
#1120000
0,
#1125000
1,
#1130000
0,
#1135000
1,
#1140000
0,
#1145000
1,
#1150000
0,
#1155000
1,
#1160000
0,
#1165000
1,
#1170000
0,
#1175000
1,
#1180000
0,
#1185000
1,
#1190000
0,
#1195000
1,
#1200000
0,
#1205000
1,
#1210000
0,
#1215000
1,
#1220000
0,
#1225000
1,
#1230000
0,
#1235000
1,
#1236000
08
#1240000
0,
#1245000
1,
#1250000
0,
#1255000
1,
#1260000
0,
#1265000
1,
#1270000
0,
#1275000
1,
#1280000
0,
#1285000
1,
#1290000
0,
#1295000
1,
#1300000
0,
#1305000
1,
#1310000
0,
#1315000
1,
#1320000
0,
#1325000
1,
#1330000
0,
#1335000
1,
#1340000
0,
#1345000
1,
#1350000
0,
#1355000
1,
#1360000
0,
#1365000
1,
#1370000
0,
#1375000
1,
#1380000
0,
#1385000
1,
#1390000
0,
#1395000
1,
#1396000
18
#1400000
0,
#1405000
1,
#1410000
0,
#1415000
1,
#1420000
0,
#1425000
1,
#1430000
0,
#1435000
1,
#1440000
0,
#1445000
1,
#1450000
0,
#1455000
1,
#1460000
0,
#1465000
1,
#1470000
0,
#1475000
1,
#1480000
0,
#1485000
1,
#1490000
0,
#1495000
1,
#1500000
0,
#1505000
1,
#1510000
0,
#1515000
1,
#1520000
0,
#1525000
1,
#1530000
0,
#1535000
1,
#1540000
0,
#1545000
1,
#1550000
0,
#1555000
1,
#1556000
08
#1560000
0,
#1565000
1,
#1570000
0,
#1575000
1,
#1580000
0,
#1585000
1,
#1590000
0,
#1595000
1,
#1600000
0,
#1605000
1,
#1610000
0,
#1615000
1,
#1620000
0,
#1625000
1,
#1630000
0,
#1635000
1,
#1640000
0,
#1645000
1,
#1650000
0,
#1655000
1,
#1660000
0,
#1665000
1,
#1670000
0,
#1675000
1,
#1680000
0,
#1685000
1,
#1690000
0,
#1695000
1,
#1700000
0,
#1705000
1,
#1710000
0,
#1715000
1,
#1716000
18
#1720000
0,
#1725000
1,
#1730000
0,
#1735000
1,
#1740000
0,
#1745000
1,
#1750000
0,
#1755000
1,
#1760000
0,
#1765000
1,
#1770000
0,
#1775000
1,
#1780000
0,
#1785000
1,
#1790000
0,
#1795000
1,
#1800000
0,
#1805000
1,
#1810000
0,
#1815000
1,
#1820000
0,
#1825000
1,
#1830000
0,
#1835000
1,
#1840000
0,
#1845000
1,
#1850000
0,
#1855000
1,
#1860000
0,
#1865000
1,
#1870000
0,
#1875000
1,
#1876000
08
#1880000
0,
#1885000
1,
#1890000
0,
#1895000
1,
#1900000
0,
#1905000
1,
#1910000
0,
#1915000
1,
#1920000
0,
#1925000
1,
#1930000
0,
#1935000
1,
#1940000
0,
#1945000
1,
#1950000
0,
#1955000
1,
#1960000
0,
#1965000
1,
#1970000
0,
#1975000
1,
#1980000
0,
#1985000
1,
#1990000
0,
#1995000
1,
#2000000
0,
#2005000
1,
#2010000
0,
#2015000
1,
#2020000
0,
#2025000
1,
#2030000
0,
#2035000
1,
#2036000
18
#2040000
0,
#2045000
1,
#2050000
0,
#2055000
1,
#2060000
0,
#2065000
1,
#2070000
0,
#2075000
1,
#2080000
0,
#2085000
1,
#2090000
0,
#2095000
1,
#2100000
0,
#2105000
1,
#2110000
0,
#2115000
1,
#2120000
0,
#2125000
1,
#2130000
0,
#2135000
1,
#2140000
0,
#2145000
1,
#2150000
0,
#2155000
1,
#2160000
0,
#2165000
1,
#2170000
0,
#2175000
1,
#2180000
0,
#2185000
1,
#2190000
0,
#2195000
1,
#2196000
08
#2200000
0,
#2205000
1,
#2210000
0,
#2215000
1,
#2220000
0,
#2225000
1,
#2230000
0,
#2235000
1,
#2240000
0,
#2245000
1,
#2250000
0,
#2255000
1,
#2260000
0,
#2265000
1,
#2270000
0,
#2275000
1,
#2280000
0,
#2285000
1,
#2290000
0,
#2295000
1,
#2300000
0,
#2305000
1,
#2310000
0,
#2315000
1,
#2320000
0,
#2325000
1,
#2330000
0,
#2335000
1,
#2340000
0,
#2345000
1,
#2350000
0,
#2355000
1,
#2356000
18
#2360000
0,
#2365000
1,
#2370000
0,
#2375000
1,
#2380000
0,
#2385000
1,
#2390000
0,
#2395000
1,
#2400000
0,
#2405000
1,
#2410000
0,
#2415000
1,
#2420000
0,
#2425000
1,
#2430000
0,
#2435000
1,
#2440000
0,
#2445000
1,
#2450000
0,
#2455000
1,
#2460000
0,
#2465000
1,
#2470000
0,
#2475000
1,
#2480000
0,
#2485000
1,
#2490000
0,
#2495000
1,
#2500000
0,
#2505000
1,
#2510000
0,
#2515000
1,
#2516000
08
#2520000
0,
#2525000
1,
#2530000
0,
#2535000
1,
#2540000
0,
#2545000
1,
#2550000
0,
#2555000
1,
#2560000
0,
#2565000
1,
#2570000
0,
#2575000
1,
#2580000
0,
#2585000
1,
#2590000
0,
#2595000
1,
#2600000
0,
#2605000
1,
#2610000
0,
#2615000
1,
#2620000
0,
#2625000
1,
#2630000
0,
#2635000
1,
#2640000
0,
#2645000
1,
#2650000
0,
#2655000
1,
#2660000
0,
#2665000
1,
#2670000
0,
#2675000
1,
#2676000
18
#2680000
0,
#2685000
1,
#2690000
0,
#2695000
1,
#2700000
0,
#2705000
1,
#2710000
0,
#2715000
1,
#2720000
0,
#2725000
1,
#2730000
0,
#2735000
1,
#2740000
0,
#2745000
1,
#2750000
0,
#2755000
1,
#2760000
0,
#2765000
1,
#2770000
0,
#2775000
1,
#2780000
0,
#2785000
1,
#2790000
0,
#2795000
1,
#2800000
0,
#2805000
1,
#2810000
0,
#2815000
1,
#2820000
0,
#2825000
1,
#2830000
0,
#2835000
1,
#2836000
08
#2840000
0,
#2845000
1,
#2850000
0,
#2855000
1,
#2860000
0,
#2865000
1,
#2870000
0,
#2875000
1,
#2880000
0,
#2885000
1,
#2890000
0,
#2895000
1,
#2900000
0,
#2905000
1,
#2910000
0,
#2915000
1,
#2920000
0,
#2925000
1,
#2930000
0,
#2935000
1,
#2940000
0,
#2945000
1,
#2950000
0,
#2955000
1,
#2960000
0,
#2965000
1,
#2970000
0,
#2975000
1,
#2980000
0,
#2985000
1,
#2990000
0,
#2995000
1,
#2996000
18
#3000000
0,
#3005000
1,
#3010000
0,
#3015000
1,
#3020000
0,
#3025000
1,
#3030000
0,
#3035000
1,
#3040000
0,
#3045000
1,
#3050000
0,
#3055000
1,
#3060000
0,
#3065000
1,
#3070000
0,
#3075000
1,
#3080000
0,
#3085000
1,
#3090000
0,
#3095000
1,
#3100000
0,
#3105000
1,
#3110000
0,
#3115000
1,
#3120000
0,
#3125000
1,
#3130000
0,
#3135000
1,
#3140000
0,
#3145000
1,
#3150000
0,
#3155000
1,
#3156000
08
#3160000
0,
#3165000
1,
#3170000
0,
#3175000
1,
#3180000
0,
#3185000
1,
#3190000
0,
#3195000
1,
#3200000
0,
#3205000
1,
#3210000
0,
#3215000
1,
#3220000
0,
#3225000
1,
#3230000
0,
#3235000
1,
#3240000
0,
#3245000
1,
#3250000
0,
#3255000
1,
#3260000
0,
#3265000
1,
#3270000
0,
#3275000
1,
#3280000
0,
#3285000
1,
#3290000
0,
#3295000
1,
#3300000
0,
#3305000
1,
#3310000
0,
#3315000
1,
#3316000
18
#3320000
0,
#3325000
1,
#3330000
0,
#3335000
1,
#3340000
0,
#3345000
1,
#3350000
0,
#3355000
1,
#3360000
0,
#3365000
1,
#3370000
0,
#3375000
1,
#3380000
0,
#3385000
1,
#3390000
0,
#3395000
1,
#3400000
0,
#3405000
1,
#3410000
0,
#3415000
1,
#3420000
0,
#3425000
1,
#3430000
0,
#3435000
1,
#3440000
0,
#3445000
1,
#3450000
0,
#3455000
1,
#3460000
0,
#3465000
1,
#3470000
0,
#3475000
1,
#3476000
08
#3480000
0,
#3485000
1,
#3490000
0,
#3495000
1,
#3500000
0,
#3505000
1,
#3510000
0,
#3515000
1,
#3520000
0,
#3525000
1,
#3530000
0,
#3535000
1,
#3540000
0,
#3545000
1,
#3550000
0,
#3555000
1,
#3560000
0,
#3565000
1,
#3570000
0,
#3575000
1,
#3580000
0,
#3585000
1,
#3590000
0,
#3595000
1,
#3600000
0,
#3605000
1,
#3610000
0,
#3615000
1,
#3620000
0,
#3625000
1,
#3630000
0,
#3635000
1,
#3636000
18
#3640000
0,
#3645000
1,
#3650000
0,
#3655000
1,
#3660000
0,
#3665000
1,
#3670000
0,
#3675000
1,
#3680000
0,
#3685000
1,
#3690000
0,
#3695000
1,
#3700000
0,
#3705000
1,
#3710000
0,
#3715000
1,
#3720000
0,
#3725000
1,
#3730000
0,
#3735000
1,
#3740000
0,
#3745000
1,
#3750000
0,
#3755000
1,
#3760000
0,
#3765000
1,
#3770000
0,
#3775000
1,
#3780000
0,
#3785000
1,
#3790000
0,
#3795000
1,
#3796000
08
#3800000
0,
#3805000
1,
#3810000
0,
#3815000
1,
#3820000
0,
#3825000
1,
#3830000
0,
#3835000
1,
#3840000
0,
#3845000
1,
#3850000
0,
#3855000
1,
#3860000
0,
#3865000
1,
#3870000
0,
#3875000
1,
#3880000
0,
#3885000
1,
#3890000
0,
#3895000
1,
#3900000
0,
#3905000
1,
#3910000
0,
#3915000
1,
#3920000
0,
#3925000
1,
#3930000
0,
#3935000
1,
#3940000
0,
#3945000
1,
#3950000
0,
#3955000
1,
#3956000
18
#3960000
0,
#3965000
1,
#3970000
0,
#3975000
1,
#3980000
0,
#3985000
1,
#3990000
0,
#3995000
1,
#4000000
0,
#4005000
1,
#4010000
0,
#4015000
1,
#4020000
0,
#4025000
1,
#4030000
0,
#4035000
1,
#4040000
0,
#4045000
1,
#4050000
0,
#4055000
1,
#4060000
0,
#4065000
1,
#4070000
0,
#4075000
1,
#4080000
0,
#4085000
1,
#4090000
0,
#4095000
1,
#4100000
0,
#4105000
1,
#4110000
0,
#4115000
1,
#4116000
08
#4120000
0,
#4125000
1,
#4130000
0,
#4135000
1,
#4140000
0,
#4145000
1,
#4150000
0,
#4155000
1,
#4160000
0,
#4165000
1,
#4170000
0,
#4175000
1,
#4180000
0,
#4185000
1,
#4190000
0,
#4195000
1,
#4200000
0,
#4205000
1,
#4210000
0,
#4215000
1,
#4220000
0,
#4225000
1,
#4230000
0,
#4235000
1,
#4240000
0,
#4245000
1,
#4250000
0,
#4255000
1,
#4260000
0,
#4265000
1,
#4270000
0,
#4275000
1,
#4276000
18
#4280000
0,
#4285000
1,
#4290000
0,
#4295000
1,
#4300000
0,
#4305000
1,
#4310000
0,
#4315000
1,
#4320000
0,
#4325000
1,
#4330000
0,
#4335000
1,
#4340000
0,
#4345000
1,
#4350000
0,
#4355000
1,
#4360000
0,
#4365000
1,
#4370000
0,
#4375000
1,
#4380000
0,
#4385000
1,
#4390000
0,
#4395000
1,
#4400000
0,
#4405000
1,
#4410000
0,
#4415000
1,
#4420000
0,
#4425000
1,
#4430000
0,
#4435000
1,
#4436000
08
#4440000
0,
#4445000
1,
#4450000
0,
#4455000
1,
#4460000
0,
#4465000
1,
#4470000
0,
#4475000
1,
#4480000
0,
#4485000
1,
#4490000
0,
#4495000
1,
#4500000
0,
#4505000
1,
#4510000
0,
#4515000
1,
#4520000
0,
#4525000
1,
#4530000
0,
#4535000
1,
#4540000
0,
#4545000
1,
#4550000
0,
#4555000
1,
#4560000
0,
#4565000
1,
#4570000
0,
#4575000
1,
#4580000
0,
#4585000
1,
#4590000
0,
#4595000
1,
#4596000
18
#4600000
0,
#4605000
1,
#4610000
0,
#4615000
1,
#4620000
0,
#4625000
1,
#4630000
0,
#4635000
1,
#4640000
0,
#4645000
1,
#4650000
0,
#4655000
1,
#4660000
0,
#4665000
1,
#4670000
0,
#4675000
1,
#4680000
0,
#4685000
1,
#4690000
0,
#4695000
1,
#4700000
0,
#4705000
1,
#4710000
0,
#4715000
1,
#4720000
0,
#4725000
1,
#4730000
0,
#4735000
1,
#4740000
0,
#4745000
1,
#4750000
0,
#4755000
1,
#4756000
08
#4760000
0,
#4765000
1,
#4770000
0,
#4775000
1,
#4780000
0,
#4785000
1,
#4790000
0,
#4795000
1,
#4800000
0,
#4805000
1,
#4810000
0,
#4815000
1,
#4820000
0,
#4825000
1,
#4830000
0,
#4835000
1,
#4840000
0,
#4845000
1,
#4850000
0,
#4855000
1,
#4860000
0,
#4865000
1,
#4870000
0,
#4875000
1,
#4880000
0,
#4885000
1,
#4890000
0,
#4895000
1,
#4900000
0,
#4905000
1,
#4910000
0,
#4915000
1,
#4916000
18
#4920000
0,
#4925000
1,
#4930000
0,
#4935000
1,
#4940000
0,
#4945000
1,
#4950000
0,
#4955000
1,
#4960000
0,
#4965000
1,
#4970000
0,
#4975000
1,
#4980000
0,
#4985000
1,
#4990000
0,
#4995000
1,
#5000000
0,
#5005000
1,
#5010000
0,
#5015000
1,
#5020000
0,
#5025000
1,
#5030000
0,
#5035000
1,
#5040000
0,
#5045000
1,
#5050000
0,
#5055000
1,
