rtl/pe_line_codec.v
// pe_line_codec.v — Tier-1 line-code codecs: NRZI, Manchester, bit-stuffing.
//
// These sit between the SM/SERDES (plain NRZ bits, one per bit_en strobe)
// and the pin matrix (wire levels). Each stage is runtime-bypassable so a
// config register can mux any subset into the pipeline (see pe_codec_mux).
//
//   pe_nrzi      TX: raw 0 -> toggle line, raw 1 -> hold (USB-LS).
//                RX: separate sampled-level register — a receiver cannot
//                see the transmitter's state. raw = wire XOR prev_level.
//   pe_manch     TX: half_phase selects which half-cell is driven;
//                raw 0 -> H then L, raw 1 -> L then H (IEEE 802.3).
//                RX: decodes from the two half-cell samples the DRU
//                captured; equal halves = illegal (no mid-bit edge).
//   pe_bitstuff  Insert/drop a complementary bit after run_cfg identical
//                consecutive bits (5 = CAN, 6 = USB). TX emits the real
//                bit first, then consumes a FOLLOWING strobe for the stuff
//                bit (tx_stuffed flags that strobe; raw input is ignored).
//                RX flags the stuffed bit (rx_raw_valid=0) and errors if
//                the bit after a full run is not complementary.
//
// None of these know protocols; config bits and one runtime parameter only.

module pe_nrzi (
  input  logic clk, rst_n,
  input  logic bit_en,
  input  logic bypass,
  input  logic tx_raw,
  output logic tx_wire,
  input  logic rx_wire,
  output logic rx_raw,
  output logic tx_lvl
);
  logic tx_level;   // line level we drive
  logic rx_level;   // last wire level we sampled (receiver state)

  assign tx_lvl  = tx_level;
  assign tx_wire = bypass ? tx_raw : tx_level;
  // Decode: a transition is a 0, no transition is a 1 (XNOR).
  assign rx_raw  = bypass ? rx_wire : ~(rx_wire ^ rx_level);

  always_ff @(posedge clk or negedge rst_n) begin
    if (!rst_n) begin
      tx_level <= 1'b1;   // idle J
      rx_level <= 1'b1;   // idle J
    end else if (bit_en) begin
      if (!bypass && (tx_raw == 1'b0)) tx_level <= ~tx_level;
      rx_level <= rx_wire;
    end
  end
endmodule


module pe_manch (
  input  logic clk, rst_n,
  input  logic bit_en,
  input  logic bypass,
  input  logic half_phase,      // 0 = first half-cell, 1 = second half-cell
  input  logic tx_raw,
  output logic tx_wire,
  input  logic rx_wire,
  input  logic rx_first,        // DRU half-cell sample, first half
  input  logic rx_second,       // DRU half-cell sample, second half
  output logic rx_raw,
  output logic rx_err
);
  // TX: raw 0 -> first half high, second low (H->L mid-bit).
  //     raw 1 -> first half low,  second high (L->H mid-bit).
  assign tx_wire = bypass ? tx_raw : (half_phase ? tx_raw : ~tx_raw);
  // RX: the second-half level carries the bit (a 0's second half is low).
  assign rx_raw  = bypass ? rx_wire : rx_second;
  assign rx_err  = bypass ? 1'b0 : (rx_first == rx_second);
endmodule


module pe_bitstuff (
  input  logic       clk, rst_n,
  input  logic       bit_en,
  input  logic       bypass,
  input  logic       clr,          // frame/SOF boundary: reset run tracking
  input  logic [3:0] run_cfg,      // stuff after this many identical bits
  input  logic       tx_raw,
  output logic       tx_wire,
  output logic       tx_stuffed,   // this strobe emits a stuff bit (raw ignored)
  input  logic       rx_wire,
  output logic       rx_raw,
  output logic       rx_raw_valid, // 0 => this wire bit was a stuff bit
  output logic       rx_err        // bit after a full run not complementary
);
  // ---------------- TX ----------------
  logic [3:0] tx_run;    // identical consecutive raw bits emitted
  logic       tx_lvl;    // value of that run
  logic       tx_pend;   // a stuff bit is owed on the NEXT strobe

  assign tx_stuffed = !bypass && tx_pend;
  assign tx_wire    = bypass ? tx_raw : (tx_pend ? ~tx_lvl : tx_raw);

  always_ff @(posedge clk or negedge rst_n) begin
    if (!rst_n) begin
      tx_run <= 4'd0; tx_lvl <= 1'b0; tx_pend <= 1'b0;
    end else if (clr) begin
      tx_run <= 4'd0; tx_lvl <= 1'b0; tx_pend <= 1'b0;
    end else if (bit_en && !bypass) begin
      if (tx_pend) begin
        tx_pend <= 1'b0;
        tx_run  <= 4'd1;      // the stuff bit opens a new run
        tx_lvl  <= ~tx_lvl;
      end else if (tx_raw == tx_lvl) begin
        if (tx_run == run_cfg - 4'd1) tx_pend <= 1'b1;
        tx_run <= tx_run + 4'd1;
      end else begin
        tx_lvl <= tx_raw;
        tx_run <= 4'd1;
      end
    end
  end

  // ---------------- RX ----------------
  logic [3:0] rx_run;    // identical consecutive WIRE bits seen
  logic       rx_lvl;
  logic       rx_is_stuff;

  assign rx_is_stuff  = !bypass && (rx_run == run_cfg);
  assign rx_raw       = rx_wire;
  assign rx_raw_valid = bypass ? 1'b1 : !rx_is_stuff;

  always_ff @(posedge clk or negedge rst_n) begin
    if (!rst_n) begin
      rx_run <= 4'd0; rx_lvl <= 1'b0; rx_err <= 1'b0;
    end else if (clr) begin
      rx_run <= 4'd0; rx_lvl <= 1'b0; rx_err <= 1'b0;
    end else if (bit_en && !bypass) begin
      rx_err <= 1'b0;
      if (rx_run == run_cfg) begin
        // this wire bit is the stuffed one: it must be complementary
        if (rx_wire == rx_lvl) rx_err <= 1'b1;
        rx_run <= 4'd1;
        rx_lvl <= rx_wire;
      end else if (rx_wire == rx_lvl) begin
        rx_run <= rx_run + 4'd1;
      end else begin
        rx_run <= 4'd1;
        rx_lvl <= rx_wire;
      end
    end
  end
endmodule

tb/tb_pe_line_codec.v
// tb_pe_line_codec.v — self-checking testbenches for the Tier-1 codec trio.
//
// Timing discipline: drive inputs, #1 to settle combinational outputs,
// sample BEFORE the strobe that commits state.
//
// pe_nrzi:     TX and RX as two instances joined by an explicit wire (a
//              real receiver cannot see TX state). Fixed + adversarial
//              (all-ones = no transitions, all-zeros) + random vectors.
// pe_manch:    both half-cells of every bit; decode; error injection.
// pe_bitstuff: run_cfg 5 (CAN) and 6 (USB), TX stuff placement, RX
//              destuff, wire-stream round trip, violation, bypass, clr.

`timescale 1ns / 1ps

// ---------------------------------------------------------------- NRZI
module tb_pe_nrzi;
  logic clk=0, rst_n;
  logic tx_en, tx_bypass, tx_raw, tx_wire, tx_lvl;
  logic rx_en, rx_bypass, rx_wire, rx_raw, rx_lvl_unused;
  logic wire_lvl;

  pe_nrzi u_tx (.clk(clk), .rst_n(rst_n), .bit_en(tx_en), .bypass(tx_bypass),
                .tx_raw(tx_raw), .tx_wire(tx_wire), .rx_wire(1'b0),
                .rx_raw(), .tx_lvl(tx_lvl));
  pe_nrzi u_rx (.clk(clk), .rst_n(rst_n), .bit_en(rx_en), .bypass(rx_bypass),
                .tx_raw(1'b1), .tx_wire(), .rx_wire(rx_wire),
                .rx_raw(rx_raw), .tx_lvl(rx_lvl_unused));

  always #5 clk = ~clk;
  integer errors = 0;
  integer seed = 42;

  task automatic check(input bit c, input string m);
    if (!c) begin $display("FAIL nrzi: %s @%0t", m, $time); errors++; end
  endtask

  task automatic strobe_tx(); tx_en = 1; @(posedge clk); #1; tx_en = 0; endtask
  task automatic strobe_rx(); rx_en = 1; @(posedge clk); #1; rx_en = 0; endtask

  // Send one raw bit: TX strobes (may toggle the line), wire settles,
  // RX decodes against its previous sample, then commits it.
  task automatic send_bit(input bit b, output bit decoded);
    tx_raw = b;
    strobe_tx();
    #1;
    wire_lvl = tx_wire;
    rx_wire  = wire_lvl;
    #1;
    decoded = rx_raw;
    strobe_rx();
  endtask

  initial begin
    $dumpfile("tb_pe_nrzi.vcd"); $dumpvars(0, tb_pe_nrzi);
    rst_n=0; tx_en=0; rx_en=0; tx_bypass=0; rx_bypass=0;
    tx_raw=0; rx_wire=0; wire_lvl=0;
    repeat(3) @(posedge clk); #1; rst_n=1; @(posedge clk); #1;

    // Fixed vector: runs, alternation, and boundaries
    begin
      logic [63:0] v; bit d;
      v = 64'b1011_0001_1111_1110_0101_0101_0000_0000_1100_1100_1010_1010_1110_0001_0110_1001;
      for (int k = 63; k >= 0; k--) begin
        send_bit(v[k], d);
        check(d === v[k], $sformatf("fixed bit %0d", k));
      end
    end

    // Worst case: all ones (no transitions at all)
    begin
      bit d;
      for (int k = 0; k < 24; k++) begin
        send_bit(1'b1, d);
        check(d === 1'b1, $sformatf("ones run bit %0d", k));
      end
    end

    // All zeros (transition every bit)
    begin
      bit d;
      for (int k = 0; k < 24; k++) begin
        send_bit(1'b0, d);
        check(d === 1'b0, $sformatf("zeros run bit %0d", k));
      end
    end

    // Random soak
    for (int t = 0; t < 12; t++) begin
      logic [31:0] rv; bit d;
      rv = $random(seed);
      for (int k = 31; k >= 0; k--) begin
        send_bit(rv[k], d);
        check(d === rv[k], $sformatf("rand %0d bit %0d", t, k));
      end
    end

    // Bypass passthrough
    tx_bypass = 1; rx_bypass = 1;
    tx_raw = 1'b1; #1; check(tx_wire === 1'b1, "bypass tx passthrough");
    rx_wire = 1'b0; #1; check(rx_raw === 1'b0, "bypass rx passthrough");
    tx_bypass = 0; rx_bypass = 0;

    if (errors == 0) $display("PASS: tb_pe_nrzi");
    else $display("FAILURES nrzi: %0d", errors);
    $finish;
  end
endmodule


// ------------------------------------------------------------- Manchester
module tb_pe_manch;
  logic clk=0, rst_n, bit_en, bypass, half_phase, tx_raw, tx_wire;
  logic rx_wire, rx_first, rx_second, rx_raw, rx_err;
  pe_manch dut (.*);
  always #5 clk = ~clk;
  integer errors = 0;

  task automatic check(input bit c, input string m);
    if (!c) begin $display("FAIL manch: %s @%0t", m, $time); errors++; end
  endtask

  // Check both half-cells of one transmitted bit.
  task automatic tx_bit(input bit b);
    half_phase = 1'b0; tx_raw = b; #1;
    check(tx_wire === (b ? 1'b0 : 1'b1), $sformatf("bit %b first half", b));
    half_phase = 1'b1; #1;
    check(tx_wire === (b ? 1'b1 : 1'b0), $sformatf("bit %b second half", b));
  endtask

  initial begin
    $dumpfile("tb_pe_manch.vcd"); $dumpvars(0, tb_pe_manch);
    rst_n=0; bit_en=0; bypass=0; half_phase=0; tx_raw=0;
    rx_wire=0; rx_first=0; rx_second=0;
    repeat(3) @(posedge clk); #1; rst_n=1; @(posedge clk); #1;

    tx_bit(1'b0);   // H then L
    tx_bit(1'b1);   // L then H
    tx_bit(1'b0);

    // RX decode from DRU half-cell samples
    rx_first=1'b1; rx_second=1'b0; #1;
    check(rx_raw === 1'b0, "rx H->L decodes 0");
    check(rx_err === 1'b0, "rx H->L legal");
    rx_first=1'b0; rx_second=1'b1; #1;
    check(rx_raw === 1'b1, "rx L->H decodes 1");
    check(rx_err === 1'b0, "rx L->H legal");
    rx_first=1'b1; rx_second=1'b1; #1;
    check(rx_err === 1'b1, "rx high no-transition flagged");
    rx_first=1'b0; rx_second=1'b0; #1;
    check(rx_err === 1'b1, "rx low no-transition flagged");

    // Bypass
    bypass = 1; tx_raw = 1'b1; rx_wire = 1'b0;
    rx_first=1'b1; rx_second=1'b1; #1;
    check(tx_wire === 1'b1, "bypass tx passthrough");
    check(rx_raw === 1'b0, "bypass rx passthrough");
    check(rx_err === 1'b0, "bypass suppresses error");

    if (errors == 0) $display("PASS: tb_pe_manch");
    else $display("FAILURES manch: %0d", errors);
    $finish;
  end
endmodule


// ----------------------------------------------------------- Bit stuffing
module tb_pe_bitstuff;
  logic clk=0, rst_n, bit_en, bypass, clr;
  logic [3:0] run_cfg;
  logic tx_raw, tx_wire, tx_stuffed;
  logic rx_wire, rx_raw, rx_raw_valid, rx_err;
  pe_bitstuff dut (.*);
  always #5 clk = ~clk;
  integer errors = 0;
  integer seed = 7;

  task automatic check(input bit c, input string m);
    if (!c) begin $display("FAIL stuff: %s @%0t", m, $time); errors++; end
  endtask

  task automatic strobe(); bit_en = 1; @(posedge clk); #1; bit_en = 0; #1; endtask

  // TX one raw bit; returns the wire bit this strobe emitted.
  task automatic tx_bit(input bit b, output bit w);
    tx_raw = b; #1;
    w = tx_wire;
    strobe();
  endtask

  // Emit the owed stuff bit (raw input ignored on this strobe).
  task automatic tx_stuff(output bit w);
    #1;
    check(tx_stuffed === 1'b1, "stuff strobe flagged");
    w = tx_wire;
    strobe();
    #1;
    check(tx_stuffed === 1'b0, "stuff flag clears after the strobe");
  endtask

  initial begin
    $dumpfile("tb_pe_bitstuff.vcd"); $dumpvars(0, tb_pe_bitstuff);
    rst_n=0; bit_en=0; bypass=0; clr=0; run_cfg=4'd5;
    tx_raw=0; rx_wire=0;
    repeat(3) @(posedge clk); #1; rst_n=1; @(posedge clk); #1;

    // ---- CAN (run_cfg=5): five 1s then a stuffed 0 ----
    begin
      bit w;
      clr = 1; @(posedge clk); #1; clr = 0;
      for (int k = 0; k < 5; k++) begin
        tx_bit(1'b1, w);
        check(w === 1'b1, $sformatf("can: data 1 at %0d", k));
      end
      check(tx_stuffed === 1'b1, "can: stuff owed after 5 ones");
      tx_stuff(w);
      check(w === 1'b0, "can: stuff bit complementary (0)");
      tx_bit(1'b0, w);
      check(w === 1'b0, "can: data resumes after stuff");
    end

    // ---- CAN: five 0s ----
    begin
      bit w;
      clr = 1; @(posedge clk); #1; clr = 0;
      for (int k = 0; k < 5; k++) begin
        tx_bit(1'b0, w);
        check(w === 1'b0, $sformatf("can0: data 0 at %0d", k));
      end
      tx_stuff(w);
      check(w === 1'b1, "can0: stuff bit complementary (1)");
    end

    // ---- USB (run_cfg=6): six 1s then a stuffed 0 ----
    begin
      bit w;
      run_cfg = 4'd6;
      clr = 1; @(posedge clk); #1; clr = 0;
      for (int k = 0; k < 6; k++) begin
        tx_bit(1'b1, w);
        check(w === 1'b1, $sformatf("usb: data 1 at %0d", k));
      end
      check(tx_stuffed === 1'b1, "usb: stuff owed after 6 ones");
      tx_stuff(w);
      check(w === 1'b0, "usb: stuff bit complementary");
    end

    // ---- Wire-stream round trip: TX all-ones (max stuffing), replay RX ----
    begin
      bit w; int nwire; logic wbits [128]; int nraw; logic rec [128];
      run_cfg = 4'd5;
      clr = 1; @(posedge clk); #1; clr = 0;
      nwire = 0;
      for (int k = 0; k < 64; k++) begin
        tx_bit(1'b1, w);
        wbits[nwire] = w; nwire++;
        if (tx_stuffed) begin
          tx_stuff(w);
          wbits[nwire] = w; nwire++;
        end
      end
      check(nwire > 64, "stuffing inserted extra wire bits");

      clr = 1; @(posedge clk); #1; clr = 0;
      nraw = 0;
      for (int i = 0; i < nwire; i++) begin
        rx_wire = wbits[i]; #1;
        if (rx_raw_valid) begin rec[nraw] = rx_raw; nraw++; end
        strobe();
      end
      check(nraw == 64, $sformatf("rx recovered 64 raw bits (got %0d)", nraw));
      for (int i = 0; i < 64; i++)
        check(rec[i] === 1'b1, $sformatf("rx recovered bit %0d = 1", i));
    end

    // ---- RX violation: bit after a full run is not complementary ----
    begin
      run_cfg = 4'd5;
      clr = 1; @(posedge clk); #1; clr = 0;
      for (int k = 0; k < 5; k++) begin
        rx_wire = 1'b1; #1; strobe();
      end
      rx_wire = 1'b1; #1;   // illegal: should have been a stuffed 0
      check(rx_raw_valid === 1'b0, "violating bit occupies the stuff slot");
      strobe(); #1;
      check(rx_err === 1'b1, "violation detected");
    end

    // ---- bypass ----
    begin
      bypass = 1; tx_raw = 1'b1; rx_wire = 1'b0; #1;
      check(tx_wire === 1'b1, "bypass tx passthrough");
      check(tx_stuffed === 1'b0, "bypass: no stuff");
      check(rx_raw_valid === 1'b1, "bypass: rx always valid");
      bypass = 0;
    end

    if (errors == 0) $display("PASS: tb_pe_bitstuff");
    else $display("FAILURES stuff: %0d", errors);
    $finish;
  end
endmodule

sim/tb_pe_bitstuff.vcd
$date
	Fri Sep 18 20:43:40 2026
$end
$version
	Icarus Verilog
$end
$timescale
	1ps
$end
$scope module tb_pe_bitstuff $end
$var wire 1 ! tx_wire $end
$var wire 1 " tx_stuffed $end
$var wire 1 # rx_raw_valid $end
$var wire 1 $ rx_raw $end
$var wire 1 % rx_err $end
$var reg 1 & bit_en $end
$var reg 1 ' bypass $end
$var reg 1 ( clk $end
$var reg 1 ) clr $end
$var reg 1 * rst_n $end
$var reg 4 + run_cfg [3:0] $end
$var reg 1 , rx_wire $end
$var reg 1 - tx_raw $end
$var integer 32 . errors [31:0] $end
$var integer 32 / seed [31:0] $end
$scope module dut $end
$var wire 1 & bit_en $end
$var wire 1 ' bypass $end
$var wire 1 ( clk $end
$var wire 1 ) clr $end
$var wire 1 * rst_n $end
$var wire 4 0 run_cfg [3:0] $end
$var wire 1 1 rx_is_stuff $end
$var wire 1 $ rx_raw $end
$var wire 1 , rx_wire $end
$var wire 1 - tx_raw $end
$var wire 1 " tx_stuffed $end
$var wire 1 ! tx_wire $end
$var wire 1 # rx_raw_valid $end
$var reg 1 % rx_err $end
$var reg 1 2 rx_lvl $end
$var reg 4 3 rx_run [3:0] $end
$var reg 1 4 tx_lvl $end
$var reg 1 5 tx_pend $end
$var reg 4 6 tx_run [3:0] $end
$upscope $end
$scope begin $ivl_for_loop11 $end
$var integer 32 7 k [31:0] $end
$upscope $end
$scope begin $unm_blk_32 $end
$var reg 1 8 w $end
$scope begin $ivl_for_loop5 $end
$var integer 32 9 k [31:0] $end
$upscope $end
$upscope $end
$scope begin $unm_blk_34 $end
$var reg 1 : w $end
$scope begin $ivl_for_loop6 $end
$var integer 32 ; k [31:0] $end
$upscope $end
$upscope $end
$scope begin $unm_blk_36 $end
$var reg 1 < w $end
$scope begin $ivl_for_loop7 $end
$var integer 32 = k [31:0] $end
$upscope $end
$upscope $end
$scope begin $unm_blk_38 $end
$var integer 32 > nraw [31:0] $end
$var integer 32 ? nwire [31:0] $end
$var reg 1 @ w $end
$scope begin $ivl_for_loop10 $end
$var integer 32 A i [31:0] $end
$upscope $end
$scope begin $ivl_for_loop8 $end
$var integer 32 B k [31:0] $end
$upscope $end
$scope begin $ivl_for_loop9 $end
$var integer 32 C i [31:0] $end
$upscope $end
$upscope $end
$scope task check $end
$upscope $end
$scope task strobe $end
$upscope $end
$scope task tx_bit $end
$upscope $end
$scope task tx_stuff $end
$upscope $end
$upscope $end
$enddefinitions $end
$comment Show the parameter values. $end
$dumpall
$end
#0
$dumpvars
b0 C
b0 B
b0 A
0@
b0 ?
b0 >
b0 =
0<
b0 ;
0:
b0 9
08
b0 7
b0 6
05
04
b0 3
02
01
b101 0
b111 /
b0 .
0-
0,
b101 +
0*
0)
0(
0'
0&
0%
0$
1#
0"
0!
$end
#5000
1(
#10000
0(
#15000
1(
#20000
0(
#25000
1(
#26000
1*
#30000
0(
#35000
1(
#36000
1)
#40000
0(
#45000
1(
#46000
1!
1-
0)
#47000
1&
#50000
0(
#55000
b1 6
14
b1 3
1(
#56000
0&
#57000
b1 9
18
#58000
1&
#60000
0(
#65000
b10 3
b10 6
1(
#66000
0&
#67000
b10 9
#68000
1&
#70000
0(
#75000
b11 6
b11 3
1(
#76000
0&
#77000
b11 9
#78000
1&
#80000
0(
#85000
b100 3
b100 6
1(
#86000
0&
#87000
b100 9
#88000
1&
#90000
0(
#95000
0!
0#
1"
11
b101 6
15
b101 3
1(
#96000
0&
#97000
b101 9
#98000
1&
#100000
0(
#105000
1#
1!
01
0"
b1 3
1%
04
b1 6
05
1(
#106000
0&
#108000
0!
0-
08
#109000
1&
#110000
0(
#115000
b10 6
b10 3
0%
1(
#116000
0&
#117000
1)
#120000
0(
#125000
b0 3
b0 6
1(
#126000
0)
#127000
1&
#130000
0(
#135000
b1 6
b1 3
1(
#136000
0&
#137000
b1 ;
#138000
1&
#140000
0(
#145000
b10 3
b10 6
1(
#146000
0&
#147000
b10 ;
#148000
1&
#150000
0(
#155000
b11 6
b11 3
1(
#156000
0&
#157000
b11 ;
#158000
1&
#160000
0(
#165000
b100 3
b100 6
1(
#166000
0&
#167000
b100 ;
#168000
1&
#170000
0(
#175000
1!
0#
1"
11
b101 6
15
b101 3
1(
#176000
0&
#177000
b101 ;
#178000
1&
#180000
0(
#185000
1#
0!
01
0"
b1 3
1%
14
b1 6
05
1(
#186000
0&
#188000
1)
b110 +
b110 0
1:
#190000
0(
#195000
04
b0 6
0%
b0 3
1(
#196000
1!
1-
0)
#197000
1&
#200000
0(
#205000
b1 3
b1 6
14
1(
#206000
0&
#207000
b1 =
1<
#208000
1&
#210000
0(
#215000
b10 6
b10 3
1(
#216000
0&
#217000
b10 =
#218000
1&
#220000
0(
#225000
b11 3
b11 6
1(
#226000
0&
#227000
b11 =
#228000
1&
#230000
0(
#235000
b100 6
b100 3
1(
#236000
0&
#237000
b100 =
#238000
1&
#240000
0(
#245000
b101 3
b101 6
1(
#246000
0&
#247000
b101 =
#248000
1&
#250000
0(
#255000
0!
0#
1"
11
b110 6
15
b110 3
1(
#256000
0&
#257000
b110 =
#258000
1&
#260000
0(
#265000
1#
1!
01
0"
b1 3
1%
04
b1 6
05
1(
#266000
0&
#268000
1)
b101 +
b101 0
0<
#270000
0(
#275000
b0 6
0%
b0 3
1(
#276000
0)
#277000
1&
#280000
0(
#285000
b1 3
b1 6
14
1(
#286000
0&
#287000
b1 B
b1 ?
1@
#288000
1&
#290000
0(
#295000
b10 6
b10 3
1(
#296000
0&
#297000
b10 B
b10 ?
#298000
1&
#300000
0(
#305000
b11 3
b11 6
1(
#306000
0&
#307000
b11 B
b11 ?
#308000
1&
#310000
0(
#315000
b100 6
b100 3
1(
#316000
0&
#317000
b100 B
b100 ?
#318000
1&
#320000
0(
#325000
0#
0!
11
1"
b101 3
b101 6
15
1(
#326000
0&
#327000
b101 ?
#328000
1&
#330000
0(
#335000
1!
1#
0"
01
04
b1 6
05
b1 3
1%
1(
#336000
0&
#338000
b101 B
b110 ?
0@
#339000
1&
#340000
0(
#345000
b10 3
0%
14
1(
#346000
0&
#347000
b110 B
b111 ?
1@
#348000
1&
#350000
0(
#355000
b10 6
b11 3
1(
#356000
0&
#357000
b111 B
b1000 ?
#358000
1&
#360000
0(
#365000
b100 3
b11 6
1(
#366000
0&
#367000
b1000 B
b1001 ?
#368000
1&
#370000
0(
#375000
0#
11
b100 6
b101 3
1(
#376000
0&
#377000
b1001 B
b1010 ?
#378000
1&
#380000
0(
#385000
1#
0!
01
1"
b1 3
1%
b101 6
15
1(
#386000
0&
#387000
b1011 ?
#388000
1&
#390000
0(
#395000
1!
0"
04
b1 6
05
b10 3
0%
1(
#396000
0&
#398000
b1010 B
b1100 ?
0@
#399000
1&
#400000
0(
#405000
b11 3
14
1(
#406000
0&
#407000
b1011 B
b1101 ?
1@
#408000
1&
#410000
0(
#415000
b10 6
b100 3
1(
#416000
0&
#417000
b1100 B
b1110 ?
#418000
1&
#420000
0(
#425000
0#
11
b101 3
b11 6
1(
#426000
0&
#427000
b1101 B
b1111 ?
#428000
1&
#430000
0(
#435000
1#
01
b100 6
b1 3
1%
1(
#436000
0&
#437000
b1110 B
b10000 ?
#438000
1&
#440000
0(
#445000
0!
1"
b10 3
0%
b101 6
15
1(
#446000
0&
#447000
b10001 ?
#448000
1&
#450000
0(
#455000
1!
0"
04
b1 6
05
b11 3
1(
#456000
0&
#458000
b1111 B
b10010 ?
0@
#459000
1&
#460000
0(
#465000
b100 3
14
1(
#466000
0&
#467000
b10000 B
b10011 ?
1@
#468000
1&
#470000
0(
#475000
0#
11
b10 6
b101 3
1(
#476000
0&
#477000
b10001 B
b10100 ?
#478000
1&
#480000
0(
#485000
1#
01
b1 3
1%
b11 6
1(
#486000
0&
#487000
b10010 B
b10101 ?
#488000
1&
#490000
0(
#495000
b100 6
b10 3
0%
1(
#496000
0&
#497000
b10011 B
b10110 ?
#498000
1&
#500000
0(
#505000
0!
1"
b11 3
b101 6
15
1(
#506000
0&
#507000
b10111 ?
#508000
1&
#510000
0(
#515000
1!
0"
04
b1 6
05
b100 3
1(
#516000
0&
#518000
b10100 B
b11000 ?
0@
#519000
1&
#520000
0(
#525000
0#
11
b101 3
14
1(
#526000
0&
#527000
b10101 B
b11001 ?
1@
#528000
1&
#530000
0(
#535000
1#
01
b10 6
b1 3
1%
1(
#536000
0&
#537000
b10110 B
b11010 ?
#538000
1&
#540000
0(
#545000
b10 3
0%
b11 6
1(
#546000
0&
#547000
b10111 B
b11011 ?
#548000
1&
#550000
0(
#555000
b100 6
b11 3
1(
#556000
0&
#557000
b11000 B
b11100 ?
#558000
1&
#560000
0(
#565000
0!
1"
b100 3
b101 6
15
1(
#566000
0&
#567000
b11101 ?
#568000
1&
#570000
0(
#575000
1!
0#
0"
11
04
b1 6
05
b101 3
1(
#576000
0&
#578000
b11001 B
b11110 ?
0@
#579000
1&
#580000
0(
#585000
1#
01
b1 3
1%
14
1(
#586000
0&
#587000
b11010 B
b11111 ?
1@
#588000
1&
#590000
0(
#595000
b10 6
b10 3
0%
1(
#596000
0&
#597000
b11011 B
b100000 ?
#598000
1&
#600000
0(
#605000
b11 3
b11 6
1(
#606000
0&
#607000
b11100 B
b100001 ?
#608000
1&
#610000
0(
#615000
b100 6
b100 3
1(
#616000
0&
#617000
b11101 B
b100010 ?
#618000
1&
#620000
0(
#625000
0#
0!
11
1"
b101 3
b101 6
15
1(
#626000
0&
#627000
b100011 ?
#628000
1&
#630000
0(
#635000
1!
1#
0"
01
04
b1 6
05
b1 3
1%
1(
#636000
0&
#638000
b11110 B
b100100 ?
0@
#639000
1&
#640000
0(
#645000
b10 3
0%
14
1(
#646000
0&
#647000
b11111 B
b100101 ?
1@
#648000
1&
#650000
0(
#655000
b10 6
b11 3
1(
#656000
0&
#657000
b100000 B
b100110 ?
#658000
1&
#660000
0(
#665000
b100 3
b11 6
1(
#666000
0&
#667000
b100001 B
b100111 ?
#668000
1&
#670000
0(
#675000
0#
11
b100 6
b101 3
1(
#676000
0&
#677000
b100010 B
b101000 ?
#678000
1&
#680000
0(
#685000
1#
0!
01
1"
b1 3
1%
b101 6
15
1(
#686000
0&
#687000
b101001 ?
#688000
1&
#690000
0(
#695000
1!
0"
04
b1 6
05
b10 3
0%
1(
#696000
0&
#698000
b100011 B
b101010 ?
0@
#699000
1&
#700000
0(
#705000
b11 3
14
1(
#706000
0&
#707000
b100100 B
b101011 ?
1@
#708000
1&
#710000
0(
#715000
b10 6
b100 3
1(
#716000
0&
#717000
b100101 B
b101100 ?
#718000
1&
#720000
0(
#725000
0#
11
b101 3
b11 6
1(
#726000
0&
#727000
b100110 B
b101101 ?
#728000
1&
#730000
0(
#735000
1#
01
b100 6
b1 3
1%
1(
#736000
0&
#737000
b100111 B
b101110 ?
#738000
1&
#740000
0(
#745000
0!
1"
b10 3
0%
b101 6
15
1(
#746000
0&
#747000
b101111 ?
#748000
1&
#750000
0(
#755000
1!
0"
04
b1 6
05
b11 3
1(
#756000
0&
#758000
b101000 B
b110000 ?
0@
#759000
1&
#760000
0(
#765000
b100 3
14
1(
#766000
0&
#767000
b101001 B
b110001 ?
1@
#768000
1&
#770000
0(
#775000
0#
11
b10 6
b101 3
1(
#776000
0&
#777000
b101010 B
b110010 ?
#778000
1&
#780000
0(
#785000
1#
01
b1 3
1%
b11 6
1(
#786000
0&
#787000
b101011 B
b110011 ?
#788000
1&
#790000
0(
#795000
b100 6
b10 3
0%
1(
#796000
0&
#797000
b101100 B
b110100 ?
#798000
1&
#800000
0(
#805000
0!
1"
b11 3
b101 6
15
1(
#806000
0&
#807000
b110101 ?
#808000
1&
#810000
0(
#815000
1!
0"
04
b1 6
05
b100 3
1(
#816000
0&
#818000
b101101 B
b110110 ?
0@
#819000
1&
#820000
0(
#825000
0#
11
b101 3
14
1(
#826000
0&
#827000
b101110 B
b110111 ?
1@
#828000
1&
#830000
0(
#835000
1#
01
b10 6
b1 3
1%
1(
#836000
0&
#837000
b101111 B
b111000 ?
#838000
1&
#840000
0(
#845000
b10 3
0%
b11 6
1(
#846000
0&
#847000
b110000 B
b111001 ?
#848000
1&
#850000
0(
#855000
b100 6
b11 3
1(
#856000
0&
#857000
b110001 B
b111010 ?
#858000
1&
#860000
0(
#865000
0!
1"
b100 3
b101 6
15
1(
#866000
0&
#867000
b111011 ?
#868000
1&
#870000
0(
#875000
1!
0#
0"
11
04
b1 6
05
b101 3
1(
#876000
0&
#878000
b110010 B
b111100 ?
0@
#879000
1&
#880000
0(
#885000
1#
01
b1 3
1%
14
1(
#886000
0&
#887000
b110011 B
b111101 ?
1@
#888000
1&
#890000
0(
#895000
b10 6
b10 3
0%
1(
#896000
0&
#897000
b110100 B
b111110 ?
#898000
1&
#900000
0(
#905000
b11 3
b11 6
1(
#906000
0&
#907000
b110101 B
b111111 ?
#908000
1&
#910000
0(
#915000
b100 6
b100 3
1(
#916000
0&
#917000
b110110 B
b1000000 ?
#918000
1&
#920000
0(
#925000
0#
0!
11
1"
b101 3
b101 6
15
1(
#926000
0&
#927000
b1000001 ?
#928000
1&
#930000
0(
#935000
1!
1#
0"
01
04
b1 6
05
b1 3
1%
1(
#936000
0&
#938000
b110111 B
b1000010 ?
0@
#939000
1&
#940000
0(
#945000
b10 3
0%
14
1(
#946000
0&
#947000
b111000 B
b1000011 ?
1@
#948000
1&
#950000
0(
#955000
b10 6
b11 3
1(
#956000
0&
#957000
b111001 B
b1000100 ?
#958000
1&
#960000
0(
#965000
b100 3
b11 6
1(
#966000
0&
#967000
b111010 B
b1000101 ?
#968000
1&
#970000
0(
#975000
0#
11
b100 6
b101 3
1(
#976000
0&
#977000
b111011 B
b1000110 ?
#978000
1&
#980000
0(
#985000
1#
0!
01
1"
b1 3
1%
b101 6
15
1(
#986000
0&
#987000
b1000111 ?
#988000
1&
#990000
0(
#995000
1!
0"
04
b1 6
05
b10 3
0%
1(
#996000
0&
#998000
b111100 B
b1001000 ?
0@
#999000
1&
#1000000
0(
#1005000
b11 3
14
1(
#1006000
0&
#1007000
b111101 B
b1001001 ?
1@
#1008000
1&
#1010000
0(
#1015000
b10 6
b100 3
1(
#1016000
0&
#1017000
b111110 B
b1001010 ?
#1018000
1&
#1020000
0(
#1025000
0#
11
b101 3
b11 6
1(
#1026000
0&
#1027000
b111111 B
b1001011 ?
#1028000
1&
#1030000
0(
#1035000
1#
01
b100 6
b1 3
1%
1(
#1036000
0&
#1037000
1)
b1000000 B
b1001100 ?
#1040000
0(
#1045000
0%
b0 3
04
b0 6
1(
#1046000
1$
1,
0)
#1047000
1&
b1 >
