rtl/pe_serdes.v
// pe_serdes.v — protocol-emulator shared serializer / deserializer.
// Signal meanings: wiki/reference/signal-names.md#pe_serdes
//
// One shift engine serves every target protocol (UART, SPI, I2C, JTAG, SWD,
// PS/2, CAN, USB-LS, 10BASE-T): firmware works at the word level, this block
// handles bit order and bit counting.
//
// * Bit order is SNAPSHOT at tx_load / rx_start into per-side registers, so
//   cfg_lsb_first may be rewritten by the core at any time without
//   corrupting an in-flight transfer (cfg = 1 UART LSB-first, 0 SPI-style).
// * Transfer length 1..MAXLEN bits, captured on load/start. Lengths above
//   MAXLEN or 0 are out of contract (0 is ignored; >MAXLEN is not clamped).
// * bit_en is the per-bit-cell strobe from the core/DRU timing logic.
//   The RX serial input is expected to be already synchronized (latch-pair
//   dual-edge capture flop, ADR-002); this block is single-edge.
// * tx_ser idles HIGH (suits UART; SPI is CS-gated; I2C/SWD direction is
//   handled by the pin-matrix OE logic, not here).
// * A load/start while busy restarts the transfer (start on the final bit
//   cell drops that bit; start one cycle later still completes the word).
// * Valid RX payload lands in rx_data[rx_len-1:0]: first-received bit sits
//   at [0] when LSB-first, at [rx_len-1] when MSB-first.
// * RX completion is delayed one cycle from the final strobe (rx_busy drops
//   first, rx_valid/rx_data follow) so rx_data can copy rx_shreg directly
//   instead of paying for a variable-shift forward path.
// * Parameter constraint: MAXLEN >= 2 (IDXW would otherwise be 0).

module pe_serdes #(
  parameter int MAXLEN = 32,
  parameter int LENW   = $clog2(MAXLEN + 1),
  parameter int IDXW   = $clog2(MAXLEN)
) (
  input  logic                 clk,
  input  logic                 rst_n,

  input  logic                 cfg_lsb_first,
  input  logic                 bit_en,

  // Transmit side
  input  logic                 tx_load,
  input  logic [MAXLEN-1:0]    tx_data,
  input  logic [LENW-1:0]      tx_len,
  output logic                 tx_ser,
  output logic                 tx_busy,
  output logic                 tx_done,

  // Receive side
  input  logic                 rx_ser,
  input  logic                 rx_start,
  input  logic [LENW-1:0]      rx_len,
  output logic [MAXLEN-1:0]    rx_data,
  output logic                 rx_busy,
  output logic                 rx_valid
);

  // Elaboration guard: MAXLEN=1 would make IDXW=0 (illegal range).
  if (IDXW < 1) $error("pe_serdes: MAXLEN must be >= 2");

  // ---------------- Transmit ----------------
  logic [MAXLEN-1:0] tx_shreg;
  logic [LENW-1:0]   tx_nbits;   // snapshot of tx_len at load
  logic [LENW-1:0]   tx_cnt;     // index of the bit currently on tx_ser
  logic              cfg_lsb_tx; // snapshot of cfg_lsb_first at load

  // Index width only needs $clog2(MAXLEN); LENW expressions truncate cleanly.
  logic [IDXW-1:0] tx_rd_idx;
  assign tx_rd_idx = cfg_lsb_tx
    ? IDXW'(tx_cnt)
    : IDXW'(tx_nbits - 1'b1 - tx_cnt);
  assign tx_ser = tx_busy ? tx_shreg[tx_rd_idx] : 1'b1;

  always_ff @(posedge clk or negedge rst_n) begin
    if (!rst_n) begin
      tx_shreg   <= '0;
      tx_nbits   <= '0;
      tx_cnt     <= '0;
      cfg_lsb_tx <= 1'b0;
      tx_busy    <= 1'b0;
      tx_done    <= 1'b0;
    end else begin
      tx_done <= 1'b0;
      if (tx_load && (|tx_len)) begin
        tx_shreg   <= tx_data;
        tx_nbits   <= tx_len;
        tx_cnt     <= '0;
        cfg_lsb_tx <= cfg_lsb_first;
        tx_busy    <= 1'b1;
      end else if (bit_en && tx_busy) begin
        if (tx_cnt == tx_nbits - 1'b1) begin
          tx_busy <= 1'b0;
          tx_done <= 1'b1;
        end else begin
          tx_cnt <= tx_cnt + 1'b1;
        end
      end
    end
  end

  // ---------------- Receive ----------------
  // Bit-placer (not a shifter): bit k of the transfer is written straight
  // to rx_shreg[pos], with pos counting 0..len-1 when LSB-first and
  // len-1..0 when MSB-first. Payload always ends up in [len-1:0].
  logic [MAXLEN-1:0] rx_shreg;
  logic [LENW-1:0]   rx_nbits;   // snapshot of rx_len at start
  logic [LENW-1:0]   rx_cnt;     // number of bits captured so far
  logic [IDXW-1:0]   rx_pos;     // write position for the incoming bit
  logic              cfg_lsb_rx; // snapshot of cfg_lsb_first at start
  logic              rx_fin;     // final bit seen; complete next cycle

  always_ff @(posedge clk or negedge rst_n) begin
    if (!rst_n) begin
      rx_shreg   <= '0;
      rx_nbits   <= '0;
      rx_cnt     <= '0;
      rx_pos     <= '0;
      cfg_lsb_rx <= 1'b0;
      rx_fin     <= 1'b0;
      rx_data    <= '0;
      rx_busy    <= 1'b0;
      rx_valid   <= 1'b0;
    end else begin
      rx_valid <= 1'b0;
      // Delayed completion: rx_shreg holds the full word by now, so the
      // copy needs no variable-shift forward path. Deliberately ordered
      // before rx_start handling so a start on this exact cycle still
      // delivers the old word (no register conflict: disjoint targets).
      if (rx_fin) begin
        rx_fin   <= 1'b0;
        rx_valid <= 1'b1;
        rx_data  <= rx_shreg;
      end
      if (rx_start && (|rx_len)) begin
        rx_shreg   <= '0;
        rx_nbits   <= rx_len;
        rx_cnt     <= '0;
        rx_pos     <= cfg_lsb_first ? '0 : IDXW'(rx_len - 1'b1);
        cfg_lsb_rx <= cfg_lsb_first;
        rx_busy    <= 1'b1;
      end else if (bit_en && rx_busy) begin
        rx_shreg[rx_pos] <= rx_ser;
        if (rx_cnt == rx_nbits - 1'b1) begin
          rx_busy <= 1'b0;
          rx_fin  <= 1'b1;
        end else begin
          rx_cnt <= rx_cnt + 1'b1;
          rx_pos <= cfg_lsb_rx ? rx_pos + 1'b1 : rx_pos - 1'b1;
        end
      end
    end
  end

endmodule

tb/tb_pe_can.v
// tb_pe_can.v — CAN 2.0 classic frame bit-level model around pe_serdes.
//
// NRZ + bit stuffing (after 5 identical consecutive bits a complementary
// stuff bit is inserted). The SERDES carries ONE DATA BYTE (8 bits,
// MSB-first) per word — multi-byte payloads are chunked per byte, which
// is exactly how the core will drive it. The TB models the full frame:
// SOF, arbitration (11b), control (6b), data (1 byte here), 15-bit CRC
// over destuffed bits, ACK slot, EOF. Stuffing spans SOF..CRC.

`timescale 1ns / 1ps

module tb_pe_can;

  localparam int MAXLEN = 32;
  localparam int LENW = $clog2(MAXLEN + 1);
  localparam int H = 8;

  logic              clk, rst_n;
  logic              cfg_lsb_first, bit_en;
  logic              tx_load, tx_ser, tx_busy, tx_done;
  logic [MAXLEN-1:0] tx_data;
  logic [LENW-1:0]   tx_len;
  logic              rx_ser, rx_start, rx_busy, rx_valid;
  logic [MAXLEN-1:0] rx_data;
  logic [LENW-1:0]   rx_len;
  logic              can_rx;

  pe_serdes #(.MAXLEN(MAXLEN)) dut (.*);

  initial clk = 0;
  always #5 clk = ~clk;

  integer errors = 0;

  logic tx_done_seen, rx_valid_seen;
  always @(posedge clk or negedge rst_n)
    if (!rst_n) begin tx_done_seen <= 0; rx_valid_seen <= 0; end
    else begin
      if (tx_done)  tx_done_seen  <= 1'b1;
      if (rx_valid) rx_valid_seen <= 1'b1;
    end

  task automatic check(input bit c, input string m);
    if (!c) begin $display("FAIL: %s @%0t", m, $time); errors++; end
  endtask

  task automatic bit_cell();
    repeat (H) @(posedge clk); #1;
  endtask

  // CRC-15 CAN poly: x^15+x^14+x^10+x^8+x^7+x^4+x^3+1 (0x4599).
  // bits[] is MSB-first: index n-1 = first bit on the wire.
  function automatic [14:0] crc15(input [63:0] bits, input int n);
    logic [14:0] crc;
    logic b, fb;
    crc = '0;
    for (int i = n - 1; i >= 0; i--) begin
      b   = bits[i];
      fb  = b ^ crc[14];
      crc = {crc[13:0], 1'b0};
      if (fb) crc ^= 15'h4599;
    end
    return crc;
  endfunction

  // Stuffed-wire sender: pushes a destuffed bit sequence onto the wire,
  // inserting stuff bits; returns the stuffed stream + count.
  logic run_last;
  int   run_len;
  logic run_last_before_data;  // snapshots for the receiver's tracker
  int   run_len_before_data;
  task automatic stuff_send(input [63:0] bits, input int n,
                            inout logic [127:0] stuffed, inout int sc);
    for (int i = n - 1; i >= 0; i--) begin
      can_rx = bits[i];
      stuffed[sc] = bits[i]; sc++;
      if (bits[i] == run_last) begin
        run_len++;
        if (run_len == 5) begin
          can_rx = ~run_last;      // stuff bit
          stuffed[sc] = ~run_last; sc++;
          run_last = ~run_last; run_len = 1;
        end
      end else begin
        run_last = bits[i]; run_len = 1;
      end
      bit_cell();
    end
  endtask

  // One CAN frame with a single data byte (chunked per byte by design).
  task automatic can_frame(input [10:0] arb, input [7:0] data,
                           input string tag);
    logic [63:0] seq;      // destuffed SOF..CRC (1+11+6+8+15 = 41 bits)
    logic [127:0] stuffed;
    int sc, seq_n;
    logic [14:0] crc;

    seq = '0; seq_n = 0;
    seq[seq_n++] = 1'b0;                              // SOF
    for (int i = 10; i >= 0; i--) seq[seq_n++] = arb[i];
    for (int i = 0; i < 6; i++)                        // IDE,r0,DLC=1
      seq[seq_n++] = (i >= 3) ? (i == 5) : 1'b0;      // DLC bits 3..0 -> 0001
    for (int i = 7; i >= 0; i--) seq[seq_n++] = data[i];
    crc = crc15(seq, seq_n);
    for (int i = 14; i >= 0; i--) seq[seq_n++] = crc[i];

    // SERDES word = the single data byte, MSB-first
    @(posedge clk); #1;
    cfg_lsb_first = 1'b0;
    tx_data = data; tx_len = 8; tx_load = 1'b1;
    rx_len = 8; rx_start = 1'b1;
    tx_done_seen = 1'b0; rx_valid_seen = 1'b0;
    @(posedge clk); #1; tx_load = 1'b0; rx_start = 1'b0;

    // Wire: SOF+arb+ctrl stuffed, then data (strobe per DESTUFFED bit),
    // then CRC stuffed. Receiver destuffs on the fly: it mirrors the
    // run-length tracker and skips stuff bits.
    stuffed = '0; sc = 0;
    run_last = 1'b1; run_len = 1;  // bus idle recessive counts as run of 1s
    stuff_send(seq, 1 + 11 + 6, stuffed, sc);
    run_last_before_data = run_last; run_len_before_data = run_len;
    begin : data_phase
      int sc0;
      sc0 = sc;
      stuff_send(seq >> (1 + 11 + 6), 8, stuffed, sc);
      // Walk the stuffed stream, skipping inserted stuff bits. Mirror
      // the TX run tracker: when the run of identical bits reaches 5,
      // the CURRENT bit is still real data — the NEXT wire bit is the
      // stuff bit and must be skipped.
      begin
        logic lv, b; int rl, k;
        lv = run_last_before_data; rl = run_len_before_data;
        k = 0;  // destuffed data bit index
        for (int i = sc0; i < sc; i++) begin
          b = stuffed[i];
          if (b == lv) rl++;
          else begin lv = b; rl = 1; end
          rx_ser = b;  // real data bit k
          bit_en = 1'b1; @(posedge clk); #1; bit_en = 1'b0;
          k++;
          if (rl == 5) begin
            i++;            // skip the stuff bit that follows
            lv = ~b; rl = 1;
          end
        end
        check(k == 8, {tag, ": 8 destuffed data bits"});
      end
    end
    stuff_send(seq >> (1 + 11 + 6 + 8), 15, stuffed, sc);
    // CRC delimiter, ACK slot (a receiver drives dominant), ACK delim,
    // EOF x7, intermission x3 — all recessive except the ACK slot.
    can_rx = 1'b1; bit_cell();
    can_rx = 1'b0; bit_cell();
    check(can_rx === 1'b0, {tag, ": ACK slot dominant"});
    can_rx = 1'b1; bit_cell();
    repeat (10) bit_cell();

    repeat (2) @(posedge clk); #1;
    check(rx_valid_seen === 1'b1, {tag, ": rx_valid"});
    check(tx_done_seen === 1'b1, {tag, ": tx_done"});
    check(rx_data[7:0] === data, {tag, ": data byte"});
  endtask

  initial begin
    $dumpfile("tb_pe_can.vcd");
    $dumpvars(0, tb_pe_can);
    rst_n = 0; can_rx = 1; bit_en = 0;
    cfg_lsb_first = 0; tx_load = 0; tx_data = 0; tx_len = 0;
    rx_ser = 0; rx_start = 0; rx_len = 0;
    repeat (3) @(posedge clk); #1; rst_n = 1;
    @(posedge clk); #1;

    can_frame(11'h5A3, 8'h3C, "can 3C");
    can_frame(11'h123, 8'h00, "can 00");  // stuffing edge case: zero byte
    can_frame(11'h7FF, 8'hFF, "can FF");  // stuffing edge case: ones byte

    if (errors == 0) $display("PASS: tb_pe_can");
    else $display("FAILURES: %0d", errors);
    $finish;
  end

endmodule

sim/tb_pe_can.vcd
$date
	Fri Sep 18 10:36:06 2026
$end
$version
	Icarus Verilog
$end
$timescale
	1ps
$end
$scope module tb_pe_can $end
$var wire 1 ! tx_ser $end
$var wire 1 " tx_done $end
$var wire 1 # tx_busy $end
$var wire 1 $ rx_valid $end
$var wire 32 % rx_data [31:0] $end
$var wire 1 & rx_busy $end
$var parameter 32 ' H $end
$var parameter 32 ( LENW $end
$var parameter 32 ) MAXLEN $end
$var reg 1 * bit_en $end
$var reg 1 + can_rx $end
$var reg 1 , cfg_lsb_first $end
$var reg 1 - clk $end
$var reg 1 . rst_n $end
$var reg 1 / run_last $end
$var reg 1 0 run_last_before_data $end
$var reg 6 1 rx_len [5:0] $end
$var reg 1 2 rx_ser $end
$var reg 1 3 rx_start $end
$var reg 1 4 rx_valid_seen $end
$var reg 32 5 tx_data [31:0] $end
$var reg 1 6 tx_done_seen $end
$var reg 6 7 tx_len [5:0] $end
$var reg 1 8 tx_load $end
$var integer 32 9 errors [31:0] $end
$var integer 32 : run_len [31:0] $end
$var integer 32 ; run_len_before_data [31:0] $end
$scope function crc15 $end
$scope begin $ivl_for_loop0 $end
$upscope $end
$upscope $end
$scope module dut $end
$var wire 1 * bit_en $end
$var wire 1 , cfg_lsb_first $end
$var wire 1 - clk $end
$var wire 1 . rst_n $end
$var wire 6 < rx_len [5:0] $end
$var wire 1 2 rx_ser $end
$var wire 1 3 rx_start $end
$var wire 32 = tx_data [31:0] $end
$var wire 6 > tx_len [5:0] $end
$var wire 1 8 tx_load $end
$var wire 1 ! tx_ser $end
$var wire 5 ? tx_rd_idx [4:0] $end
$var parameter 32 @ IDXW $end
$var parameter 32 A LENW $end
$var parameter 32 B MAXLEN $end
$var reg 1 C cfg_lsb_rx $end
$var reg 1 D cfg_lsb_tx $end
$var reg 1 & rx_busy $end
$var reg 6 E rx_cnt [5:0] $end
$var reg 32 F rx_data [31:0] $end
$var reg 1 G rx_fin $end
$var reg 6 H rx_nbits [5:0] $end
$var reg 5 I rx_pos [4:0] $end
$var reg 32 J rx_shreg [31:0] $end
$var reg 1 $ rx_valid $end
$var reg 1 # tx_busy $end
$var reg 6 K tx_cnt [5:0] $end
$var reg 1 " tx_done $end
$var reg 6 L tx_nbits [5:0] $end
$var reg 32 M tx_shreg [31:0] $end
$upscope $end
$scope task bit_cell $end
$upscope $end
$scope task can_frame $end
$scope begin $ivl_for_loop2 $end
$upscope $end
$scope begin $ivl_for_loop3 $end
$upscope $end
$scope begin $ivl_for_loop4 $end
$upscope $end
$scope begin $ivl_for_loop5 $end
$upscope $end
$scope begin data_phase $end
$scope begin $unm_blk_24 $end
$scope begin $ivl_for_loop6 $end
$upscope $end
$upscope $end
$upscope $end
$upscope $end
$scope task check $end
$upscope $end
$scope task stuff_send $end
$scope begin $ivl_for_loop1 $end
$upscope $end
$upscope $end
$upscope $end
$enddefinitions $end
$comment Show the parameter values. $end
$dumpall
b100000 B
b110 A
b101 @
b100000 )
b110 (
b1000 '
$end
#0
$dumpvars
b0 M
b0 L
b0 K
b0 J
b0 I
b0 H
0G
b0 F
b0 E
0D
0C
b11111 ?
b0 >
b0 =
b0 <
b0 ;
b0 :
b0 9
08
b0 7
06
b0 5
04
03
02
b0 1
x0
x/
0.
0-
0,
1+
0*
0&
b0 %
0$
0#
0"
1!
$end
#5000
1-
#10000
0-
#15000
1-
#20000
0-
#25000
1-
#26000
1.
#30000
0-
#35000
1-
#40000
0-
#45000
1-
#46000
13
b1000 1
b1000 <
18
b1000 7
b1000 >
b111100 5
b111100 =
#50000
0-
#55000
b111 ?
0!
1#
b1000 L
b111100 M
1&
b111 I
b1000 H
1-
#56000
b10 :
1/
03
08
#60000
0-
#65000
1-
#70000
0-
#75000
1-
#80000
0-
#85000
1-
#90000
0-
#95000
1-
#100000
0-
#105000
1-
#110000
0-
#115000
1-
#120000
0-
#125000
1-
#130000
0-
#135000
1-
#136000
b1 :
0/
0+
#140000
0-
#145000
1-
#150000
0-
#155000
1-
#160000
0-
#165000
1-
#170000
0-
#175000
1-
#180000
0-
#185000
1-
#190000
0-
#195000
1-
#200000
0-
#205000
1-
#210000
0-
#215000
1-
#216000
b10 :
#220000
0-
#225000
1-
#230000
0-
#235000
1-
#240000
0-
#245000
1-
#250000
0-
#255000
1-
#260000
0-
#265000
1-
#270000
0-
#275000
1-
#280000
0-
#285000
1-
#290000
0-
#295000
1-
#296000
b11 :
#300000
0-
#305000
1-
#310000
0-
#315000
1-
#320000
0-
#325000
1-
#330000
0-
#335000
1-
#340000
0-
#345000
1-
#350000
0-
#355000
1-
#360000
0-
#365000
1-
#370000
0-
#375000
1-
#376000
b100 :
#380000
0-
#385000
1-
#390000
0-
#395000
1-
#400000
0-
#405000
1-
#410000
0-
#415000
1-
#420000
0-
#425000
1-
#430000
0-
#435000
1-
#440000
0-
#445000
1-
#450000
0-
#455000
1-
#456000
1/
1+
b1 :
#460000
0-
#465000
1-
#470000
0-
#475000
1-
#480000
0-
#485000
1-
#490000
0-
#495000
1-
#500000
0-
#505000
1-
#510000
0-
#515000
1-
#520000
0-
#525000
1-
#530000
0-
#535000
1-
#536000
b10 :
#540000
0-
#545000
1-
#550000
0-
#555000
1-
#560000
0-
#565000
1-
#570000
0-
#575000
1-
#580000
0-
#585000
1-
#590000
0-
#595000
1-
#600000
0-
#605000
1-
#610000
0-
#615000
1-
#616000
b11 :
#620000
0-
#625000
1-
#630000
0-
#635000
1-
#640000
0-
#645000
1-
#650000
0-
#655000
1-
#660000
0-
#665000
1-
#670000
0-
#675000
1-
#680000
0-
#685000
1-
#690000
0-
#695000
1-
#696000
b1 :
0/
0+
#700000
0-
#705000
1-
#710000
0-
#715000
1-
#720000
0-
#725000
1-
#730000
0-
#735000
1-
#740000
0-
#745000
1-
#750000
0-
#755000
1-
#760000
0-
#765000
1-
#770000
0-
#775000
1-
#776000
b10 :
#780000
0-
#785000
1-
#790000
0-
#795000
1-
#800000
0-
#805000
1-
#810000
0-
#815000
1-
#820000
0-
#825000
1-
#830000
0-
#835000
1-
#840000
0-
#845000
1-
#850000
0-
#855000
1-
#856000
b11 :
#860000
0-
#865000
1-
#870000
0-
#875000
1-
#880000
0-
#885000
1-
#890000
0-
#895000
1-
#900000
0-
#905000
1-
#910000
0-
#915000
1-
#920000
0-
#925000
1-
#930000
0-
#935000
1-
#936000
b1 :
1/
1+
#940000
0-
#945000
1-
#950000
0-
#955000
1-
#960000
0-
#965000
1-
#970000
0-
#975000
1-
#980000
0-
#985000
1-
#990000
0-
#995000
1-
#1000000
0-
#1005000
1-
#1010000
0-
#1015000
1-
#1016000
0/
0+
#1020000
0-
#1025000
1-
#1030000
0-
#1035000
1-
#1040000
0-
#1045000
1-
#1050000
0-
#1055000
1-
#1060000
0-
#1065000
1-
#1070000
0-
#1075000
1-
#1080000
0-
#1085000
1-
#1090000
0-
#1095000
1-
#1096000
1/
1+
#1100000
0-
#1105000
1-
#1110000
0-
#1115000
1-
#1120000
0-
#1125000
1-
#1130000
0-
#1135000
1-
#1140000
0-
#1145000
1-
#1150000
0-
#1155000
1-
#1160000
0-
#1165000
1-
#1170000
0-
#1175000
1-
#1176000
b10 :
#1180000
0-
#1185000
1-
#1190000
0-
#1195000
1-
#1200000
0-
#1205000
1-
#1210000
0-
#1215000
1-
#1220000
0-
#1225000
1-
#1230000
0-
#1235000
1-
#1240000
0-
#1245000
1-
#1250000
0-
#1255000
1-
#1256000
b1 :
0/
0+
#1260000
0-
#1265000
1-
#1270000
0-
#1275000
1-
#1280000
0-
#1285000
1-
#1290000
0-
#1295000
1-
#1300000
0-
#1305000
1-
#1310000
0-
#1315000
1-
#1320000
0-
#1325000
1-
#1330000
0-
#1335000
1-
#1336000
1/
1+
#1340000
0-
#1345000
1-
#1350000
0-
#1355000
1-
#1360000
0-
#1365000
1-
#1370000
0-
#1375000
1-
#1380000
0-
#1385000
1-
#1390000
0-
#1395000
1-
#1400000
0-
#1405000
1-
#1410000
0-
#1415000
1-
#1416000
0/
0+
#1420000
0-
#1425000
1-
#1430000
0-
#1435000
1-
#1440000
0-
#1445000
1-
#1450000
0-
#1455000
1-
#1460000
0-
#1465000
1-
#1470000
0-
#1475000
1-
#1480000
0-
#1485000
1-
#1490000
0-
#1495000
1-
#1496000
b10 :
b1 ;
00
#1500000
0-
#1505000
1-
#1510000
0-
#1515000
1-
#1520000
0-
#1525000
1-
#1530000
0-
#1535000
1-
#1540000
0-
#1545000
1-
#1550000
0-
#1555000
1-
#1560000
0-
#1565000
1-
#1570000
0-
#1575000
1-
#1576000
b11 :
#1580000
0-
#1585000
1-
#1590000
0-
#1595000
1-
#1600000
0-
#1605000
1-
#1610000
0-
#1615000
1-
#1620000
0-
#1625000
1-
#1630000
0-
#1635000
1-
#1640000
0-
#1645000
1-
#1650000
0-
#1655000
1-
#1656000
b1 :
1/
1+
#1660000
0-
#1665000
1-
#1670000
0-
#1675000
1-
#1680000
0-
#1685000
1-
#1690000
0-
#1695000
1-
#1700000
0-
#1705000
1-
#1710000
0-
#1715000
1-
#1720000
0-
#1725000
1-
#1730000
0-
#1735000
1-
#1736000
b10 :
#1740000
0-
#1745000
1-
#1750000
0-
#1755000
1-
#1760000
0-
#1765000
1-
#1770000
0-
#1775000
1-
#1780000
0-
#1785000
1-
#1790000
0-
#1795000
1-
#1800000
0-
#1805000
1-
#1810000
0-
#1815000
1-
#1816000
b11 :
#1820000
0-
#1825000
1-
#1830000
0-
#1835000
1-
#1840000
0-
#1845000
1-
#1850000
0-
#1855000
1-
#1860000
0-
#1865000
1-
#1870000
0-
#1875000
1-
#1880000
0-
#1885000
1-
#1890000
0-
#1895000
1-
#1896000
b100 :
#1900000
0-
#1905000
1-
#1910000
0-
#1915000
1-
#1920000
0-
#1925000
1-
#1930000
0-
#1935000
1-
#1940000
0-
#1945000
1-
#1950000
0-
#1955000
1-
#1960000
0-
#1965000
1-
#1970000
0-
#1975000
1-
#1976000
b1 :
0/
0+
#1980000
0-
#1985000
1-
#1990000
0-
#1995000
1-
#2000000
0-
#2005000
1-
#2010000
0-
#2015000
1-
#2020000
0-
#2025000
1-
#2030000
0-
#2035000
1-
#2040000
0-
#2045000
1-
#2050000
0-
#2055000
1-
#2056000
b10 :
#2060000
0-
#2065000
1-
#2070000
0-
#2075000
1-
#2080000
0-
#2085000
1-
#2090000
0-
#2095000
1-
#2100000
0-
#2105000
1-
#2110000
0-
#2115000
1-
#2120000
0-
#2125000
1-
#2130000
0-
#2135000
1-
#2136000
1*
#2140000
0-
#2145000
b110 ?
b110 I
b1 E
b1 K
1-
#2146000
1*
#2150000
0-
#2155000
1!
b101 ?
b10 K
b101 I
b10 E
1-
#2156000
12
1*
#2160000
0-
#2165000
b100 ?
b100 I
b11 E
b100000 J
b11 K
1-
#2166000
1*
#2170000
0-
#2175000
b11 ?
b100 K
b11 I
b100 E
b110000 J
1-
#2176000
1*
#2180000
0-
#2185000
b10 ?
b10 I
b101 E
b111000 J
b101 K
1-
#2186000
1*
#2190000
0-
#2195000
0!
b1 ?
b110 K
b1 I
b110 E
b111100 J
1-
#2196000
02
1*
#2200000
0-
#2205000
b0 ?
b0 I
b111 E
b111 K
1-
#2206000
1*
#2210000
0-
#2215000
1!
1"
0#
1G
0&
1-
#2216000
b1 :
1/
1+
0*
#2220000
0-
#2225000
16
b111100 %
b111100 F
1$
0G
0"
1-
#2230000
0-
#2235000
0$
14
1-
#2240000
0-
#2245000
1-
#2250000
0-
#2255000
1-
#2260000
0-
#2265000
1-
#2270000
0-
#2275000
1-
#2280000
0-
#2285000
1-
#2290000
0-
#2295000
1-
#2296000
0/
0+
#2300000
0-
#2305000
1-
#2310000
0-
#2315000
1-
#2320000
0-
#2325000
1-
#2330000
0-
#2335000
1-
#2340000
0-
#2345000
1-
#2350000
0-
#2355000
1-
#2360000
0-
#2365000
1-
#2370000
0-
#2375000
1-
#2376000
1/
1+
#2380000
0-
#2385000
1-
#2390000
0-
#2395000
1-
#2400000
0-
#2405000
1-
#2410000
0-
#2415000
1-
#2420000
0-
#2425000
1-
#2430000
0-
#2435000
1-
#2440000
0-
#2445000
1-
#2450000
0-
#2455000
1-
#2456000
b10 :
#2460000
0-
#2465000
1-
#2470000
0-
#2475000
1-
#2480000
0-
#2485000
1-
#2490000
0-
#2495000
1-
#2500000
0-
#2505000
1-
#2510000
0-
#2515000
1-
#2520000
0-
#2525000
1-
#2530000
0-
#2535000
1-
#2536000
b11 :
#2540000
0-
#2545000
1-
#2550000
0-
#2555000
1-
#2560000
0-
#2565000
1-
#2570000
0-
#2575000
1-
#2580000
0-
#2585000
1-
#2590000
0-
#2595000
1-
#2600000
0-
#2605000
1-
#2610000
0-
#2615000
1-
#2616000
b100 :
#2620000
0-
#2625000
1-
#2630000
0-
#2635000
1-
#2640000
0-
#2645000
1-
#2650000
0-
#2655000
1-
#2660000
0-
#2665000
1-
#2670000
0-
#2675000
1-
#2680000
0-
#2685000
1-
#2690000
0-
#2695000
1-
#2696000
b1 :
0/
0+
#2700000
0-
#2705000
1-
#2710000
0-
#2715000
1-
#2720000
0-
#2725000
1-
#2730000
0-
#2735000
1-
#2740000
0-
#2745000
1-
#2750000
0-
#2755000
1-
#2760000
0-
#2765000
1-
#2770000
0-
#2775000
1-
#2776000
1/
1+
#2780000
0-
#2785000
1-
#2790000
0-
#2795000
1-
#2800000
0-
#2805000
1-
#2810000
0-
#2815000
1-
#2820000
0-
#2825000
1-
#2830000
0-
#2835000
1-
#2840000
0-
#2845000
1-
#2850000
0-
#2855000
1-
#2856000
0/
0+
#2860000
0-
#2865000
1-
#2870000
0-
#2875000
1-
#2880000
0-
#2885000
1-
#2890000
0-
#2895000
1-
#2900000
0-
#2905000
1-
#2910000
0-
#2915000
1-
#2920000
0-
#2925000
1-
#2930000
0-
#2935000
1-
#2936000
1/
1+
#2940000
0-
#2945000
1-
#2950000
0-
#2955000
1-
#2960000
0-
#2965000
1-
#2970000
0-
#2975000
1-
#2980000
0-
#2985000
1-
#2990000
0-
#2995000
1-
#3000000
0-
#3005000
1-
#3010000
0-
#3015000
1-
#3016000
b10 :
#3020000
0-
#3025000
1-
#3030000
0-
#3035000
1-
#3040000
0-
#3045000
1-
#3050000
0-
#3055000
1-
#3060000
0-
#3065000
1-
#3070000
0-
#3075000
1-
#3080000
0-
#3085000
1-
#3090000
0-
#3095000
1-
#3096000
b11 :
#3100000
0-
#3105000
1-
#3110000
0-
#3115000
1-
#3120000
0-
#3125000
1-
#3130000
0-
#3135000
1-
#3140000
0-
#3145000
1-
#3150000
0-
#3155000
1-
#3160000
0-
#3165000
1-
#3170000
0-
#3175000
1-
#3176000
b1 :
0/
0+
#3180000
0-
#3185000
1-
#3190000
0-
#3195000
1-
#3200000
0-
#3205000
1-
#3210000
0-
#3215000
1-
#3220000
0-
#3225000
1-
#3230000
0-
#3235000
1-
#3240000
0-
#3245000
1-
#3250000
0-
#3255000
1-
#3256000
b10 :
#3260000
0-
#3265000
1-
#3270000
0-
#3275000
1-
#3280000
0-
#3285000
1-
#3290000
0-
#3295000
1-
#3300000
0-
#3305000
1-
#3310000
0-
#3315000
1-
#3320000
0-
#3325000
1-
#3330000
0-
#3335000
1-
#3336000
b11 :
#3340000
0-
#3345000
1-
#3350000
0-
#3355000
1-
#3360000
0-
#3365000
1-
#3370000
0-
#3375000
1-
#3380000
0-
#3385000
1-
#3390000
0-
#3395000
1-
#3400000
0-
#3405000
1-
#3410000
0-
#3415000
1-
#3416000
1+
#3420000
0-
#3425000
1-
#3430000
0-
#3435000
1-
#3440000
0-
#3445000
1-
#3450000
0-
#3455000
1-
#3460000
0-
#3465000
1-
#3470000
0-
#3475000
1-
#3480000
0-
#3485000
1-
#3490000
0-
#3495000
1-
#3496000
0+
#3500000
0-
#3505000
1-
#3510000
0-
#3515000
1-
#3520000
0-
#3525000
1-
#3530000
0-
#3535000
1-
#3540000
0-
#3545000
1-
#3550000
0-
#3555000
1-
#3560000
0-
#3565000
1-
#3570000
0-
#3575000
1-
#3576000
1+
